Workbook

Sheet Global 1 (1.5)
A1: Scenario 1: Cut extraction by 10% per year, $1 trillion climate grants
A2: Parameters | C2: Initial fossil fuel extraction cap (gigatonnes of CO2e) | D2: Initial carbon charge (per extracted tonne of CO2e) | F2: Running costs of Trust (% of charge money raised) | G2: Initial proportion of charge proceeds going into the Fund (% of total proceeds) | J2: Management costs of the Fund (% of total Fund capital expended) | K2: Assumed annual rate of return on Fund investments | N2: Year that money from distribution pot starts getting reinvested | O2: Distribution costs of the pot (% of total distributed) | P2: Amount of pot to be distributed as climate grants | R2: Initial global population expected in 2025 | S2: Proportion of global population to receive dividends
C3: 37.4 | D3: 144 | F3: 0.005 | G3: 0.05 | J3: 0.0005 | K3: 0.0634 | N3: 2075 | O3: 0.005 | P3: 1300000000000 | S3: 1
C4: Annual shrinkage of cap | D4: Annual growth of charge | G4: Initial annual increase in proportion going into the Fund (% of total proceeds) | H4: After 2035 annual increase in proportion going into the Fund (% of total proceeds) | I4: Starting endowment of the fund | N4: Maximum proportion that gets reinvested | P4: Alternatively, proportion of pot to be distributed as climate grants | S4: Description of segment of population to receive dividends
C5: 0.1 | D5: 0.164 | G5: 0.03 | H5: 0.03 | I5: 0 | N5: 0.1 | P5: 0 | S5: All adults and children worldwide
A7: From start | B7: Year | C7: Carbon cap (gigatonnes of CO2e) | D7: Carbon charge | E7: Amount raised | F7: Amount raised less 0.5% Trust costs | G7: Proportion of this amount going into the Fund | H7: Amount being placed in the Fund this year | I7: Total capital amount that would be in the Fund if there were no management costs | J7: Total capital amount in the Fund less cumulative 0.05% Fund management costs | K7: Investment income of the Fund this year | L7: Amount to be directly distributed (bypassing the Fund) | M7: Total amount in this year's pot for distribution | N7: Amount from distribution pot to go back into Fund for reinvestment | O7: Total distribution pot less 0.5% distribution costs, and less any amount going back to the Fund | P7: Amount to be distributed as climate grants | Q7: Amount left in pot after climate grants distribution | R7: Global population (projected for 1st January each year) | S7: Proportion of global population to receive dividends | T7: Monthly dividend per person
A9: Year 1 | B9: 2025 | C9: =C3 -> 37.4 | D9: =D3 -> 144 | E9: =D9*C9*1000000000 -> 5.3856e+12 | F9: =E9*(1-$F$3) -> 5.358672e+12 | G9: =G3 -> 0.05 | H9: =F9*G9 -> 2.679336e+11 | I9: =$I$5+H9 -> 2.679336e+11 | J9: =($I$5+H9*(1-$J$3)) -> 2.6779963e+11 | K9: =J8*$K$3 -> 0 | L9: =F9*(1-G9) -> 5.0907384e+12 | M9: =K9+L9 -> 5.0907384e+12 | O9: =(M9-N9)*(1-$O$3) -> 5.0652847e+12 | P9: =$P$3 -> 1300000000000 | Q9: =O9-P9 -> 3.7652847e+12 | R9: 8231613070 | S9: =$S$3 -> 1 | T9: =(Q9/(R9*S9))/12 -> 38.118133
A10: Year 2 | B10: 2026 | C10: =C9*(1-$C$5) -> 33.66 | D10: =D9*(1+$D$5) -> 167.616 | E10: =D10*C10*1000000000 -> 5.6419546e+12 | F10: =E10*(1-$F$3) -> 5.6137448e+12 | G10: =$G$3+$G$5 -> 0.08 | H10: =F10*G10 -> 4.4909958e+11 | I10: =I9+H10 -> 7.1703318e+11 | J10: =(J9+H10)*(1-$J$3) -> 7.1654077e+11 | K10: =J9*$K$3 -> 1.6978497e+10 | L10: =F10*(1-G10) -> 5.1646452e+12 | M10: =K10+L10 -> 5.1816237e+12 | O10: =(M10-N10)*(1-$O$3) -> 5.1557156e+12 | P10: =$P$3 -> 1300000000000 | Q10: =O10-P10 -> 3.8557156e+12 | R10: 8300678395 | S10: =$S$3 -> 1 | T10: =(Q10/(R10*S10))/12 -> 38.70884
A11: Year 3 | B11: 2027 | C11: =C10*(1-$C$5) -> 30.294 | D11: =D10*(1+$D$5) -> 195.10502 | E11: =D11*C11*1000000000 -> 5.9105116e+12 | F11: =E11*(1-$F$3) -> 5.880959e+12 | G11: =G10+$G$5 -> 0.11 | H11: =F11*G11 -> 6.4690549e+11 | I11: =I10+H11 -> 1.3639387e+12 | J11: =(J10+H11)*(1-$J$3) -> 1.3627645e+12 | K11: =J10*$K$3 -> 4.5428685e+10 | L11: =F11*(1-G11) -> 5.2340535e+12 | M11: =K11+L11 -> 5.2794822e+12 | O11: =(M11-N11)*(1-$O$3) -> 5.2530848e+12 | P11: =$P$3 -> 1300000000000 | Q11: =O11-P11 -> 3.9530848e+12 | R11: 8369094344 | S11: =$S$3 -> 1 | T11: =(Q11/(R11*S11))/12 -> 39.361933
A12: Year 4 | B12: 2028 | C12: =C11*(1-$C$5) -> 27.2646 | D12: =D11*(1+$D$5) -> 227.10225 | E12: =D12*C12*1000000000 -> 6.1918519e+12 | F12: =E12*(1-$F$3) -> 6.1608927e+12 | G12: =G11+$G$5 -> 0.14 | H12: =F12*G12 -> 8.6252498e+11 | I12: =I11+H12 -> 2.2264637e+12 | J12: =(J11+H12)*(1-$J$3) -> 2.2241769e+12 | K12: =J11*$K$3 -> 8.6399272e+10 | L12: =F12*(1-G12) -> 5.2983677e+12 | M12: =K12+L12 -> 5.384767e+12 | O12: =(M12-N12)*(1-$O$3) -> 5.3578431e+12 | P12: =$P$3 -> 1300000000000 | Q12: =O12-P12 -> 4.0578431e+12 | R12: 8436618886 | S12: =$S$3 -> 1 | T12: =(Q12/(R12*S12))/12 -> 40.081649
A13: Year 5 | B13: 2029 | C13: =C12*(1-$C$5) -> 24.53814 | D13: =D12*(1+$D$5) -> 264.34702 | E13: =D13*C13*1000000000 -> 6.4865841e+12 | F13: =E13*(1-$F$3) -> 6.4541512e+12 | G13: =G12+$G$5 -> 0.17 | H13: =F13*G13 -> 1.0972057e+12 | I13: =I12+H13 -> 3.3236694e+12 | J13: =(J12+H13)*(1-$J$3) -> 3.3197219e+12 | K13: =J12*$K$3 -> 1.4101281e+11 | L13: =F13*(1-G13) -> 5.3569455e+12 | M13: =K13+L13 -> 5.4979583e+12 | O13: =(M13-N13)*(1-$O$3) -> 5.4704685e+12 | P13: =$P$3 -> 1300000000000 | Q13: =O13-P13 -> 4.1704685e+12 | R13: 8503285323 | S13: =$S$3 -> 1 | T13: =(Q13/(R13*S13))/12 -> 40.871149
A14: Year 6 | B14: 2030 | C14: =C13*(1-$C$5) -> 22.084326 | D14: =D13*(1+$D$5) -> 307.69993 | E14: =D14*C14*1000000000 -> 6.7953455e+12 | F14: =E14*(1-$F$3) -> 6.7613688e+12 | G14: =G13+$G$5 -> 0.2 | H14: =F14*G14 -> 1.3522738e+12 | I14: =I13+H14 -> 4.6759431e+12 | J14: =(J13+H14)*(1-$J$3) -> 4.6696596e+12 | K14: =J13*$K$3 -> 2.1047037e+11 | L14: =F14*(1-G14) -> 5.409095e+12 | M14: =K14+L14 -> 5.6195654e+12 | O14: =(M14-N14)*(1-$O$3) -> 5.5914676e+12 | P14: =$P$3 -> 1300000000000 | Q14: =O14-P14 -> 4.2914676e+12 | R14: 8569124911 | S14: =$S$3 -> 1 | T14: =(Q14/(R14*S14))/12 -> 41.733818
A15: Year 7 | B15: 2031 | C15: =C14*(1-$C$5) -> 19.875893 | D15: =D14*(1+$D$5) -> 358.16272 | E15: =D15*C15*1000000000 -> 7.118804e+12 | F15: =E15*(1-$F$3) -> 7.0832099e+12 | G15: =G14+$G$5 -> 0.23 | H15: =F15*G15 -> 1.6291383e+12 | I15: =I14+H15 -> 6.3050814e+12 | J15: =(J14+H15)*(1-$J$3) -> 6.2956485e+12 | K15: =J14*$K$3 -> 2.9605642e+11 | L15: =F15*(1-G15) -> 5.4540716e+12 | M15: =K15+L15 -> 5.7501281e+12 | O15: =(M15-N15)*(1-$O$3) -> 5.7213774e+12 | P15: =$P$3 -> 1300000000000 | Q15: =O15-P15 -> 4.4213774e+12 | R15: 8634119333 | S15: =$S$3 -> 1 | T15: =(Q15/(R15*S15))/12 -> 42.673503
A16: Year 8 | B16: 2032 | C16: =C15*(1-$C$5) -> 17.888304 | D16: =D15*(1+$D$5) -> 416.9014 | E16: =D16*C16*1000000000 -> 7.457659e+12 | F16: =E16*(1-$F$3) -> 7.4203707e+12 | G16: =G15+$G$5 -> 0.26 | H16: =F16*G16 -> 1.9292964e+12 | I16: =I15+H16 -> 8.2343778e+12 | J16: =(J15+H16)*(1-$J$3) -> 8.2208324e+12 | K16: =J15*$K$3 -> 3.9914412e+11 | L16: =F16*(1-G16) -> 5.4910743e+12 | M16: =K16+L16 -> 5.8902185e+12 | O16: =(M16-N16)*(1-$O$3) -> 5.8607674e+12 | P16: =$P$3 -> 1300000000000 | Q16: =O16-P16 -> 4.5607674e+12 | R16: 8698229812 | S16: =$S$3 -> 1 | T16: =(Q16/(R16*S16))/12 -> 43.694402
A17: Year 9 | B17: 2033 | C17: =C16*(1-$C$5) -> 16.099474 | D17: =D16*(1+$D$5) -> 485.27323 | E17: =D17*C17*1000000000 -> 7.8126436e+12 | F17: =E17*(1-$F$3) -> 7.7735804e+12 | G17: =G16+$G$5 -> 0.29 | H17: =F17*G17 -> 2.2543383e+12 | I17: =I16+H17 -> 1.0488716e+13 | J17: =(J16+H17)*(1-$J$3) -> 1.0469933e+13 | K17: =J16*$K$3 -> 5.2120078e+11 | L17: =F17*(1-G17) -> 5.5192421e+12 | M17: =K17+L17 -> 6.0404428e+12 | O17: =(M17-N17)*(1-$O$3) -> 6.0102406e+12 | P17: =$P$3 -> 1300000000000 | Q17: =O17-P17 -> 4.7102406e+12 | R17: 8761449081 | S17: =$S$3 -> 1 | T17: =(Q17/(R17*S17))/12 -> 44.800814
A18: Year 10 | B18: 2034 | C18: =C17*(1-$C$5) -> 14.489526 | D18: =D17*(1+$D$5) -> 564.85804 | E18: =D18*C18*1000000000 -> 8.1845254e+12 | F18: =E18*(1-$F$3) -> 8.1436028e+12 | G18: =G17+$G$5 -> 0.32 | H18: =F18*G18 -> 2.6059529e+12 | I18: =I17+H18 -> 1.3094669e+13 | J18: =(J17+H18)*(1-$J$3) -> 1.3069348e+13 | K18: =J17*$K$3 -> 6.6379376e+11 | L18: =F18*(1-G18) -> 5.5376499e+12 | M18: =K18+L18 -> 6.2014437e+12 | O18: =(M18-N18)*(1-$O$3) -> 6.1704364e+12 | P18: =$P$3 -> 1300000000000 | Q18: =O18-P18 -> 4.8704364e+12 | R18: 8823784909 | S18: =$S$3 -> 1 | T18: =(Q18/(R18*S18))/12 -> 45.997235
A19: Year 11 | B19: 2035 | C19: =C18*(1-$C$5) -> 13.040574 | D19: =D18*(1+$D$5) -> 657.49476 | E19: =D19*C19*1000000000 -> 8.5741088e+12 | F19: =E19*(1-$F$3) -> 8.5312383e+12 | G19: =G18+$G$5 -> 0.35 | H19: =F19*G19 -> 2.9859334e+12 | I19: =I18+H19 -> 1.6080602e+13 | J19: =(J18+H19)*(1-$J$3) -> 1.6047254e+13 | K19: =J18*$K$3 -> 8.2859667e+11 | L19: =F19*(1-G19) -> 5.5453049e+12 | M19: =K19+L19 -> 6.3739016e+12 | O19: =(M19-N19)*(1-$O$3) -> 6.3420321e+12 | P19: =$P$3 -> 1300000000000 | Q19: =O19-P19 -> 5.0420321e+12 | R19: 8885210181 | S19: =$S$3 -> 1 | T19: =(Q19/(R19*S19))/12 -> 47.288621
A20: Year 12 | B20: 2036 | C20: =C19*(1-$C$5) -> 11.736516 | D20: =D19*(1+$D$5) -> 765.3239 | E20: =D20*C20*1000000000 -> 8.9822364e+12 | F20: =E20*(1-$F$3) -> 8.9373252e+12 | G20: =G19+$H$5 -> 0.38 | H20: =F20*G20 -> 3.3961836e+12 | I20: =I19+H20 -> 1.9476786e+13 | J20: =(J19+H20)*(1-$J$3) -> 1.9433716e+13 | K20: =J19*$K$3 -> 1.0173959e+12 | L20: =F20*(1-G20) -> 5.5411416e+12 | M20: =K20+L20 -> 6.5585375e+12 | O20: =(M20-N20)*(1-$O$3) -> 6.5257449e+12 | P20: =$P$3 -> 1300000000000 | Q20: =O20-P20 -> 5.2257449e+12 | R20: 8945686614 | S20: =$S$3 -> 1 | T20: =(Q20/(R20*S20))/12 -> 48.680303
A21: Year 13 | B21: 2037 | C21: =C20*(1-$C$5) -> 10.562865 | D21: =D20*(1+$D$5) -> 890.83702 | E21: =D21*C21*1000000000 -> 9.4097909e+12 | F21: =E21*(1-$F$3) -> 9.3627419e+12 | G21: =G20+$H$5 -> 0.41 | H21: =F21*G21 -> 3.8387242e+12 | I21: =I20+H21 -> 2.331551e+13 | J21: =(J20+H21)*(1-$J$3) -> 2.3260804e+13 | K21: =J20*$K$3 -> 1.2320976e+12 | L21: =F21*(1-G21) -> 5.5240177e+12 | M21: =K21+L21 -> 6.7561153e+12 | O21: =(M21-N21)*(1-$O$3) -> 6.7223347e+12 | P21: =$P$3 -> 1300000000000 | Q21: =O21-P21 -> 5.4223347e+12 | R21: 9005152624 | S21: =$S$3 -> 1 | T21: =(Q21/(R21*S21))/12 -> 50.178075
A22: Year 14 | B22: 2038 | C22: =C21*(1-$C$5) -> 9.5065782 | D22: =D21*(1+$D$5) -> 1036.9343 | E22: =D22*C22*1000000000 -> 9.8576969e+12 | F22: =E22*(1-$F$3) -> 9.8084084e+12 | G22: =G21+$H$5 -> 0.44 | H22: =F22*G22 -> 4.3156997e+12 | I22: =I21+H22 -> 2.763121e+13 | J22: =(J21+H22)*(1-$J$3) -> 2.7562715e+13 | K22: =J21*$K$3 -> 1.474735e+12 | L22: =F22*(1-G22) -> 5.4927087e+12 | M22: =K22+L22 -> 6.9674437e+12 | O22: =(M22-N22)*(1-$O$3) -> 6.9326065e+12 | P22: =$P$3 -> 1300000000000 | Q22: =O22-P22 -> 5.6326065e+12 | R22: 9063572926 | S22: =$S$3 -> 1 | T22: =(Q22/(R22*S22))/12 -> 51.787951
A23: Year 15 | B23: 2039 | C23: =C22*(1-$C$5) -> 8.5559204 | D23: =D22*(1+$D$5) -> 1206.9915 | E23: =D23*C23*1000000000 -> 1.0326923e+13 | F23: =E23*(1-$F$3) -> 1.0275289e+13 | G23: =G22+$H$5 -> 0.47 | H23: =F23*G23 -> 4.8293857e+12 | I23: =I22+H23 -> 3.2460596e+13 | J23: =(J22+H23)*(1-$J$3) -> 3.2375905e+13 | K23: =J22*$K$3 -> 1.7474761e+12 | L23: =F23*(1-G23) -> 5.445903e+12 | M23: =K23+L23 -> 7.1933791e+12 | O23: =(M23-N23)*(1-$O$3) -> 7.1574122e+12 | P23: =$P$3 -> 1300000000000 | Q23: =O23-P23 -> 5.8574122e+12 | R23: 9120928380 | S23: =$S$3 -> 1 | T23: =(Q23/(R23*S23))/12 -> 53.516228
A24: Year 16 | B24: 2040 | C24: =C23*(1-$C$5) -> 7.7003283 | D24: =D23*(1+$D$5) -> 1404.9381 | E24: =D24*C24*1000000000 -> 1.0818485e+13 | F24: =E24*(1-$F$3) -> 1.0764392e+13 | G24: =G23+$H$5 -> 0.5 | H24: =F24*G24 -> 5.3821962e+12 | I24: =I23+H24 -> 3.7842792e+13 | J24: =(J23+H24)*(1-$J$3) -> 3.7739222e+13 | K24: =J23*$K$3 -> 2.0526324e+12 | L24: =F24*(1-G24) -> 5.3821962e+12 | M24: =K24+L24 -> 7.4348286e+12 | O24: =(M24-N24)*(1-$O$3) -> 7.3976544e+12 | P24: =$P$3 -> 1300000000000 | Q24: =O24-P24 -> 6.0976544e+12 | R24: 9177190203 | S24: =$S$3 -> 1 | T24: =(Q24/(R24*S24))/12 -> 55.369656
A25: Year 17 | B25: 2041 | C25: =C24*(1-$C$5) -> 6.9302955 | D25: =D24*(1+$D$5) -> 1635.348 | E25: =D25*C25*1000000000 -> 1.1333445e+13 | F25: =E25*(1-$F$3) -> 1.1276777e+13 | G25: =G24+$H$5 -> 0.53 | H25: =F25*G25 -> 5.9766921e+12 | I25: =I24+H25 -> 4.3819484e+13 | J25: =(J24+H25)*(1-$J$3) -> 4.3694056e+13 | K25: =J24*$K$3 -> 2.3926667e+12 | L25: =F25*(1-G25) -> 5.3000854e+12 | M25: =K25+L25 -> 7.6927521e+12 | O25: =(M25-N25)*(1-$O$3) -> 7.6542883e+12 | P25: =$P$3 -> 1300000000000 | Q25: =O25-P25 -> 6.3542883e+12 | R25: 9232281575 | S25: =$S$3 -> 1 | T25: =(Q25/(R25*S25))/12 -> 57.355706
A26: Year 18 | B26: 2042 | C26: =C25*(1-$C$5) -> 6.237266 | D26: =D25*(1+$D$5) -> 1903.545 | E26: =D26*C26*1000000000 -> 1.1872917e+13 | F26: =E26*(1-$F$3) -> 1.1813552e+13 | G26: =G25+$H$5 -> 0.56 | H26: =F26*G26 -> 6.6155892e+12 | I26: =I25+H26 -> 5.0435073e+13 | J26: =(J25+H26)*(1-$J$3) -> 5.028449e+13 | K26: =J25*$K$3 -> 2.7702032e+12 | L26: =F26*(1-G26) -> 5.1979629e+12 | M26: =K26+L26 -> 7.9681661e+12 | O26: =(M26-N26)*(1-$O$3) -> 7.9283252e+12 | P26: =$P$3 -> 1300000000000 | Q26: =O26-P26 -> 6.6283252e+12 | R26: 9286110371 | S26: =$S$3 -> 1 | T26: =(Q26/(R26*S26))/12 -> 59.482433
A27: Year 19 | B27: 2043 | C27: =C26*(1-$C$5) -> 5.6135394 | D27: =D26*(1+$D$5) -> 2215.7264 | E27: =D27*C27*1000000000 -> 1.2438068e+13 | F27: =E27*(1-$F$3) -> 1.2375877e+13 | G27: =G26+$H$5 -> 0.59 | H27: =F27*G27 -> 7.3017675e+12 | I27: =I26+H27 -> 5.7736841e+13 | J27: =(J26+H27)*(1-$J$3) -> 5.7557465e+13 | K27: =J26*$K$3 -> 3.1880367e+12 | L27: =F27*(1-G27) -> 5.0741096e+12 | M27: =K27+L27 -> 8.2621463e+12 | O27: =(M27-N27)*(1-$O$3) -> 8.2208356e+12 | P27: =$P$3 -> 1300000000000 | Q27: =O27-P27 -> 6.9208356e+12 | R27: 9338661314 | S27: =$S$3 -> 1 | T27: =(Q27/(R27*S27))/12 -> 61.75792
A28: Year 20 | B28: 2044 | C28: =C27*(1-$C$5) -> 5.0521854 | D28: =D27*(1+$D$5) -> 2579.1056 | E28: =D28*C28*1000000000 -> 1.303012e+13 | F28: =E28*(1-$F$3) -> 1.2964969e+13 | G28: =G27+$H$5 -> 0.62 | H28: =F28*G28 -> 8.0382807e+12 | I28: =I27+H28 -> 6.5775121e+13 | J28: =(J27+H28)*(1-$J$3) -> 6.5562948e+13 | K28: =J27*$K$3 -> 3.6491433e+12 | L28: =F28*(1-G28) -> 4.9266882e+12 | M28: =K28+L28 -> 8.5758315e+12 | O28: =(M28-N28)*(1-$O$3) -> 8.5329523e+12 | P28: =$P$3 -> 1300000000000 | Q28: =O28-P28 -> 7.2329523e+12 | R28: 9389873693 | S28: =$S$3 -> 1 | T28: =(Q28/(R28*S28))/12 -> 64.191068
A29: Year 21 | B29: 2045 | C29: =C28*(1-$C$5) -> 4.5469669 | D29: 3000 | E29: =D29*C29*1000000000 -> 1.3640901e+13 | F29: =E29*(1-$F$3) -> 1.3572696e+13 | G29: =G28+$H$5 -> 0.65 | H29: =F29*G29 -> 8.8222525e+12 | I29: =I28+H29 -> 7.4597374e+13 | J29: =(J28+H29)*(1-$J$3) -> 7.4348008e+13 | K29: =J28*$K$3 -> 4.1566909e+12 | L29: =F29*(1-G29) -> 4.7504436e+12 | M29: =K29+L29 -> 8.9071345e+12 | O29: =(M29-N29)*(1-$O$3) -> 8.8625989e+12 | P29: =$P$3 -> 1300000000000 | Q29: =O29-P29 -> 7.5625989e+12 | R29: 9439639668 | S29: =$S$3 -> 1 | T29: =(Q29/(R29*S29))/12 -> 66.762778
A30: Year 22 | B30: 2046 | C30: =C29*(1-$C$5) -> 4.0922702 | D30: =D29*(1+$D$5) -> 3492 | E30: =D30*C30*1000000000 -> 1.4290208e+13 | F30: =E30*(1-$F$3) -> 1.4218756e+13 | G30: =G29+$H$5 -> 0.68 | H30: =F30*G30 -> 9.6687544e+12 | I30: =I29+H30 -> 8.4266128e+13 | J30: =(J29+H30)*(1-$J$3) -> 8.3974754e+13 | K30: =J29*$K$3 -> 4.7136637e+12 | L30: =F30*(1-G30) -> 4.5500021e+12 | M30: =K30+L30 -> 9.2636658e+12 | O30: =(M30-N30)*(1-$O$3) -> 9.2173474e+12 | P30: =$P$3 -> 1300000000000 | Q30: =O30-P30 -> 7.9173474e+12 | R30: 9487889604 | S30: =$S$3 -> 1 | T30: =(Q30/(R30*S30))/12 -> 69.539063
A31: Year 23 | B31: 2047 | C31: =C30*(1-$C$5) -> 3.6830432 | D31: 4000 | E31: =D31*C31*1000000000 -> 1.4732173e+13 | F31: =E31*(1-$F$3) -> 1.4658512e+13 | G31: =G30+$H$5 -> 0.71 | H31: =F31*G31 -> 1.0407543e+13 | I31: =I30+H31 -> 9.4673672e+13 | J31: =(J30+H31)*(1-$J$3) -> 9.4335106e+13 | K31: =J30*$K$3 -> 5.3239994e+12 | L31: =F31*(1-G31) -> 4.2509684e+12 | M31: =K31+L31 -> 9.5749678e+12 | O31: =(M31-N31)*(1-$O$3) -> 9.527093e+12 | P31: =$P$3 -> 1300000000000 | Q31: =O31-P31 -> 8.227093e+12 | R31: 9534545977 | S31: =$S$3 -> 1 | T31: =(Q31/(R31*S31))/12 -> 71.906002
A32: Year 24 | B32: 2048 | C32: =C31*(1-$C$5) -> 3.3147389 | D32: 4000 | E32: =D32*C32*1000000000 -> 1.3258955e+13 | F32: =E32*(1-$F$3) -> 1.3192661e+13 | G32: =G31+$H$5 -> 0.74 | H32: =F32*G32 -> 9.7625689e+12 | I32: =I31+H32 -> 1.0443624e+14 | J32: =(J31+H32)*(1-$J$3) -> 1.0404563e+14 | K32: =J31*$K$3 -> 5.9808457e+12 | L32: =F32*(1-G32) -> 3.4300918e+12 | M32: =K32+L32 -> 9.4109375e+12 | O32: =(M32-N32)*(1-$O$3) -> 9.3638828e+12 | P32: =$P$3 -> 1300000000000 | Q32: =O32-P32 -> 8.0638828e+12 | R32: 9579536043 | S32: =$S$3 -> 1 | T32: =(Q32/(R32*S32))/12 -> 70.148516
A33: Year 25 | B33: 2049 | C33: =C32*(1-$C$5) -> 2.983265 | D33: 4000 | E33: =D33*C33*1000000000 -> 1.193306e+13 | F33: =E33*(1-$F$3) -> 1.1873395e+13 | G33: =G32+$H$5 -> 0.77 | H33: =F33*G33 -> 9.1425138e+12 | I33: =I32+H33 -> 1.1357875e+14 | J33: =(J32+H33)*(1-$J$3) -> 1.1313155e+14 | K33: =J32*$K$3 -> 6.5964927e+12 | L33: =F33*(1-G33) -> 2.7308808e+12 | M33: =K33+L33 -> 9.3273734e+12 | O33: =(M33-N33)*(1-$O$3) -> 9.2807366e+12 | P33: =$P$3 -> 1300000000000 | Q33: =O33-P33 -> 7.9807366e+12 | R33: 9622824029 | S33: =$S$3 -> 1 | T33: =(Q33/(R33*S33))/12 -> 69.112911
A34: Year 26 | B34: 2050 | C34: =C33*(1-$C$5) -> 2.6849385 | D34: 4000 | E34: =D34*C34*1000000000 -> 1.0739754e+13 | F34: =E34*(1-$F$3) -> 1.0686055e+13 | G34: =G33+$H$5 -> 0.8 | H34: =F34*G34 -> 8.5488441e+12 | I34: =I33+H34 -> 1.221276e+14 | J34: =(J33+H34)*(1-$J$3) -> 1.2161955e+14 | K34: =J33*$K$3 -> 7.17254e+12 | L34: =F34*(1-G34) -> 2.137211e+12 | M34: =K34+L34 -> 9.309751e+12 | O34: =(M34-N34)*(1-$O$3) -> 9.2632023e+12 | P34: =$P$3 -> 1300000000000 | Q34: =O34-P34 -> 7.9632023e+12 | R34: 9664378587 | S34: =$S$3 -> 1 | T34: =(Q34/(R34*S34))/12 -> 68.664548
A35: Year 27 | B35: 2051 | C35: =C34*(1-$C$5) -> 2.4164446 | D35: 4000 | E35: =D35*C35*1000000000 -> 9.6657785e+12 | F35: =E35*(1-$F$3) -> 9.6174496e+12 | G35: =G34+$H$5 -> 0.83 | H35: =F35*G35 -> 7.9824832e+12 | I35: =I34+H35 -> 1.3011008e+14 | J35: =(J34+H35)*(1-$J$3) -> 1.2953723e+14 | K35: =J34*$K$3 -> 7.7106794e+12 | L35: =F35*(1-G35) -> 1.6349664e+12 | M35: =K35+L35 -> 9.3456459e+12 | O35: =(M35-N35)*(1-$O$3) -> 9.2989176e+12 | P35: =$P$3 -> 1300000000000 | Q35: =O35-P35 -> 7.9989176e+12 | R35: 9704192304 | S35: =$S$3 -> 1 | T35: =(Q35/(R35*S35))/12 -> 68.689536
A36: Year 28 | B36: 2052 | C36: =C35*(1-$C$5) -> 2.1748002 | D36: 4000 | E36: =D36*C36*1000000000 -> 8.6992007e+12 | F36: =E36*(1-$F$3) -> 8.6557047e+12 | G36: =G35+$H$5 -> 0.86 | H36: =F36*G36 -> 7.443906e+12 | I36: =I35+H36 -> 1.3755399e+14 | J36: =(J35+H36)*(1-$J$3) -> 1.3691265e+14 | K36: =J35*$K$3 -> 8.2126605e+12 | L36: =F36*(1-G36) -> 1.2117987e+12 | M36: =K36+L36 -> 9.4244591e+12 | O36: =(M36-N36)*(1-$O$3) -> 9.3773368e+12 | P36: =$P$3 -> 1300000000000 | Q36: =O36-P36 -> 8.0773368e+12 | R36: 9742264515 | S36: =$S$3 -> 1 | T36: =(Q36/(R36*S36))/12 -> 69.091883
A37: Year 29 | B37: 2053 | C37: =C36*(1-$C$5) -> 1.9573201 | D37: 4000 | E37: =D37*C37*1000000000 -> 7.8292806e+12 | F37: =E37*(1-$F$3) -> 7.7901342e+12 | G37: =G36+$H$5 -> 0.89 | H37: =F37*G37 -> 6.9332194e+12 | I37: =I36+H37 -> 1.4448721e+14 | J37: =(J36+H37)*(1-$J$3) -> 1.4377394e+14 | K37: =J36*$K$3 -> 8.6802618e+12 | L37: =F37*(1-G37) -> 8.5691476e+11 | M37: =K37+L37 -> 9.5371766e+12 | O37: =(M37-N37)*(1-$O$3) -> 9.4894907e+12 | P37: =$P$3 -> 1300000000000 | Q37: =O37-P37 -> 8.1894907e+12 | R37: 9778614614 | S37: =$S$3 -> 1 | T37: =(Q37/(R37*S37))/12 -> 69.790823
A38: Year 30 | B38: 2054 | C38: =C37*(1-$C$5) -> 1.7615881 | D38: 4000 | E38: =D38*C38*1000000000 -> 7.0463525e+12 | F38: =E38*(1-$F$3) -> 7.0111208e+12 | G38: =G37+$H$5 -> 0.92 | H38: =F38*G38 -> 6.4502311e+12 | I38: =I37+H38 -> 1.5093744e+14 | J38: =(J37+H38)*(1-$J$3) -> 1.5014906e+14 | K38: =J37*$K$3 -> 9.115268e+12 | L38: =F38*(1-G38) -> 5.6088966e+11 | M38: =K38+L38 -> 9.6761577e+12 | O38: =(M38-N38)*(1-$O$3) -> 9.6277769e+12 | P38: =$P$3 -> 1300000000000 | Q38: =O38-P38 -> 8.3277769e+12 | R38: 9813251659 | S38: =$S$3 -> 1 | T38: =(Q38/(R38*S38))/12 -> 70.718803
A39: Year 31 | B39: 2055 | C39: =C38*(1-$C$5) -> 1.5854293 | D39: 4000 | E39: =D39*C39*1000000000 -> 6.3417173e+12 | F39: =E39*(1-$F$3) -> 6.3100087e+12 | G39: =G38+$H$5 -> 0.95 | H39: =F39*G39 -> 5.9945083e+12 | I39: =I38+H39 -> 1.5693195e+14 | J39: =(J38+H39)*(1-$J$3) -> 1.560655e+14 | K39: =J38*$K$3 -> 9.5194506e+12 | L39: =F39*(1-G39) -> 3.1550043e+11 | M39: =K39+L39 -> 9.834951e+12 | O39: =(M39-N39)*(1-$O$3) -> 9.7857763e+12 | P39: =$P$3 -> 1300000000000 | Q39: =O39-P39 -> 8.4857763e+12 | R39: 9846237570 | S39: =$S$3 -> 1 | T39: =(Q39/(R39*S39))/12 -> 71.81911
A40: Year 32 | B40: 2056 | C40: =C39*(1-$C$5) -> 1.4268864 | D40: 4000 | E40: =D40*C40*1000000000 -> 5.7075456e+12 | F40: =E40*(1-$F$3) -> 5.6790078e+12 | G40: =G39+$H$5 -> 0.98 | H40: =F40*G40 -> 5.5654277e+12 | I40: =I39+H40 -> 1.6249737e+14 | J40: =(J39+H40)*(1-$J$3) -> 1.6155011e+14 | K40: =J39*$K$3 -> 9.8945526e+12 | L40: =F40*(1-G40) -> 1.1358016e+11 | M40: =K40+L40 -> 1.0008133e+13 | O40: =(M40-N40)*(1-$O$3) -> 9.9580921e+12 | P40: =$P$3 -> 1300000000000 | Q40: =O40-P40 -> 8.6580921e+12 | R40: 9877680392 | S40: =$S$3 -> 1 | T40: =(Q40/(R40*S40))/12 -> 73.044242
A41: Year 33 | B41: 2057 | C41: =C40*(1-$C$5) -> 1.2841977 | D41: 4000 | E41: =D41*C41*1000000000 -> 5.136791e+12 | F41: =E41*(1-$F$3) -> 5.111107e+12 | G41: 1 | H41: =F41*G41 -> 5.111107e+12 | I41: =I40+H41 -> 1.6760848e+14 | J41: =(J40+H41)*(1-$J$3) -> 1.6657789e+14 | K41: =J40*$K$3 -> 1.0242277e+13 | L41: =F41*(1-G41) -> 0 | M41: =K41+L41 -> 1.0242277e+13 | N41: =M41*0.2% -> 2.0484554e+10 | O41: =(M41-N41)*(1-$O$3) -> 1.0170684e+13 | P41: =$P$3 -> 1300000000000 | Q41: =O41-P41 -> 8.8706835e+12 | R41: 9907637193 | S41: =$S$3 -> 1 | T41: =(Q41/(R41*S41))/12 -> 74.611496
A42: Year 34 | B42: 2058 | C42: =C41*(1-$C$5) -> 1.155778 | D42: 4000 | E42: =D42*C42*1000000000 -> 4.6231119e+12 | F42: =E42*(1-$F$3) -> 4.5999963e+12 | G42: 1 | H42: =F42*G42 -> 4.5999963e+12 | I42: =I41+H42 -> 1.7220848e+14 | J42: =(J41+H42)*(1-$J$3) -> 1.710923e+14 | K42: =J41*$K$3 -> 1.0561038e+13 | L42: =F42*(1-G42) -> 0 | M42: =K42+L42 -> 1.0561038e+13 | N42: =M42*0.4% -> 4.2244152e+10 | O42: =(M42-N42)*(1-$O$3) -> 1.04662e+13 | P42: =$P$3 -> 1300000000000 | Q42: =O42-P42 -> 9.1662e+12 | R42: 9936164379 | S42: =$S$3 -> 1 | T42: =(Q42/(R42*S42))/12 -> 76.875741
A43: Year 35 | B43: 2059 | C43: =C42*(1-$C$5) -> 1.0402002 | D43: 4000 | E43: =D43*C43*1000000000 -> 4.1608007e+12 | F43: =E43*(1-$F$3) -> 4.1399967e+12 | G43: 1 | H43: =F43*G43 -> 4.1399967e+12 | I43: =I42+H43 -> 1.7634847e+14 | J43: =(J42+H43)*(1-$J$3) -> 1.7514468e+14 | K43: =J42*$K$3 -> 1.0847252e+13 | L43: =F43*(1-G43) -> 0 | M43: =K43+L43 -> 1.0847252e+13 | N43: =M43*0.6% -> 6.5083509e+10 | O43: =(M43-N43)*(1-$O$3) -> 1.0728257e+13 | P43: =$P$3 -> 1300000000000 | Q43: =O43-P43 -> 9.4282572e+12 | R43: 9963337082 | S43: =$S$3 -> 1 | T43: =(Q43/(R43*S43))/12 -> 78.857926
A44: Year 36 | B44: 2060 | C44: =C43*(1-$C$5) -> 0.93618016 | D44: 4000 | E44: =D44*C44*1000000000 -> 3.7447206e+12 | F44: =E44*(1-$F$3) -> 3.725997e+12 | G44: 1 | H44: =F44*G44 -> 3.725997e+12 | I44: =I43+H44 -> 1.8007447e+14 | J44: =(J43+H44)*(1-$J$3) -> 1.7878124e+14 | K44: =J43*$K$3 -> 1.1104172e+13 | L44: =F44*(1-G44) -> 0 | M44: =K44+L44 -> 1.1104172e+13 | N44: =M44*0.8% -> 8.883338e+10 | O44: =(M44-N44)*(1-$O$3) -> 1.0960262e+13 | P44: =$P$3 -> 1300000000000 | Q44: =O44-P44 -> 9.6602624e+12 | R44: 9989232292 | S44: =$S$3 -> 1 | T44: =(Q44/(R44*S44))/12 -> 80.588962
A45: Year 37 | B45: 2061 | C45: =C44*(1-$C$5) -> 0.84256214 | D45: 4000 | E45: =D45*C45*1000000000 -> 3.3702486e+12 | F45: =E45*(1-$F$3) -> 3.3533973e+12 | G45: 1 | H45: =F45*G45 -> 3.3533973e+12 | I45: =I44+H45 -> 1.8342787e+14 | J45: =(J44+H45)*(1-$J$3) -> 1.8204357e+14 | K45: =J44*$K$3 -> 1.133473e+13 | L45: =F45*(1-G45) -> 0 | M45: =K45+L45 -> 1.133473e+13 | N45: =M45*1% -> 1.133473e+11 | O45: =(M45-N45)*(1-$O$3) -> 1.1165276e+13 | P45: =$P$3 -> 1300000000000 | Q45: =O45-P45 -> 9.8652762e+12 | R45: 10013916213 | S45: =$S$3 -> 1 | T45: =(Q45/(R45*S45))/12 -> 82.096388
A46: Year 38 | B46: 2062 | C46: =C45*(1-$C$5) -> 0.75830593 | D46: 4000 | E46: =D46*C46*1000000000 -> 3.0332237e+12 | F46: =E46*(1-$F$3) -> 3.0180576e+12 | G46: 1 | H46: =F46*G46 -> 3.0180576e+12 | I46: =I45+H46 -> 1.8644593e+14 | J46: =(J45+H46)*(1-$J$3) -> 1.8496909e+14 | K46: =J45*$K$3 -> 1.1541562e+13 | L46: =F46*(1-G46) -> 0 | M46: =K46+L46 -> 1.1541562e+13 | N46: =M46*1.2% -> 1.3849875e+11 | O46: =(M46-N46)*(1-$O$3) -> 1.1346048e+13 | P46: =$P$3 -> 1300000000000 | Q46: =O46-P46 -> 1.0046048e+13 | R46: 10037466600 | S46: =$S$3 -> 1 | T46: =(Q46/(R46*S46))/12 -> 83.404579
A47: Year 39 | B47: 2063 | C47: =C46*(1-$C$5) -> 0.68247534 | D47: 4000 | E47: =D47*C47*1000000000 -> 2.7299013e+12 | F47: =E47*(1-$F$3) -> 2.7162518e+12 | G47: 1 | H47: =F47*G47 -> 2.7162518e+12 | I47: =I46+H47 -> 1.8916218e+14 | J47: =(J46+H47)*(1-$J$3) -> 1.875915e+14 | K47: =J46*$K$3 -> 1.1727041e+13 | L47: =F47*(1-G47) -> 0 | M47: =K47+L47 -> 1.1727041e+13 | N47: =M47*1.4% -> 1.6417857e+11 | O47: =(M47-N47)*(1-$O$3) -> 1.1505048e+13 | P47: =$P$3 -> 1300000000000 | Q47: =O47-P47 -> 1.0205048e+13 | R47: 10059950035 | S47: =$S$3 -> 1 | T47: =(Q47/(R47*S47))/12 -> 84.535275
A48: Year 40 | B48: 2064 | C48: =C47*(1-$C$5) -> 0.6142278 | D48: 4000 | E48: =D48*C48*1000000000 -> 2.4569112e+12 | F48: =E48*(1-$F$3) -> 2.4446267e+12 | G48: 1 | H48: =F48*G48 -> 2.4446267e+12 | I48: =I47+H48 -> 1.916068e+14 | J48: =(J47+H48)*(1-$J$3) -> 1.8994111e+14 | K48: =J47*$K$3 -> 1.1893301e+13 | L48: =F48*(1-G48) -> 0 | M48: =K48+L48 -> 1.1893301e+13 | N48: =M48*1.6% -> 1.9029282e+11 | O48: =(M48-N48)*(1-$O$3) -> 1.1644493e+13 | P48: =$P$3 -> 1300000000000 | Q48: =O48-P48 -> 1.0344493e+13 | R48: 10081402737 | S48: =$S$3 -> 1 | T48: =(Q48/(R48*S48))/12 -> 85.508053
A49: Year 41 | B49: 2065 | C49: =C48*(1-$C$5) -> 0.55280502 | D49: 4000 | E49: =D49*C49*1000000000 -> 2.2112201e+12 | F49: =E49*(1-$F$3) -> 2.200164e+12 | G49: 1 | H49: =F49*G49 -> 2.200164e+12 | I49: =I48+H49 -> 1.9380697e+14 | J49: =(J48+H49)*(1-$J$3) -> 1.9204521e+14 | K49: =J48*$K$3 -> 1.2042266e+13 | L49: =F49*(1-G49) -> 0 | M49: =K49+L49 -> 1.2042266e+13 | N49: =M49*1.8% -> 2.167608e+11 | O49: =(M49-N49)*(1-$O$3) -> 1.1766378e+13 | P49: =$P$3 -> 1300000000000 | Q49: =O49-P49 -> 1.0466378e+13 | R49: 10101849561 | S49: =$S$3 -> 1 | T49: =(Q49/(R49*S49))/12 -> 86.340444
A50: Year 42 | B50: 2066 | C50: =C49*(1-$C$5) -> 0.49752452 | D50: 4000 | E50: =D50*C50*1000000000 -> 1.9900981e+12 | F50: =E50*(1-$F$3) -> 1.9801476e+12 | G50: 1 | H50: =F50*G50 -> 1.9801476e+12 | I50: =I49+H50 -> 1.9578712e+14 | J50: =(J49+H50)*(1-$J$3) -> 1.9392834e+14 | K50: =J49*$K$3 -> 1.2175666e+13 | L50: =F50*(1-G50) -> 0 | M50: =K50+L50 -> 1.2175666e+13 | N50: =M50*2% -> 2.4351332e+11 | O50: =(M50-N50)*(1-$O$3) -> 1.1872492e+13 | P50: =$P$3 -> 1300000000000 | Q50: =O50-P50 -> 1.0572492e+13 | R50: 10121317107 | S50: =$S$3 -> 1 | T50: =(Q50/(R50*S50))/12 -> 87.048058
A51: Year 43 | B51: 2067 | C51: =C50*(1-$C$5) -> 0.44777207 | D51: 4000 | E51: =D51*C51*1000000000 -> 1.7910883e+12 | F51: =E51*(1-$F$3) -> 1.7821328e+12 | G51: 1 | H51: =F51*G51 -> 1.7821328e+12 | I51: =I50+H51 -> 1.9756925e+14 | J51: =(J50+H51)*(1-$J$3) -> 1.9561262e+14 | K51: =J50*$K$3 -> 1.2295057e+13 | L51: =F51*(1-G51) -> 0 | M51: =K51+L51 -> 1.2295057e+13 | N51: =M51*2.2% -> 2.7049125e+11 | O51: =(M51-N51)*(1-$O$3) -> 1.1964443e+13 | P51: =$P$3 -> 1300000000000 | Q51: =O51-P51 -> 1.0664443e+13 | R51: 10139808361 | S51: =$S$3 -> 1 | T51: =(Q51/(R51*S51))/12 -> 87.645005
A52: Year 44 | B52: 2068 | C52: =C51*(1-$C$5) -> 0.40299486 | D52: 4000 | E52: =D52*C52*1000000000 -> 1.6119794e+12 | F52: =E52*(1-$F$3) -> 1.6039195e+12 | G52: 1 | H52: =F52*G52 -> 1.6039195e+12 | I52: =I51+H52 -> 1.9917317e+14 | J52: =(J51+H52)*(1-$J$3) -> 1.9711793e+14 | K52: =J51*$K$3 -> 1.240184e+13 | L52: =F52*(1-G52) -> 0 | M52: =K52+L52 -> 1.240184e+13 | N52: =M52*2.4% -> 2.9764416e+11 | O52: =(M52-N52)*(1-$O$3) -> 1.2043675e+13 | P52: =$P$3 -> 1300000000000 | Q52: =O52-P52 -> 1.0743675e+13 | R52: 10157301941 | S52: =$S$3 -> 1 | T52: =(Q52/(R52*S52))/12 -> 88.1441
A53: Year 45 | B53: 2069 | C53: =C52*(1-$C$5) -> 0.36269537 | D53: 4000 | E53: =D53*C53*1000000000 -> 1.4507815e+12 | F53: =E53*(1-$F$3) -> 1.4435276e+12 | G53: 1 | H53: =F53*G53 -> 1.4435276e+12 | I53: =I52+H53 -> 2.006167e+14 | J53: =(J52+H53)*(1-$J$3) -> 1.9846218e+14 | K53: =J52*$K$3 -> 1.2497277e+13 | L53: =F53*(1-G53) -> 0 | M53: =K53+L53 -> 1.2497277e+13 | N53: =M53*2.6% -> 3.2492919e+11 | O53: =(M53-N53)*(1-$O$3) -> 1.2111486e+13 | P53: =$P$3 -> 1300000000000 | Q53: =O53-P53 -> 1.0811486e+13 | R53: 10173782135 | S53: =$S$3 -> 1 | T53: =(Q53/(R53*S53))/12 -> 88.556757
A54: Year 46 | B54: 2070 | C54: =C53*(1-$C$5) -> 0.32642584 | D54: 4000 | E54: =D54*C54*1000000000 -> 1.3057033e+12 | F54: =E54*(1-$F$3) -> 1.2991748e+12 | G54: 1 | H54: =F54*G54 -> 1.2991748e+12 | I54: =I53+H54 -> 2.0191587e+14 | J54: =(J53+H54)*(1-$J$3) -> 1.9966147e+14 | K54: =J53*$K$3 -> 1.2582502e+13 | L54: =F54*(1-G54) -> 0 | M54: =K54+L54 -> 1.2582502e+13 | N54: =M54*2.8% -> 3.5231005e+11 | O54: =(M54-N54)*(1-$O$3) -> 1.2169041e+13 | P54: =$P$3 -> 1300000000000 | Q54: =O54-P54 -> 1.0869041e+13 | R54: 10189241959 | S54: =$S$3 -> 1 | T54: =(Q54/(R54*S54))/12 -> 88.893111
A55: Year 47 | B55: 2071 | C55: =C54*(1-$C$5) -> 0.29378325 | D55: 4000 | E55: =D55*C55*1000000000 -> 1.175133e+12 | F55: =E55*(1-$F$3) -> 1.1692573e+12 | G55: 1 | H55: =F55*G55 -> 1.1692573e+12 | I55: =I54+H55 -> 2.0308513e+14 | J55: =(J54+H55)*(1-$J$3) -> 2.0073031e+14 | K55: =J54*$K$3 -> 1.2658537e+13 | L55: =F55*(1-G55) -> 0 | M55: =K55+L55 -> 1.2658537e+13 | N55: =M55*3% -> 3.7975612e+11 | O55: =(M55-N55)*(1-$O$3) -> 1.2217387e+13 | P55: =$P$3 -> 1300000000000 | Q55: =O55-P55 -> 1.0917387e+13 | R55: 10203681568 | S55: =$S$3 -> 1 | T55: =(Q55/(R55*S55))/12 -> 89.162158
A56: Year 48 | B56: 2072 | C56: =C55*(1-$C$5) -> 0.26440493 | D56: 4000 | E56: =D56*C56*1000000000 -> 1.0576197e+12 | F56: =E56*(1-$F$3) -> 1.0523316e+12 | G56: 1 | H56: =F56*G56 -> 1.0523316e+12 | I56: =I55+H56 -> 2.0413746e+14 | J56: =(J55+H56)*(1-$J$3) -> 2.0168175e+14 | K56: =J55*$K$3 -> 1.2726302e+13 | L56: =F56*(1-G56) -> 0 | M56: =K56+L56 -> 1.2726302e+13 | N56: =M56*3.2% -> 4.0724166e+11 | O56: =(M56-N56)*(1-$O$3) -> 1.2257465e+13 | P56: =$P$3 -> 1300000000000 | Q56: =O56-P56 -> 1.0957465e+13 | R56: 10217055169 | S56: =$S$3 -> 1 | T56: =(Q56/(R56*S56))/12 -> 89.372334
A57: Year 49 | B57: 2073 | C57: =C56*(1-$C$5) -> 0.23796444 | D57: 4000 | E57: =D57*C57*1000000000 -> 9.5185774e+11 | F57: =E57*(1-$F$3) -> 9.4709845e+11 | G57: 1 | H57: =F57*G57 -> 9.4709845e+11 | I57: =I56+H57 -> 2.0508456e+14 | J57: =(J56+H57)*(1-$J$3) -> 2.0252754e+14 | K57: =J56*$K$3 -> 1.2786623e+13 | L57: =F57*(1-G57) -> 0 | M57: =K57+L57 -> 1.2786623e+13 | N57: =M57*3.4% -> 4.3474519e+11 | O57: =(M57-N57)*(1-$O$3) -> 1.2290119e+13 | P57: =$P$3 -> 1300000000000 | Q57: =O57-P57 -> 1.0990119e+13 | R57: 10229327824 | S57: =$S$3 -> 1 | T57: =(Q57/(R57*S57))/12 -> 89.531123
A58: Year 50 | B58: 2074 | C58: =C57*(1-$C$5) -> 0.21416799 | D58: 4000 | E58: =D58*C58*1000000000 -> 8.5667197e+11 | F58: =E58*(1-$F$3) -> 8.5238861e+11 | G58: 1 | H58: =F58*G58 -> 8.5238861e+11 | I58: =I57+H58 -> 2.0593695e+14 | J58: =(J57+H58)*(1-$J$3) -> 2.0327824e+14 | K58: =J57*$K$3 -> 1.2840246e+13 | L58: =F58*(1-G58) -> 0 | M58: =K58+L58 -> 1.2840246e+13 | N58: =M58*3.6% -> 4.6224885e+11 | O58: =(M58-N58)*(1-$O$3) -> 1.2316107e+13 | P58: =$P$3 -> 1300000000000 | Q58: =O58-P58 -> 1.1016107e+13 | R58: 10240485056 | S58: =$S$3 -> 1 | T58: =(Q58/(R58*S58))/12 -> 89.645062
A59: Year 51 | B59: 2075 | C59: =C58*(1-$C$5) -> 0.19275119 | D59: 4000 | E59: =D59*C59*1000000000 -> 7.7100477e+11 | F59: =E59*(1-$F$3) -> 7.6714975e+11 | G59: 1 | H59: =F59*G59 -> 7.6714975e+11 | I59: =I58+H59 -> 2.067041e+14 | J59: =(J58+H59)*(1-$J$3) -> 2.0394336e+14 | K59: =J58*$K$3 -> 1.288784e+13 | L59: =F59*(1-G59) -> 0 | M59: =K59+L59 -> 1.288784e+13 | N59: =M59*3.8% -> 4.8973792e+11 | O59: =(M59-N59)*(1-$O$3) -> 1.2336112e+13 | P59: =$P$3 -> 1300000000000 | Q59: =O59-P59 -> 1.1036112e+13 | R59: 10250496432 | S59: =$S$3 -> 1 | T59: =(Q59/(R59*S59))/12 -> 89.72014
A60: Year 52 | B60: 2076 | C60: =C59*(1-$C$5) -> 0.17347607 | D60: 4000 | E60: =D60*C60*1000000000 -> 6.9390429e+11 | F60: =E60*(1-$F$3) -> 6.9043477e+11 | G60: =100% -> 1 | H60: =F60*G60 -> 6.9043477e+11 | I60: =I59+H60+N59 -> 2.0788427e+14 | J60: =(J59+H60)*(1-$J$3) -> 2.0453148e+14 | K60: =J59*$K$3 -> 1.2930009e+13 | L60: =F60*(1-G60) -> 0 | M60: =K60+L60 -> 1.2930009e+13 | N60: =M60*4% -> 5.1720037e+11 | O60: =(M60-N60)*(1-$O$3) -> 1.2350745e+13 | P60: =$P$3 -> 1300000000000 | Q60: =O60-P60 -> 1.1050745e+13 | R60: 10259351432 | S60: =$S$3 -> 1 | T60: =(Q60/(R60*S60))/12 -> 89.761561
A61: Year 53 | B61: 2077 | C61: =C60*(1-$C$5) -> 0.15612847 | D61: 4000 | E61: =D61*C61*1000000000 -> 6.2451386e+11 | F61: =E61*(1-$F$3) -> 6.213913e+11 | G61: =100% -> 1 | H61: =F61*G61 -> 6.213913e+11 | I61: =I60+H61+N60 -> 2.0902286e+14 | J61: =(J60+H61+N60)*(1-$J$3) -> 2.0556724e+14 | K61: =J60*$K$3 -> 1.2967296e+13 | L61: =F61*(1-G61) -> 0 | M61: =K61+L61 -> 1.2967296e+13 | N61: =M61*4.5% -> 5.8352831e+11 | O61: =(M61-N61)*(1-$O$3) -> 1.2321849e+13 | P61: =$P$3 -> 1300000000000 | Q61: =O61-P61 -> 1.1021849e+13 | R61: 10267045023 | S61: =$S$3 -> 1 | T61: =(Q61/(R61*S61))/12 -> 89.459761
A62: Year 54 | B62: 2078 | C62: =C61*(1-$C$5) -> 0.14051562 | D62: 4000 | E62: =D62*C62*1000000000 -> 5.6206248e+11 | F62: =E62*(1-$F$3) -> 5.5925217e+11 | G62: =100% -> 1 | H62: =F62*G62 -> 5.5925217e+11 | I62: =I61+H62+N61 -> 210165641522342 | J62: =(J61+H62+N61)*(1-$J$3) -> 2.0660666e+14 | K62: =J61*$K$3 -> 1.3032963e+13 | L62: =F62*(1-G62) -> 0 | M62: =K62+L62 -> 1.3032963e+13 | N62: =M62*5% -> 6.5164814e+11 | O62: =(M62-N62)*(1-$O$3) -> 1.2319408e+13 | P62: =$P$3 -> 1300000000000 | Q62: =O62-P62 -> 1.1019408e+13 | R62: 10273556322 | S62: =$S$3 -> 1 | T62: =(Q62/(R62*S62))/12 -> 89.383265
A63: Year 55 | B63: 2079 | C63: =C62*(1-$C$5) -> 0.12646406 | D63: 4000 | E63: =D63*C63*1000000000 -> 5.0585623e+11 | F63: =E63*(1-$F$3) -> 5.0332695e+11 | G63: =100% -> 1 | H63: =F63*G63 -> 5.0332695e+11 | I63: =I62+H63+N62 -> 2.1132062e+14 | J63: =(J62+H63+N62)*(1-$J$3) -> 2.0765776e+14 | K63: =J62*$K$3 -> 1.3098862e+13 | L63: =F63*(1-G63) -> 0 | M63: =K63+L63 -> 1.3098862e+13 | N63: =M63*5.5% -> 7.2043743e+11 | O63: =(M63-N63)*(1-$O$3) -> 1.2316533e+13 | P63: =$P$3 -> 1300000000000 | Q63: =O63-P63 -> 1.1016533e+13 | R63: 10278887473 | S63: =$S$3 -> 1 | T63: =(Q63/(R63*S63))/12 -> 89.313596
A64: Year 56 | B64: 2080 | C64: =C63*(1-$C$5) -> 0.11381765 | D64: 4000 | E64: =D64*C64*1000000000 -> 4.5527061e+11 | F64: =E64*(1-$F$3) -> 4.5299425e+11 | G64: =100% -> 1 | H64: =F64*G64 -> 4.5299425e+11 | I64: =I63+H64+N63 -> 2.1249405e+14 | J64: =(J63+H64+N63)*(1-$J$3) -> 2.0872677e+14 | K64: =J63*$K$3 -> 1.3165502e+13 | L64: =F64*(1-G64) -> 0 | M64: =K64+L64 -> 1.3165502e+13 | N64: =M64*6% -> 7.8993011e+11 | O64: =(M64-N64)*(1-$O$3) -> 1.2313694e+13 | P64: =$P$3 -> 1300000000000 | Q64: =O64-P64 -> 1.1013694e+13 | R64: 10283078029 | S64: =$S$3 -> 1 | T64: =(Q64/(R64*S64))/12 -> 89.254192
A65: Year 57 | B65: 2081 | C65: =C64*(1-$C$5) -> 0.10243589 | D65: 4000 | E65: =D65*C65*1000000000 -> 4.0974355e+11 | F65: =E65*(1-$F$3) -> 4.0769483e+11 | G65: =100% -> 1 | H65: =F65*G65 -> 4.0769483e+11 | I65: =I64+H65+N64 -> 2.1369167e+14 | J65: =(J64+H65+N64)*(1-$J$3) -> 2.0981944e+14 | K65: =J64*$K$3 -> 1.3233277e+13 | L65: =F65*(1-G65) -> 0 | M65: =K65+L65 -> 1.3233277e+13 | N65: =M65*6.5% -> 8.6016303e+11 | O65: =(M65-N65)*(1-$O$3) -> 1.2311249e+13 | P65: =$P$3 -> 1300000000000 | Q65: =O65-P65 -> 1.1011249e+13 | R65: 10286161735 | S65: =$S$3 -> 1 | T65: =(Q65/(R65*S65))/12 -> 89.207626
A66: Year 58 | B66: 2082 | C66: =C65*(1-$C$5) -> 0.092192298 | D66: 4000 | E66: =D66*C66*1000000000 -> 3.6876919e+11 | F66: =E66*(1-$F$3) -> 3.6692535e+11 | G66: =100% -> 1 | H66: =F66*G66 -> 3.6692535e+11 | I66: =I65+H66+N65 -> 2.1491876e+14 | J66: =(J65+H66+N65)*(1-$J$3) -> 2.10941e+14 | K66: =J65*$K$3 -> 1.3302552e+13 | L66: =F66*(1-G66) -> 0 | M66: =K66+L66 -> 1.3302552e+13 | N66: =M66*7% -> 9.3117865e+11 | O66: =(M66-N66)*(1-$O$3) -> 1.2309517e+13 | P66: =$P$3 -> 1300000000000 | Q66: =O66-P66 -> 1.1009517e+13 | R66: 10288205050 | S66: =$S$3 -> 1 | T66: =(Q66/(R66*S66))/12 -> 89.175878
A67: Year 59 | B67: 2083 | C67: =C66*(1-$C$5) -> 0.082973068 | D67: 4000 | E67: =D67*C67*1000000000 -> 3.3189227e+11 | F67: =E67*(1-$F$3) -> 3.3023281e+11 | G67: =100% -> 1 | H67: =F67*G67 -> 3.3023281e+11 | I67: =I66+H67+N66 -> 2.1618017e+14 | J67: =(J66+H67+N66)*(1-$J$3) -> 2.1209631e+14 | K67: =J66*$K$3 -> 1.3373659e+13 | L67: =F67*(1-G67) -> 0 | M67: =K67+L67 -> 1.3373659e+13 | N67: =M67*7.5% -> 1.0030245e+12 | O67: =(M67-N67)*(1-$O$3) -> 1.2308782e+13 | P67: =$P$3 -> 1300000000000 | Q67: =O67-P67 -> 1.1008782e+13 | R67: 10289247323 | S67: =$S$3 -> 1 | T67: =(Q67/(R67*S67))/12 -> 89.160893
A68: Year 60 | B68: 2084 | C68: =C67*(1-$C$5) -> 0.074675761 | D68: 4000 | E68: =D68*C68*1000000000 -> 2.9870305e+11 | F68: =E68*(1-$F$3) -> 2.9720953e+11 | G68: =100% -> 1 | H68: =F68*G68 -> 2.9720953e+11 | I68: =I67+H68+N67 -> 2.1748041e+14 | J68: =(J67+H68+N67)*(1-$J$3) -> 2.1328985e+14 | K68: =J67*$K$3 -> 1.3446906e+13 | L68: =F68*(1-G68) -> 0 | M68: =K68+L68 -> 1.3446906e+13 | N68: =M68*8% -> 1.0757525e+12 | O68: =(M68-N68)*(1-$O$3) -> 1.2309298e+13 | P68: =$P$3 -> 1300000000000 | Q68: =O68-P68 -> 1.1009298e+13 | R68: 10289315244 | S68: =$S$3 -> 1 | T68: =(Q68/(R68*S68))/12 -> 89.164484
A69: Year 61 | B69: 2085 | C69: =C68*(1-$C$5) -> 0.067208185 | D69: 4000 | E69: =D69*C69*1000000000 -> 2.6883274e+11 | F69: =E69*(1-$F$3) -> 2.6748858e+11 | G69: =100% -> 1 | H69: =F69*G69 -> 2.6748858e+11 | I69: =I68+H69+N68 -> 2.1882365e+14 | J69: =(J68+H69+N68)*(1-$J$3) -> 2.1452577e+14 | K69: =J68*$K$3 -> 1.3522576e+13 | L69: =F69*(1-G69) -> 0 | M69: =K69+L69 -> 1.3522576e+13 | N69: =M69*8.5% -> 1.149419e+12 | O69: =(M69-N69)*(1-$O$3) -> 1.2311291e+13 | P69: =$P$3 -> 1300000000000 | Q69: =O69-P69 -> 1.1011291e+13 | R69: 10288456599 | S69: =$S$3 -> 1 | T69: =(Q69/(R69*S69))/12 -> 89.188074
A70: Year 62 | B70: 2086 | C70: =C69*(1-$C$5) -> 0.060487367 | D70: 4000 | E70: =D70*C70*1000000000 -> 2.4194947e+11 | F70: =E70*(1-$F$3) -> 2.4073972e+11 | G70: =100% -> 1 | H70: =F70*G70 -> 2.4073972e+11 | I70: =I69+H70+N69 -> 2.2021381e+14 | J70: =(J69+H70+N69)*(1-$J$3) -> 2.1580797e+14 | K70: =J69*$K$3 -> 1.3600934e+13 | L70: =F70*(1-G70) -> 0 | M70: =K70+L70 -> 1.3600934e+13 | N70: =M70*9% -> 1.224084e+12 | O70: =(M70-N70)*(1-$O$3) -> 1.2314966e+13 | P70: =$P$3 -> 1300000000000 | Q70: =O70-P70 -> 1.1014966e+13 | R70: 10286708360 | S70: =$S$3 -> 1 | T70: =(Q70/(R70*S70))/12 -> 89.232995
A71: Year 63 | B71: 2087 | C71: =C70*(1-$C$5) -> 0.05443863 | D71: 4000 | E71: =D71*C71*1000000000 -> 2.1775452e+11 | F71: =E71*(1-$F$3) -> 2.1666575e+11 | G71: =100% -> 1 | H71: =F71*G71 -> 2.1666575e+11 | I71: =I70+H71+N70 -> 2.2165456e+14 | J71: =(J70+H71+N70)*(1-$J$3) -> 2.171401e+14 | K71: =J70*$K$3 -> 1.3682225e+13 | L71: =F71*(1-G71) -> 0 | M71: =K71+L71 -> 1.3682225e+13 | N71: =M71*9.5% -> 1.2998114e+12 | O71: =(M71-N71)*(1-$O$3) -> 1.2320502e+13 | P71: =$P$3 -> 1300000000000 | Q71: =O71-P71 -> 1.1020502e+13 | R71: 10284111374 | S71: =$S$3 -> 1 | T71: =(Q71/(R71*S71))/12 -> 89.30039
A72: Year 64 | B72: 2088 | C72: =C71*(1-$C$5) -> 0.048994767 | D72: 4000 | E72: =D72*C72*1000000000 -> 1.9597907e+11 | F72: =E72*(1-$F$3) -> 1.9499917e+11 | G72: =100% -> 1 | H72: =F72*G72 -> 1.9499917e+11 | I72: =I71+H72+N71 -> 2.2314937e+14 | J72: =(J71+H72+N71)*(1-$J$3) -> 2.1852559e+14 | K72: =J71*$K$3 -> 1.3766682e+13 | L72: =F72*(1-G72) -> 0 | M72: =K72+L72 -> 1.3766682e+13 | N72: =M72*$N$5 -> 1.3766682e+12 | O72: =(M72-N72)*(1-$O$3) -> 1.2328064e+13 | P72: =$P$3 -> 1300000000000 | Q72: =O72-P72 -> 1.1028064e+13 | R72: 10280704572 | S72: =$S$3 -> 1 | T72: =(Q72/(R72*S72))/12 -> 89.391278
A73: Year 65 | B73: 2089 | C73: =C72*(1-$C$5) -> 0.04409529 | D73: 4000 | E73: =D73*C73*1000000000 -> 1.7638116e+11 | F73: =E73*(1-$F$3) -> 1.7549926e+11 | G73: =100% -> 1 | H73: =F73*G73 -> 1.7549926e+11 | I73: =I72+H73+N72 -> 2.2470153e+14 | J73: =(J72+H73+N72)*(1-$J$3) -> 2.1996772e+14 | K73: =J72*$K$3 -> 1.3854522e+13 | L73: =F73*(1-G73) -> 0 | M73: =K73+L73 -> 1.3854522e+13 | N73: =M73*$N$5 -> 1.3854522e+12 | O73: =(M73-N73)*(1-$O$3) -> 1.2406725e+13 | P73: =$P$3 -> 1300000000000 | Q73: =O73-P73 -> 1.1106725e+13 | R73: 10276518280 | S73: =$S$3 -> 1 | T73: =(Q73/(R73*S73))/12 -> 90.065563
A74: Year 66 | B74: 2090 | C74: =C73*(1-$C$5) -> 0.039685761 | D74: 4000 | E74: =D74*C74*1000000000 -> 1.5874305e+11 | F74: =E74*(1-$F$3) -> 1.5794933e+11 | G74: =100% -> 1 | H74: =F74*G74 -> 1.5794933e+11 | I74: =I73+H74+N73 -> 2.2624494e+14 | J74: =(J73+H74+N73)*(1-$J$3) -> 2.2140036e+14 | K74: =J73*$K$3 -> 1.3945953e+13 | L74: =F74*(1-G74) -> 0 | M74: =K74+L74 -> 1.3945953e+13 | N74: =M74*$N$5 -> 1.3945953e+12 | O74: =(M74-N74)*(1-$O$3) -> 1.2488601e+13 | P74: =$P$3 -> 1300000000000 | Q74: =O74-P74 -> 1.1188601e+13 | R74: 10271565070 | S74: =$S$3 -> 1 | T74: =(Q74/(R74*S74))/12 -> 90.773259
A75: Year 67 | B75: 2091 | C75: =C74*(1-$C$5) -> 0.035717185 | D75: 4000 | E75: =D75*C75*1000000000 -> 1.4286874e+11 | F75: =E75*(1-$F$3) -> 1.421544e+11 | G75: =100% -> 1 | H75: =F75*G75 -> 1.421544e+11 | I75: =I74+H75+N74 -> 2.2778169e+14 | J75: =(J74+H75+N74)*(1-$J$3) -> 2.2282565e+14 | K75: =J74*$K$3 -> 1.4036783e+13 | L75: =F75*(1-G75) -> 0 | M75: =K75+L75 -> 1.4036783e+13 | N75: =M75*$N$5 -> 1.4036783e+12 | O75: =(M75-N75)*(1-$O$3) -> 1.2569939e+13 | P75: =$P$3 -> 1300000000000 | Q75: =O75-P75 -> 1.1269939e+13 | R75: 10265861714 | S75: =$S$3 -> 1 | T75: =(Q75/(R75*S75))/12 -> 91.483953
A76: Year 68 | B76: 2092 | C76: =C75*(1-$C$5) -> 0.032145467 | D76: 4000 | E76: =D76*C76*1000000000 -> 1.2858187e+11 | F76: =E76*(1-$F$3) -> 1.2793896e+11 | G76: =100% -> 1 | H76: =F76*G76 -> 1.2793896e+11 | I76: =I75+H76+N75 -> 2.293133e+14 | J76: =(J75+H76+N75)*(1-$J$3) -> 2.2424508e+14 | K76: =J75*$K$3 -> 1.4127146e+13 | L76: =F76*(1-G76) -> 0 | M76: =K76+L76 -> 1.4127146e+13 | N76: =M76*$N$5 -> 1.4127146e+12 | O76: =(M76-N76)*(1-$O$3) -> 1.2650859e+13 | P76: =$P$3 -> 1300000000000 | Q76: =O76-P76 -> 1.1350859e+13 | R76: 10259408375 | S76: =$S$3 -> 1 | T76: =(Q76/(R76*S76))/12 -> 92.19878
A77: Year 69 | B77: 2093 | C77: =C76*(1-$C$5) -> 0.02893092 | D77: 4000 | E77: =D77*C77*1000000000 -> 1.1572368e+11 | F77: =E77*(1-$F$3) -> 1.1514506e+11 | G77: =100% -> 1 | H77: =F77*G77 -> 1.1514506e+11 | I77: =I76+H77+N76 -> 2.3084116e+14 | J77: =(J76+H77+N76)*(1-$J$3) -> 2.2566006e+14 | K77: =J76*$K$3 -> 1.4217138e+13 | L77: =F77*(1-G77) -> 0 | M77: =K77+L77 -> 1.4217138e+13 | N77: =M77*$N$5 -> 1.4217138e+12 | O77: =(M77-N77)*(1-$O$3) -> 1.2731447e+13 | P77: =$P$3 -> 1300000000000 | Q77: =O77-P77 -> 1.1431447e+13 | R77: 10252184759 | S77: =$S$3 -> 1 | T77: =(Q77/(R77*S77))/12 -> 92.918791
A78: Year 70 | B78: 2094 | C78: =C77*(1-$C$5) -> 0.026037828 | D78: 4000 | E78: =D78*C78*1000000000 -> 1.0415131e+11 | F78: =E78*(1-$F$3) -> 1.0363056e+11 | G78: =100% -> 1 | H78: =F78*G78 -> 1.0363056e+11 | I78: =I77+H78+N77 -> 2.3236651e+14 | J78: =(J77+H78+N77)*(1-$J$3) -> 2.2707181e+14 | K78: =J77*$K$3 -> 1.4306848e+13 | L78: =F78*(1-G78) -> 0 | M78: =K78+L78 -> 1.4306848e+13 | N78: =M78*$N$5 -> 1.4306848e+12 | O78: =(M78-N78)*(1-$O$3) -> 1.2811782e+13 | P78: =$P$3 -> 1300000000000 | Q78: =O78-P78 -> 1.1511782e+13 | R78: 10244185837 | S78: =$S$3 -> 1 | T78: =(Q78/(R78*S78))/12 -> 93.644843
A79: Year 71 | B79: 2095 | C79: =C78*(1-$C$5) -> 0.023434045 | D79: 4000 | E79: =D79*C79*1000000000 -> 9.3736181e+10 | F79: =E79*(1-$F$3) -> 9.32675e+10 | G79: =100% -> 1 | H79: =F79*G79 -> 9.32675e+10 | I79: =I78+H79+N78 -> 2.3389046e+14 | J79: =(J78+H79+N78)*(1-$J$3) -> 2.2848146e+14 | K79: =J78*$K$3 -> 1.4396353e+13 | L79: =F79*(1-G79) -> 0 | M79: =K79+L79 -> 1.4396353e+13 | N79: =M79*$N$5 -> 1.4396353e+12 | O79: =(M79-N79)*(1-$O$3) -> 1.2891934e+13 | P79: =$P$3 -> 1300000000000 | Q79: =O79-P79 -> 1.1591934e+13 | R79: 10235403601 | S79: =$S$3 -> 1 | T79: =(Q79/(R79*S79))/12 -> 94.377762
A80: Year 72 | B80: 2096 | C80: =C79*(1-$C$5) -> 0.021090641 | D80: 4000 | E80: =D80*C80*1000000000 -> 8.4362563e+10 | F80: =E80*(1-$F$3) -> 8.394075e+10 | G80: =100% -> 1 | H80: =F80*G80 -> 8.394075e+10 | I80: =I79+H80+N79 -> 235414035582095 | J80: =(J79+H80+N79)*(1-$J$3) -> 2.2989004e+14 | K80: =J79*$K$3 -> 1.4485725e+13 | L80: =F80*(1-G80) -> 0 | M80: =K80+L80 -> 1.4485725e+13 | N80: =M80*$N$5 -> 1.4485725e+12 | O80: =(M80-N80)*(1-$O$3) -> 1.2971967e+13 | P80: =$P$3 -> 1300000000000 | Q80: =O80-P80 -> 1.1671967e+13 | R80: 10225850874 | S80: =$S$3 -> 1 | T80: =(Q80/(R80*S80))/12 -> 95.118137
A81: Year 73 | B81: 2097 | C81: =C80*(1-$C$5) -> 0.018981577 | D81: 4000 | E81: =D81*C81*1000000000 -> 7.5926306e+10 | F81: =E81*(1-$F$3) -> 7.5546675e+10 | G81: =100% -> 1 | H81: =F81*G81 -> 7.5546675e+10 | I81: =I80+H81+N80 -> 2.3693815e+14 | J81: =(J80+H81+N80)*(1-$J$3) -> 2.3129845e+14 | K81: =J80*$K$3 -> 1.4575028e+13 | L81: =F81*(1-G81) -> 0 | M81: =K81+L81 -> 1.4575028e+13 | N81: =M81*$N$5 -> 1.4575028e+12 | O81: =(M81-N81)*(1-$O$3) -> 1.3051938e+13 | P81: =$P$3 -> 1300000000000 | Q81: =O81-P81 -> 1.1751938e+13 | R81: 10215549310 | S81: =$S$3 -> 1 | T81: =(Q81/(R81*S81))/12 -> 95.866422
A82: Year 74 | B82: 2098 | C82: =C81*(1-$C$5) -> 0.017083419 | D82: 4000 | E82: =D82*C82*1000000000 -> 6.8333676e+10 | F82: =E82*(1-$F$3) -> 6.7992007e+10 | G82: =100% -> 1 | H82: =F82*G82 -> 6.7992007e+10 | I82: =I81+H82+N81 -> 2.3846365e+14 | J82: =(J81+H82+N81)*(1-$J$3) -> 2.3270753e+14 | K82: =J81*$K$3 -> 1.4664322e+13 | L82: =F82*(1-G82) -> 0 | M82: =K82+L82 -> 1.4664322e+13 | N82: =M82*$N$5 -> 1.4664322e+12 | O82: =(M82-N82)*(1-$O$3) -> 1.31319e+13 | P82: =$P$3 -> 1300000000000 | Q82: =O82-P82 -> 1.18319e+13 | R82: 10204489862 | S82: =$S$3 -> 1 | T82: =(Q82/(R82*S82))/12 -> 96.623318
A83: Year 75 | B83: 2099 | C83: =C82*(1-$C$5) -> 0.015375077 | D83: 4000 | E83: =D83*C83*1000000000 -> 6.1500308e+10 | F83: =E83*(1-$F$3) -> 6.1192807e+10 | G83: =100% -> 1 | H83: =F83*G83 -> 6.1192807e+10 | I83: =I82+H83+N82 -> 2.3999127e+14 | J83: =(J82+H83+N82)*(1-$J$3) -> 2.3411804e+14 | K83: =J82*$K$3 -> 1.4753658e+13 | L83: =F83*(1-G83) -> 0 | M83: =K83+L83 -> 1.4753658e+13 | N83: =M83*$N$5 -> 1.4753658e+12 | O83: =(M83-N83)*(1-$O$3) -> 1.32119e+13 | P83: =$P$3 -> 1300000000000 | Q83: =O83-P83 -> 1.19119e+13 | R83: 10192689066 | S83: =$S$3 -> 1 | T83: =(Q83/(R83*S83))/12 -> 97.389252
A84: Year 76 | B84: 2100 | C84: =C83*(1-$C$5) -> 0.013837569 | D84: 4000 | E84: =D84*C84*1000000000 -> 5.5350277e+10 | F84: =E84*(1-$F$3) -> 5.5073526e+10 | G84: =100% -> 1 | H84: =F84*G84 -> 5.5073526e+10 | I84: =I83+H84+N83 -> 2.4152171e+14 | J84: =(J83+H84+N83)*(1-$J$3) -> 2.3553065e+14 | K84: =J83*$K$3 -> 1.4843084e+13 | L84: =F84*(1-G84) -> 0 | M84: =K84+L84 -> 1.4843084e+13 | N84: =M84*$N$5 -> 1.4843084e+12 | O84: =(M84-N84)*(1-$O$3) -> 1.3291981e+13 | P84: =$P$3 -> 1300000000000 | Q84: =O84-P84 -> 1.1991981e+13 | R84: 10180160751 | S84: =$S$3 -> 1 | T84: =(Q84/(R84*S84))/12 -> 98.164637
A85: Year 77 | B85: 2101 | C85: =C84*(1-$C$5) -> 0.012453812 | D85: 4000 | E85: =D85*C85*1000000000 -> 4.981525e+10 | F85: =E85*(1-$F$3) -> 4.9566173e+10 | G85: =100% -> 1 | H85: =F85*G85 -> 4.9566173e+10 | I85: =I84+H85+N84 -> 2.4305559e+14 | J85: =(J84+H85+N84)*(1-$J$3) -> 2.36946e+14 | K85: =J84*$K$3 -> 1.4932644e+13 | L85: =F85*(1-G85) -> 0 | M85: =K85+L85 -> 1.4932644e+13 | N85: =M85*9% -> 1.3439379e+12 | O85: =(M85-N85)*(1-$O$3) -> 1.3520762e+13 | P85: =$P$3 -> 1300000000000 | Q85: =O85-P85 -> 1.2220762e+13 | R85: =R84*99.9% -> 1.0169981e+10 | S85: =$S$3 -> 1 | T85: =(Q85/(R85*S85))/12 -> 100.13754
A86: Year 78 | B86: 2102 | C86: =C85*(1-$C$5) -> 0.011208431 | D86: 4000 | E86: =D86*C86*1000000000 -> 4.4833725e+10 | F86: =E86*(1-$F$3) -> 4.4609556e+10 | G86: =100% -> 1 | H86: =F86*G86 -> 4.4609556e+10 | I86: =I85+H86+N85 -> 2.4444414e+14 | J86: =(J85+H86+N85)*(1-$J$3) -> 2.3821538e+14 | K86: =J85*$K$3 -> 1.5022376e+13 | L86: =F86*(1-G86) -> 0 | M86: =K86+L86 -> 1.5022376e+13 | N86: =M86*9.5% -> 1.4271257e+12 | O86: =(M86-N86)*(1-$O$3) -> 1.3527274e+13 | P86: =$P$3 -> 1300000000000 | Q86: =O86-P86 -> 1.2227274e+13 | R86: =R85*99.9% -> 1.0159811e+10 | S86: =$S$3 -> 1 | T86: =(Q86/(R86*S86))/12 -> 100.29119
A87: Year 79 | B87: 2103 | C87: =C86*(1-$C$5) -> 0.010087588 | D87: 4000 | E87: =D87*C87*1000000000 -> 4.0350352e+10 | F87: =E87*(1-$F$3) -> 4.01486e+10 | G87: =100% -> 1 | H87: =F87*G87 -> 4.01486e+10 | I87: =I86+H87+N86 -> 2.4591141e+14 | J87: =(J86+H87+N86)*(1-$J$3) -> 2.3956281e+14 | K87: =J86*$K$3 -> 1.5102855e+13 | L87: =F87*(1-G87) -> 0 | M87: =K87+L87 -> 1.5102855e+13 | N87: =M87*$N$5 -> 1.5102855e+12 | O87: =(M87-N87)*(1-$O$3) -> 1.3524607e+13 | P87: =$P$3 -> 1300000000000 | Q87: =O87-P87 -> 1.2224607e+13 | R87: =R86*99.9% -> 1.0149651e+10 | S87: =$S$3 -> 1 | T87: =(Q87/(R87*S87))/12 -> 100.36968
A88: Year 80 | B88: 2104 | C88: =C87*(1-$C$5) -> 0.0090788292 | D88: 4000 | E88: =D88*C88*1000000000 -> 3.6315317e+10 | F88: =E88*(1-$F$3) -> 3.613374e+10 | G88: =100% -> 1 | H88: =F88*G88 -> 3.613374e+10 | I88: =I87+H88+N87 -> 2.4745783e+14 | J88: =(J87+H88+N87)*(1-$J$3) -> 2.4098867e+14 | K88: =J87*$K$3 -> 1.5188282e+13 | L88: =F88*(1-G88) -> 0 | M88: =K88+L88 -> 1.5188282e+13 | N88: =M88*$N$5 -> 1.5188282e+12 | O88: =(M88-N88)*(1-$O$3) -> 1.3601107e+13 | P88: =$P$3 -> 1300000000000 | Q88: =O88-P88 -> 1.2301107e+13 | R88: =R87*99.9% -> 1.0139501e+10 | S88: =$S$3 -> 1 | T88: =(Q88/(R88*S88))/12 -> 101.09888
A89: Year 81 | B89: 2105 | C89: =C88*(1-$C$5) -> 0.0081709463 | D89: 4000 | E89: =D89*C89*1000000000 -> 3.2683785e+10 | F89: =E89*(1-$F$3) -> 3.2520366e+10 | G89: =100% -> 1 | H89: =F89*G89 -> 3.2520366e+10 | I89: =I88+H89+N88 -> 2.4900918e+14 | J89: =(J88+H89+N88)*(1-$J$3) -> 2.4241875e+14 | K89: =J88*$K$3 -> 1.5278682e+13 | L89: =F89*(1-G89) -> 0 | M89: =K89+L89 -> 1.5278682e+13 | N89: =M89*$N$5 -> 1.5278682e+12 | O89: =(M89-N89)*(1-$O$3) -> 1.368206e+13 | P89: =$P$3 -> 1300000000000 | Q89: =O89-P89 -> 1.238206e+13 | R89: =R88*99.9% -> 1.0129362e+10 | S89: =$S$3 -> 1 | T89: =(Q89/(R89*S89))/12 -> 101.86607
A90: Year 82 | B90: 2106 | C90: =C89*(1-$C$5) -> 0.0073538517 | D90: 4000 | E90: =D90*C90*1000000000 -> 2.9415407e+10 | F90: =E90*(1-$F$3) -> 2.926833e+10 | G90: =100% -> 1 | H90: =F90*G90 -> 2.926833e+10 | I90: =I89+H90+N89 -> 2.5056631e+14 | J90: =(J89+H90+N89)*(1-$J$3) -> 2.438539e+14 | K90: =J89*$K$3 -> 1.5369349e+13 | L90: =F90*(1-G90) -> 0 | M90: =K90+L90 -> 1.5369349e+13 | N90: =M90*$N$5 -> 1.5369349e+12 | O90: =(M90-N90)*(1-$O$3) -> 1.3763252e+13 | P90: =$P$3 -> 1300000000000 | Q90: =O90-P90 -> 1.2463252e+13 | R90: =R89*99.9% -> 1.0119232e+10 | S90: =$S$3 -> 1 | T90: =(Q90/(R90*S90))/12 -> 102.63667
A91: Year 83 | B91: 2107 | C91: =C90*(1-$C$5) -> 0.0066184665 | D91: 4000 | E91: =D91*C91*1000000000 -> 2.6473866e+10 | F91: =E91*(1-$F$3) -> 2.6341497e+10 | G91: =100% -> 1 | H91: =F91*G91 -> 2.6341497e+10 | I91: =I90+H91+N90 -> 2.5212959e+14 | J91: =(J90+H91+N90)*(1-$J$3) -> 2.4529447e+14 | K91: =J90*$K$3 -> 1.5460337e+13 | L91: =F91*(1-G91) -> 0 | M91: =K91+L91 -> 1.5460337e+13 | N91: =M91*$N$5 -> 1.5460337e+12 | O91: =(M91-N91)*(1-$O$3) -> 1.3844732e+13 | P91: =$P$3 -> 1300000000000 | Q91: =O91-P91 -> 1.2544732e+13 | R91: =R90*99.9% -> 1.0109113e+10 | S91: =$S$3 -> 1 | T91: =(Q91/(R91*S91))/12 -> 103.41108
A92: Year 84 | B92: 2108 | C92: =C91*(1-$C$5) -> 0.0059566199 | D92: 4000 | E92: =D92*C92*1000000000 -> 2.3826479e+10 | F92: =E92*(1-$F$3) -> 2.3707347e+10 | G92: =100% -> 1 | H92: =F92*G92 -> 2.3707347e+10 | I92: =I91+H92+N91 -> 2.5369933e+14 | J92: =(J91+H92+N91)*(1-$J$3) -> 2.4674078e+14 | K92: =J91*$K$3 -> 1.5551669e+13 | L92: =F92*(1-G92) -> 0 | M92: =K92+L92 -> 1.5551669e+13 | N92: =M92*$N$5 -> 1.5551669e+12 | O92: =(M92-N92)*(1-$O$3) -> 1.392652e+13 | P92: =$P$3 -> 1300000000000 | Q92: =O92-P92 -> 1.262652e+13 | R92: =R91*99.9% -> 1.0099004e+10 | S92: =$S$3 -> 1 | T92: =(Q92/(R92*S92))/12 -> 104.18948
A93: Year 85 | B93: 2109 | C93: =C92*(1-$C$5) -> 0.0053609579 | D93: 4000 | E93: =D93*C93*1000000000 -> 2.1443832e+10 | F93: =E93*(1-$F$3) -> 2.1336612e+10 | G93: =100% -> 1 | H93: =F93*G93 -> 2.1336612e+10 | I93: =I92+H93+N92 -> 2.5527584e+14 | J93: =(J92+H93+N92)*(1-$J$3) -> 2.4819312e+14 | K93: =J92*$K$3 -> 1.5643365e+13 | L93: =F93*(1-G93) -> 0 | M93: =K93+L93 -> 1.5643365e+13 | N93: =M93*$N$5 -> 1.5643365e+12 | O93: =(M93-N93)*(1-$O$3) -> 1.4008634e+13 | P93: =$P$3 -> 1300000000000 | Q93: =O93-P93 -> 1.2708634e+13 | R93: =R92*99.9% -> 1.0088905e+10 | S93: =$S$3 -> 1 | T93: =(Q93/(R93*S93))/12 -> 104.97203
A94: Year 86 | B94: 2110 | C94: =C93*(1-$C$5) -> 0.0048248621 | D94: 4000 | E94: =D94*C94*1000000000 -> 1.9299448e+10 | F94: =E94*(1-$F$3) -> 1.9202951e+10 | G94: =100% -> 1 | H94: =F94*G94 -> 1.9202951e+10 | I94: =I93+H94+N93 -> 2.5685938e+14 | J94: =(J93+H94+N93)*(1-$J$3) -> 2.4965177e+14 | K94: =J93*$K$3 -> 1.5735444e+13 | L94: =F94*(1-G94) -> 0 | M94: =K94+L94 -> 1.5735444e+13 | N94: =M94*$N$5 -> 1.5735444e+12 | O94: =(M94-N94)*(1-$O$3) -> 14091090135557 | P94: =$P$3 -> 1300000000000 | Q94: =O94-P94 -> 12791090135557 | R94: =R93*99.9% -> 1.0078816e+10 | S94: =$S$3 -> 1 | T94: =(Q94/(R94*S94))/12 -> 105.75887
A95: Year 87 | B95: 2111 | C95: =C94*(1-$C$5) -> 0.0043423759 | D95: 4000 | E95: =D95*C95*1000000000 -> 1.7369504e+10 | F95: =E95*(1-$F$3) -> 1.7282656e+10 | G95: =100% -> 1 | H95: =F95*G95 -> 1.7282656e+10 | I95: =I94+H95+N94 -> 2.584502e+14 | J95: =(J94+H95+N94)*(1-$J$3) -> 2.5111698e+14 | K95: =J94*$K$3 -> 1.5827923e+13 | L95: =F95*(1-G95) -> 0 | M95: =K95+L95 -> 1.5827923e+13 | N95: =M95*$N$5 -> 1.5827923e+12 | O95: =(M95-N95)*(1-$O$3) -> 1.4173905e+13 | P95: =$P$3 -> 1300000000000 | Q95: =O95-P95 -> 1.2873905e+13 | R95: =R94*99.9% -> 1.0068737e+10 | S95: =$S$3 -> 1 | T95: =(Q95/(R95*S95))/12 -> 106.55014
A96: Year 88 | B96: 2112 | C96: =C95*(1-$C$5) -> 0.0039081383 | D96: 4000 | E96: =D96*C96*1000000000 -> 1.5632553e+10 | F96: =E96*(1-$F$3) -> 1.555439e+10 | G96: =100% -> 1 | H96: =F96*G96 -> 1.555439e+10 | I96: =I95+H96+N95 -> 2.6004855e+14 | J96: =(J95+H96+N95)*(1-$J$3) -> 2.5258897e+14 | K96: =J95*$K$3 -> 1.5920817e+13 | L96: =F96*(1-G96) -> 0 | M96: =K96+L96 -> 1.5920817e+13 | N96: =M96*$N$5 -> 1.5920817e+12 | O96: =(M96-N96)*(1-$O$3) -> 1.4257091e+13 | P96: =$P$3 -> 1300000000000 | Q96: =O96-P96 -> 1.2957091e+13 | R96: =R95*99.9% -> 1.0058668e+10 | S96: =$S$3 -> 1 | T96: =(Q96/(R96*S96))/12 -> 107.34598
A97: Year 89 | B97: 2113 | C97: =C96*(1-$C$5) -> 0.0035173245 | D97: 4000 | E97: =D97*C97*1000000000 -> 1.4069298e+10 | F97: =E97*(1-$F$3) -> 1.3998951e+10 | G97: =100% -> 1 | H97: =F97*G97 -> 1.3998951e+10 | I97: =I96+H97+N96 -> 2.6165463e+14 | J97: =(J96+H97+N96)*(1-$J$3) -> 2.5406795e+14 | K97: =J96*$K$3 -> 1.6014141e+13 | L97: =F97*(1-G97) -> 0 | M97: =K97+L97 -> 1.6014141e+13 | N97: =M97*$N$5 -> 1.6014141e+12 | O97: =(M97-N97)*(1-$O$3) -> 1.4340663e+13 | P97: =$P$3 -> 1300000000000 | Q97: =O97-P97 -> 1.3040663e+13 | R97: =R96*99.9% -> 1.004861e+10 | S97: =$S$3 -> 1 | T97: =(Q97/(R97*S97))/12 -> 108.14649
A98: Year 90 | B98: 2114 | C98: =C97*(1-$C$5) -> 0.003165592 | D98: 4000 | E98: =D98*C98*1000000000 -> 1.2662368e+10 | F98: =E98*(1-$F$3) -> 1.2599056e+10 | G98: =100% -> 1 | H98: =F98*G98 -> 1.2599056e+10 | I98: =I97+H98+N97 -> 2.6326864e+14 | J98: =(J97+H98+N97)*(1-$J$3) -> 2.5555412e+14 | K98: =J97*$K$3 -> 1.6107908e+13 | L98: =F98*(1-G98) -> 0 | M98: =K98+L98 -> 1.6107908e+13 | N98: =M98*$N$5 -> 1.6107908e+12 | O98: =(M98-N98)*(1-$O$3) -> 1.4424632e+13 | P98: =$P$3 -> 1300000000000 | Q98: =O98-P98 -> 1.3124632e+13 | R98: =R97*99.9% -> 1.0038561e+10 | S98: =$S$3 -> 1 | T98: =(Q98/(R98*S98))/12 -> 108.9518
... A184: Year 176 | B184: 2200 | C184: =C183*(1-$C$5) -> 3.675452e-07 | D184: 4000 | E184: =D184*C184*1000000000 -> 1470180.8 | F184: =E184*(1-$F$3) -> 1462829.9 | G184: =100% -> 1 | H184: =F184*G184 -> 1462829.9 | I184: =I183+H184+N183 -> 4.42417e+14 | J184: =(J183+H184+N183)*(1-$J$3) -> 4.2041147e+14 | K184: =J183*$K$3 -> 2.6500377e+13 | L184: =F184*(1-G184) -> 0 | M184: =K184+L184 -> 2.6500377e+13 | N184: =M184*$N$5 -> 2.6500377e+12 | O184: =(M184-N184)*(1-$O$3) -> 2.3731088e+13 | P184: =$P$3 -> 1300000000000 | Q184: =O184-P184 -> 2.2431088e+13 | R184: =R183*99.9% -> 9.2109295e+09 | S184: =$S$3 -> 1 | T184: =(Q184/(R184*S184))/12 -> 202.93905
A186: Total CO2e extraction permitted by 2200 (gigatonnes) | C186: =SUM(C9:C184) -> 374 | D186: Total captured for the people of the world and to climate work | E186: =SUM(E8:E184) -> 3.4888209e+14 | G186: Total carbon charges placed in the Fund | H186: =SUM(H8:H184) -> 2.1360843e+14 | N186: Total distributed to the people of the world and to climate work | O186: =SUM(O8:O184) -> 2.585052e+15

Sheet Global 2 (1.6)
A1: Scenario 1: Cut extraction by 10% per year, $1 trillion climate grants
A2: Parameters | C2: Initial fossil fuel extraction cap (gigatonnes of CO2e) | D2: Initial carbon charge (per extracted tonne of CO2e) | F2: Running costs of Trust (% of charge money raised) | G2: Initial proportion of charge proceeds going into the Fund (% of total proceeds) | J2: Management costs of the Fund (% of total Fund capital expended) | K2: Assumed annual rate of return on Fund investments | N2: Year that money from distribution pot starts getting reinvested | O2: Distribution costs of the pot (% of total distributed) | P2: Amount of pot to be distributed as climate grants | R2: Initial global population expected in 2025 | S2: Proportion of global population to receive dividends
C3: 37.4 | D3: 144 | F3: 0.005 | G3: 0.1 | J3: 0.0005 | K3: 0.0634 | N3: 2075 | O3: 0.005 | P3: 1300000000000 | S3: 1
C4: Annual shrinkage of cap | D4: Annual growth of charge | G4: Initial annual increase in proportion going into the Fund (% of total proceeds) | H4: After 2035 annual increase in proportion going into the Fund (% of total proceeds) | I4: Starting endowment of the fund | N4: Maximum proportion that gets reinvested | P4: Alternatively, proportion of pot to be distributed as climate grants | S4: Description of segment of population to receive dividends
C5: 0.1 | D5: 0.164 | G5: 0.02 | H5: 0.02 | I5: 0 | N5: 0.1 | P5: 0 | S5: All adults and children worldwide
A7: From start | B7: Year | C7: Carbon cap (gigatonnes of CO2e) | D7: Carbon charge | E7: Amount raised | F7: Amount raised less 0.5% Trust costs | G7: Proportion of this amount going into the Fund | H7: Amount being placed in the Fund this year | I7: Total capital amount that would be in the Fund if there were no management costs | J7: Total capital amount in the Fund less cumulative 0.05% Fund management costs | K7: Investment income of the Fund this year | L7: Amount to be directly distributed (bypassing the Fund) | M7: Total amount in this year's pot for distribution | N7: Amount from distribution pot to go back into Fund for reinvestment | O7: Total distribution pot less 0.5% distribution costs, and less any amount going back to the Fund | P7: Amount to be distributed as climate grants | Q7: Amount left in pot after climate grants distribution | R7: Global population (projected for 1st January each year) | S7: Proportion of global population to receive dividends | T7: Monthly dividend per person
A9: Year 1 | B9: 2025 | C9: =C3 -> 37.4 | D9: =D3 -> 144 | E9: =D9*C9*1000000000 -> 5.3856e+12 | F9: =E9*(1-$F$3) -> 5.358672e+12 | G9: 0.1 | H9: =F9*G9 -> 5.358672e+11 | I9: =$I$5+H9 -> 5.358672e+11 | J9: =($I$5+H9*(1-$J$3)) -> 5.3559927e+11 | K9: =J8*$K$3 -> 0 | L9: =F9*(1-G9) -> 4.8228048e+12 | M9: =K9+L9 -> 4.8228048e+12 | O9: =(M9-N9)*(1-$O$3) -> 4.7986908e+12 | P9: =$P$3 -> 1300000000000 | Q9: =O9-P9 -> 3.4986908e+12 | R9: 8231613070 | S9: =$S$3 -> 1 | T9: =(Q9/(R9*S9))/12 -> 35.41925
A10: Year 2 | B10: 2026 | C10: =C9*(1-$C$5) -> 33.66 | D10: =D9*(1+$D$5) -> 167.616 | E10: =D10*C10*1000000000 -> 5.6419546e+12 | F10: =E10*(1-$F$3) -> 5.6137448e+12 | G10: 0.12 | H10: =F10*G10 -> 6.7364937e+11 | I10: =I9+H10 -> 1.2095166e+12 | J10: =(J9+H10)*(1-$J$3) -> 1.208644e+12 | K10: =J9*$K$3 -> 3.3956993e+10 | L10: =F10*(1-G10) -> 4.9400954e+12 | M10: =K10+L10 -> 4.9740524e+12 | O10: =(M10-N10)*(1-$O$3) -> 4.9491821e+12 | P10: =$P$3 -> 1300000000000 | Q10: =O10-P10 -> 3.6491821e+12 | R10: 8300678395 | S10: =$S$3 -> 1 | T10: =(Q10/(R10*S10))/12 -> 36.635381
A11: Year 3 | B11: 2027 | C11: =C10*(1-$C$5) -> 30.294 | D11: =D10*(1+$D$5) -> 195.10502 | E11: =D11*C11*1000000000 -> 5.9105116e+12 | F11: =E11*(1-$F$3) -> 5.880959e+12 | G11: =G10+$G$5 -> 0.14 | H11: =F11*G11 -> 8.2333427e+11 | I11: =I10+H11 -> 2.0328508e+12 | J11: =(J10+H11)*(1-$J$3) -> 2.0309623e+12 | K11: =J10*$K$3 -> 7.6628031e+10 | L11: =F11*(1-G11) -> 5.0576248e+12 | M11: =K11+L11 -> 5.1342528e+12 | O11: =(M11-N11)*(1-$O$3) -> 5.1085815e+12 | P11: =$P$3 -> 1300000000000 | Q11: =O11-P11 -> 3.8085815e+12 | R11: 8369094344 | S11: =$S$3 -> 1 | T11: =(Q11/(R11*S11))/12 -> 37.923075
A12: Year 4 | B12: 2028 | C12: =C11*(1-$C$5) -> 27.2646 | D12: =D11*(1+$D$5) -> 227.10225 | E12: =D12*C12*1000000000 -> 6.1918519e+12 | F12: =E12*(1-$F$3) -> 6.1608927e+12 | G12: =G11+$G$5 -> 0.16 | H12: =F12*G12 -> 9.8574283e+11 | I12: =I11+H12 -> 3.0185937e+12 | J12: =(J11+H12)*(1-$J$3) -> 3.0151968e+12 | K12: =J11*$K$3 -> 1.2876301e+11 | L12: =F12*(1-G12) -> 5.1751499e+12 | M12: =K12+L12 -> 5.3039129e+12 | O12: =(M12-N12)*(1-$O$3) -> 5.2773933e+12 | P12: =$P$3 -> 1300000000000 | Q12: =O12-P12 -> 3.9773933e+12 | R12: 8436618886 | S12: =$S$3 -> 1 | T12: =(Q12/(R12*S12))/12 -> 39.287
A13: Year 5 | B13: 2029 | C13: =C12*(1-$C$5) -> 24.53814 | D13: =D12*(1+$D$5) -> 264.34702 | E13: =D13*C13*1000000000 -> 6.4865841e+12 | F13: =E13*(1-$F$3) -> 6.4541512e+12 | G13: =G12+$G$5 -> 0.18 | H13: =F13*G13 -> 1.1617472e+12 | I13: =I12+H13 -> 4.1803409e+12 | J13: =(J12+H13)*(1-$J$3) -> 4.1748555e+12 | K13: =J12*$K$3 -> 1.9116348e+11 | L13: =F13*(1-G13) -> 5.292404e+12 | M13: =K13+L13 -> 5.4835674e+12 | O13: =(M13-N13)*(1-$O$3) -> 5.4561496e+12 | P13: =$P$3 -> 1300000000000 | Q13: =O13-P13 -> 4.1561496e+12 | R13: 8503285323 | S13: =$S$3 -> 1 | T13: =(Q13/(R13*S13))/12 -> 40.730822
A14: Year 6 | B14: 2030 | C14: =C13*(1-$C$5) -> 22.084326 | D14: =D13*(1+$D$5) -> 307.69993 | E14: =D14*C14*1000000000 -> 6.7953455e+12 | F14: =E14*(1-$F$3) -> 6.7613688e+12 | G14: =G13+$G$5 -> 0.2 | H14: =F14*G14 -> 1.3522738e+12 | I14: =I13+H14 -> 5.5326146e+12 | J14: =(J13+H14)*(1-$J$3) -> 5.5243657e+12 | K14: =J13*$K$3 -> 2.6468584e+11 | L14: =F14*(1-G14) -> 5.409095e+12 | M14: =K14+L14 -> 5.6737809e+12 | O14: =(M14-N14)*(1-$O$3) -> 5.645412e+12 | P14: =$P$3 -> 1300000000000 | Q14: =O14-P14 -> 4.345412e+12 | R14: 8569124911 | S14: =$S$3 -> 1 | T14: =(Q14/(R14*S14))/12 -> 42.258418
A15: Year 7 | B15: 2031 | C15: =C14*(1-$C$5) -> 19.875893 | D15: =D14*(1+$D$5) -> 358.16272 | E15: =D15*C15*1000000000 -> 7.118804e+12 | F15: =E15*(1-$F$3) -> 7.0832099e+12 | G15: =G14+$G$5 -> 0.22 | H15: =F15*G15 -> 1.5583062e+12 | I15: =I14+H15 -> 7.0909208e+12 | J15: =(J14+H15)*(1-$J$3) -> 7.0791306e+12 | K15: =J14*$K$3 -> 3.5024479e+11 | L15: =F15*(1-G15) -> 5.5249037e+12 | M15: =K15+L15 -> 5.8751485e+12 | O15: =(M15-N15)*(1-$O$3) -> 5.8457728e+12 | P15: =$P$3 -> 1300000000000 | Q15: =O15-P15 -> 4.5457728e+12 | R15: 8634119333 | S15: =$S$3 -> 1 | T15: =(Q15/(R15*S15))/12 -> 43.874121
A16: Year 8 | B16: 2032 | C16: =C15*(1-$C$5) -> 17.888304 | D16: =D15*(1+$D$5) -> 416.9014 | E16: =D16*C16*1000000000 -> 7.457659e+12 | F16: =E16*(1-$F$3) -> 7.4203707e+12 | G16: =G15+$G$5 -> 0.24 | H16: =F16*G16 -> 1.780889e+12 | I16: =I15+H16 -> 8.8718098e+12 | J16: =(J15+H16)*(1-$J$3) -> 8.8555895e+12 | K16: =J15*$K$3 -> 4.4881688e+11 | L16: =F16*(1-G16) -> 5.6394818e+12 | M16: =K16+L16 -> 6.0882986e+12 | O16: =(M16-N16)*(1-$O$3) -> 6.0578571e+12 | P16: =$P$3 -> 1300000000000 | Q16: =O16-P16 -> 4.7578571e+12 | R16: 8698229812 | S16: =$S$3 -> 1 | T16: =(Q16/(R16*S16))/12 -> 45.582619
A17: Year 9 | B17: 2033 | C17: =C16*(1-$C$5) -> 16.099474 | D17: =D16*(1+$D$5) -> 485.27323 | E17: =D17*C17*1000000000 -> 7.8126436e+12 | F17: =E17*(1-$F$3) -> 7.7735804e+12 | G17: =G16+$G$5 -> 0.26 | H17: =F17*G17 -> 2.0211309e+12 | I17: =I16+H17 -> 1.0892941e+13 | J17: =(J16+H17)*(1-$J$3) -> 1.0871282e+13 | K17: =J16*$K$3 -> 5.6144438e+11 | L17: =F17*(1-G17) -> 5.7524495e+12 | M17: =K17+L17 -> 6.3138938e+12 | O17: =(M17-N17)*(1-$O$3) -> 6.2823244e+12 | P17: =$P$3 -> 1300000000000 | Q17: =O17-P17 -> 4.9823244e+12 | R17: 8761449081 | S17: =$S$3 -> 1 | T17: =(Q17/(R17*S17))/12 -> 47.388702
A18: Year 10 | B18: 2034 | C18: =C17*(1-$C$5) -> 14.489526 | D18: =D17*(1+$D$5) -> 564.85804 | E18: =D18*C18*1000000000 -> 8.1845254e+12 | F18: =E18*(1-$F$3) -> 8.1436028e+12 | G18: =G17+$G$5 -> 0.28 | H18: =F18*G18 -> 2.2802088e+12 | I18: =I17+H18 -> 1.3173149e+13 | J18: =(J17+H18)*(1-$J$3) -> 1.3144915e+13 | K18: =J17*$K$3 -> 6.8923928e+11 | L18: =F18*(1-G18) -> 5.863394e+12 | M18: =K18+L18 -> 6.5526333e+12 | O18: =(M18-N18)*(1-$O$3) -> 6.5198701e+12 | P18: =$P$3 -> 1300000000000 | Q18: =O18-P18 -> 5.2198701e+12 | R18: 8823784909 | S18: =$S$3 -> 1 | T18: =(Q18/(R18*S18))/12 -> 49.297346
A19: Year 11 | B19: 2035 | C19: =C18*(1-$C$5) -> 13.040574 | D19: =D18*(1+$D$5) -> 657.49476 | E19: =D19*C19*1000000000 -> 8.5741088e+12 | F19: =E19*(1-$F$3) -> 8.5312383e+12 | G19: =G18+$G$5 -> 0.3 | H19: =F19*G19 -> 2.5593715e+12 | I19: =I18+H19 -> 1.5732521e+13 | J19: =(J18+H19)*(1-$J$3) -> 1.5696434e+13 | K19: =J18*$K$3 -> 8.3338762e+11 | L19: =F19*(1-G19) -> 5.9718668e+12 | M19: =K19+L19 -> 6.8052544e+12 | O19: =(M19-N19)*(1-$O$3) -> 6.7712281e+12 | P19: =$P$3 -> 1300000000000 | Q19: =O19-P19 -> 5.4712281e+12 | R19: 8885210181 | S19: =$S$3 -> 1 | T19: =(Q19/(R19*S19))/12 -> 51.314
A20: Year 12 | B20: 2036 | C20: =C19*(1-$C$5) -> 11.736516 | D20: =D19*(1+$D$5) -> 765.3239 | E20: =D20*C20*1000000000 -> 8.9822364e+12 | F20: =E20*(1-$F$3) -> 8.9373252e+12 | G20: 0.33 | H20: =F20*G20 -> 2.9493173e+12 | I20: =I19+H20 -> 1.8681838e+13 | J20: =(J19+H20)*(1-$J$3) -> 1.8636429e+13 | K20: =J19*$K$3 -> 9.9515394e+11 | L20: =F20*(1-G20) -> 5.9880079e+12 | M20: =K20+L20 -> 6.9831618e+12 | O20: =(M20-N20)*(1-$O$3) -> 6.948246e+12 | P20: =$P$3 -> 1300000000000 | Q20: =O20-P20 -> 5.648246e+12 | R20: 8945686614 | S20: =$S$3 -> 1 | T20: =(Q20/(R20*S20))/12 -> 52.616103
A21: Year 13 | B21: 2037 | C21: =C20*(1-$C$5) -> 10.562865 | D21: =D20*(1+$D$5) -> 890.83702 | E21: =D21*C21*1000000000 -> 9.4097909e+12 | F21: =E21*(1-$F$3) -> 9.3627419e+12 | G21: =G20+$H$5 -> 0.35 | H21: =F21*G21 -> 3.2769597e+12 | I21: =I20+H21 -> 2.1958798e+13 | J21: =(J20+H21)*(1-$J$3) -> 2.1902432e+13 | K21: =J20*$K$3 -> 1.1815496e+12 | L21: =F21*(1-G21) -> 6.0857822e+12 | M21: =K21+L21 -> 7.2673318e+12 | O21: =(M21-N21)*(1-$O$3) -> 7.2309952e+12 | P21: =$P$3 -> 1300000000000 | Q21: =O21-P21 -> 5.9309952e+12 | R21: 9005152624 | S21: =$S$3 -> 1 | T21: =(Q21/(R21*S21))/12 -> 54.885199
A22: Year 14 | B22: 2038 | C22: =C21*(1-$C$5) -> 9.5065782 | D22: =D21*(1+$D$5) -> 1036.9343 | E22: =D22*C22*1000000000 -> 9.8576969e+12 | F22: =E22*(1-$F$3) -> 9.8084084e+12 | G22: =G21+$H$5 -> 0.37 | H22: =F22*G22 -> 3.6291111e+12 | I22: =I21+H22 -> 2.5587909e+13 | J22: =(J21+H22)*(1-$J$3) -> 2.5518777e+13 | K22: =J21*$K$3 -> 1.3886142e+12 | L22: =F22*(1-G22) -> 6.1792973e+12 | M22: =K22+L22 -> 7.5679115e+12 | O22: =(M22-N22)*(1-$O$3) -> 7.5300719e+12 | P22: =$P$3 -> 1300000000000 | Q22: =O22-P22 -> 6.2300719e+12 | R22: 9063572926 | S22: =$S$3 -> 1 | T22: =(Q22/(R22*S22))/12 -> 57.281236
A23: Year 15 | B23: 2039 | C23: =C22*(1-$C$5) -> 8.5559204 | D23: =D22*(1+$D$5) -> 1206.9915 | E23: =D23*C23*1000000000 -> 1.0326923e+13 | F23: =E23*(1-$F$3) -> 1.0275289e+13 | G23: =G22+$H$5 -> 0.39 | H23: =F23*G23 -> 4.0073626e+12 | I23: =I22+H23 -> 2.9595272e+13 | J23: =(J22+H23)*(1-$J$3) -> 2.9511377e+13 | K23: =J22*$K$3 -> 1.6178905e+12 | L23: =F23*(1-G23) -> 6.2679261e+12 | M23: =K23+L23 -> 7.8858166e+12 | O23: =(M23-N23)*(1-$O$3) -> 7.8463875e+12 | P23: =$P$3 -> 1300000000000 | Q23: =O23-P23 -> 6.5463875e+12 | R23: 9120928380 | S23: =$S$3 -> 1 | T23: =(Q23/(R23*S23))/12 -> 59.811049
A24: Year 16 | B24: 2040 | C24: =C23*(1-$C$5) -> 7.7003283 | D24: =D23*(1+$D$5) -> 1404.9381 | E24: =D24*C24*1000000000 -> 1.0818485e+13 | F24: =E24*(1-$F$3) -> 1.0764392e+13 | G24: =G23+$H$5 -> 0.41 | H24: =F24*G24 -> 4.4134009e+12 | I24: =I23+H24 -> 3.4008673e+13 | J24: =(J23+H24)*(1-$J$3) -> 3.3907815e+13 | K24: =J23*$K$3 -> 1.8710213e+12 | L24: =F24*(1-G24) -> 6.3509915e+12 | M24: =K24+L24 -> 8.2220128e+12 | O24: =(M24-N24)*(1-$O$3) -> 8.1809027e+12 | P24: =$P$3 -> 1300000000000 | Q24: =O24-P24 -> 6.8809027e+12 | R24: 9177190203 | S24: =$S$3 -> 1 | T24: =(Q24/(R24*S24))/12 -> 62.481931
A25: Year 17 | B25: 2041 | C25: =C24*(1-$C$5) -> 6.9302955 | D25: =D24*(1+$D$5) -> 1635.348 | E25: =D25*C25*1000000000 -> 1.1333445e+13 | F25: =E25*(1-$F$3) -> 1.1276777e+13 | G25: =G24+$H$5 -> 0.43 | H25: =F25*G25 -> 4.8490143e+12 | I25: =I24+H25 -> 3.8857687e+13 | J25: =(J24+H25)*(1-$J$3) -> 3.8737451e+13 | K25: =J24*$K$3 -> 2.1497555e+12 | L25: =F25*(1-G25) -> 6.4277632e+12 | M25: =K25+L25 -> 8.5775187e+12 | O25: =(M25-N25)*(1-$O$3) -> 8.5346311e+12 | P25: =$P$3 -> 1300000000000 | Q25: =O25-P25 -> 7.2346311e+12 | R25: 9232281575 | S25: =$S$3 -> 1 | T25: =(Q25/(R25*S25))/12 -> 65.301943
A26: Year 18 | B26: 2042 | C26: =C25*(1-$C$5) -> 6.237266 | D26: =D25*(1+$D$5) -> 1903.545 | E26: =D26*C26*1000000000 -> 1.1872917e+13 | F26: =E26*(1-$F$3) -> 1.1813552e+13 | G26: =G25+$H$5 -> 0.45 | H26: =F26*G26 -> 5.3160984e+12 | I26: =I25+H26 -> 4.4173785e+13 | J26: =(J25+H26)*(1-$J$3) -> 4.4031523e+13 | K26: =J25*$K$3 -> 2.4559544e+12 | L26: =F26*(1-G26) -> 6.4974537e+12 | M26: =K26+L26 -> 8.9534081e+12 | O26: =(M26-N26)*(1-$O$3) -> 8.908641e+12 | P26: =$P$3 -> 1300000000000 | Q26: =O26-P26 -> 7.608641e+12 | R26: 9286110371 | S26: =$S$3 -> 1 | T26: =(Q26/(R26*S26))/12 -> 68.279763
A27: Year 19 | B27: 2043 | C27: =C26*(1-$C$5) -> 5.6135394 | D27: =D26*(1+$D$5) -> 2215.7264 | E27: =D27*C27*1000000000 -> 1.2438068e+13 | F27: =E27*(1-$F$3) -> 1.2375877e+13 | G27: =G26+$H$5 -> 0.47 | H27: =F27*G27 -> 5.8166623e+12 | I27: =I26+H27 -> 4.9990448e+13 | J27: =(J26+H27)*(1-$J$3) -> 4.9823261e+13 | K27: =J26*$K$3 -> 2.7915985e+12 | L27: =F27*(1-G27) -> 6.5592149e+12 | M27: =K27+L27 -> 9.3508134e+12 | O27: =(M27-N27)*(1-$O$3) -> 9.3040594e+12 | P27: =$P$3 -> 1300000000000 | Q27: =O27-P27 -> 8.0040594e+12 | R27: 9338661314 | S27: =$S$3 -> 1 | T27: =(Q27/(R27*S27))/12 -> 71.424043
A28: Year 20 | B28: 2044 | C28: =C27*(1-$C$5) -> 5.0521854 | D28: =D27*(1+$D$5) -> 2579.1056 | E28: =D28*C28*1000000000 -> 1.303012e+13 | F28: =E28*(1-$F$3) -> 1.2964969e+13 | G28: =G27+$H$5 -> 0.49 | H28: =F28*G28 -> 6.3528348e+12 | I28: =I27+H28 -> 5.6343282e+13 | J28: =(J27+H28)*(1-$J$3) -> 5.6148008e+13 | K28: =J27*$K$3 -> 3.1587947e+12 | L28: =F28*(1-G28) -> 6.6121342e+12 | M28: =K28+L28 -> 9.7709289e+12 | O28: =(M28-N28)*(1-$O$3) -> 9.7220743e+12 | P28: =$P$3 -> 1300000000000 | Q28: =O28-P28 -> 8.4220743e+12 | R28: 9389873693 | S28: =$S$3 -> 1 | T28: =(Q28/(R28*S28))/12 -> 74.744298
A29: Year 21 | B29: 2045 | C29: =C28*(1-$C$5) -> 4.5469669 | D29: 3000 | E29: =D29*C29*1000000000 -> 1.3640901e+13 | F29: =E29*(1-$F$3) -> 1.3572696e+13 | G29: =G28+$H$5 -> 0.51 | H29: =F29*G29 -> 6.922075e+12 | I29: =I28+H29 -> 6.3265357e+13 | J29: =(J28+H29)*(1-$J$3) -> 6.3038548e+13 | K29: =J28*$K$3 -> 3.5597837e+12 | L29: =F29*(1-G29) -> 6.6506211e+12 | M29: =K29+L29 -> 1.0210405e+13 | O29: =(M29-N29)*(1-$O$3) -> 1.0159353e+13 | P29: =$P$3 -> 1300000000000 | Q29: =O29-P29 -> 8.8593528e+12 | R29: 9439639668 | S29: =$S$3 -> 1 | T29: =(Q29/(R29*S29))/12 -> 78.210549
A30: Year 22 | B30: 2046 | C30: =C29*(1-$C$5) -> 4.0922702 | D30: =D29*(1+$D$5) -> 3492 | E30: =D30*C30*1000000000 -> 1.4290208e+13 | F30: =E30*(1-$F$3) -> 1.4218756e+13 | G30: =G29+$H$5 -> 0.53 | H30: =F30*G30 -> 7.5359409e+12 | I30: =I29+H30 -> 7.0801298e+13 | J30: =(J29+H30)*(1-$J$3) -> 7.0539201e+13 | K30: =J29*$K$3 -> 3.9966439e+12 | L30: =F30*(1-G30) -> 6.6828155e+12 | M30: =K30+L30 -> 1.0679459e+13 | O30: =(M30-N30)*(1-$O$3) -> 1.0626062e+13 | P30: =$P$3 -> 1300000000000 | Q30: =O30-P30 -> 9.3260622e+12 | R30: 9487889604 | S30: =$S$3 -> 1 | T30: =(Q30/(R30*S30))/12 -> 81.911983
A31: Year 23 | B31: 2047 | C31: =C30*(1-$C$5) -> 3.6830432 | D31: 4000 | E31: =D31*C31*1000000000 -> 1.4732173e+13 | F31: =E31*(1-$F$3) -> 1.4658512e+13 | G31: =G30+$H$5 -> 0.55 | H31: =F31*G31 -> 8.0621815e+12 | I31: =I30+H31 -> 7.886348e+13 | J31: =(J30+H31)*(1-$J$3) -> 7.8562082e+13 | K31: =J30*$K$3 -> 4.4721854e+12 | L31: =F31*(1-G31) -> 6.5963303e+12 | M31: =K31+L31 -> 1.1068516e+13 | O31: =(M31-N31)*(1-$O$3) -> 1.1013173e+13 | P31: =$P$3 -> 1300000000000 | Q31: =O31-P31 -> 9.7131731e+12 | R31: 9534545977 | S31: =$S$3 -> 1 | T31: =(Q31/(R31*S31))/12 -> 84.894561
A32: Year 24 | B32: 2048 | C32: =C31*(1-$C$5) -> 3.3147389 | D32: 4000 | E32: =D32*C32*1000000000 -> 1.3258955e+13 | F32: =E32*(1-$F$3) -> 1.3192661e+13 | G32: =G31+$H$5 -> 0.57 | H32: =F32*G32 -> 7.5198166e+12 | I32: =I31+H32 -> 8.6383296e+13 | J32: =(J31+H32)*(1-$J$3) -> 8.6038858e+13 | K32: =J31*$K$3 -> 4.980836e+12 | L32: =F32*(1-G32) -> 5.6728441e+12 | M32: =K32+L32 -> 1.065368e+13 | O32: =(M32-N32)*(1-$O$3) -> 1.0600412e+13 | P32: =$P$3 -> 1300000000000 | Q32: =O32-P32 -> 9.3004117e+12 | R32: 9579536043 | S32: =$S$3 -> 1 | T32: =(Q32/(R32*S32))/12 -> 80.905203
A33: Year 25 | B33: 2049 | C33: =C32*(1-$C$5) -> 2.983265 | D33: 4000 | E33: =D33*C33*1000000000 -> 1.193306e+13 | F33: =E33*(1-$F$3) -> 1.1873395e+13 | G33: =G32+$H$5 -> 0.59 | H33: =F33*G33 -> 7.0053028e+12 | I33: =I32+H33 -> 9.3388599e+13 | J33: =(J32+H33)*(1-$J$3) -> 9.2997639e+13 | K33: =J32*$K$3 -> 5.4548636e+12 | L33: =F33*(1-G33) -> 4.8680918e+12 | M33: =K33+L33 -> 1.0322955e+13 | O33: =(M33-N33)*(1-$O$3) -> 1.0271341e+13 | P33: =$P$3 -> 1300000000000 | Q33: =O33-P33 -> 8.9713406e+12 | R33: 9622824029 | S33: =$S$3 -> 1 | T33: =(Q33/(R33*S33))/12 -> 77.691509
A34: Year 26 | B34: 2050 | C34: =C33*(1-$C$5) -> 2.6849385 | D34: 4000 | E34: =D34*C34*1000000000 -> 1.0739754e+13 | F34: =E34*(1-$F$3) -> 1.0686055e+13 | G34: =G33+$H$5 -> 0.61 | H34: =F34*G34 -> 6.5184936e+12 | I34: =I33+H34 -> 9.9907093e+13 | J34: =(J33+H34)*(1-$J$3) -> 9.9466374e+13 | K34: =J33*$K$3 -> 5.8960503e+12 | L34: =F34*(1-G34) -> 4.1675615e+12 | M34: =K34+L34 -> 1.0063612e+13 | O34: =(M34-N34)*(1-$O$3) -> 1.0013294e+13 | P34: =$P$3 -> 1300000000000 | Q34: =O34-P34 -> 8.7132937e+12 | R34: 9664378587 | S34: =$S$3 -> 1 | T34: =(Q34/(R34*S34))/12 -> 75.132385
A35: Year 27 | B35: 2051 | C35: 0.1 | D35: 4000 | E35: =D35*C35*1000000000 -> 400000000000 | F35: =E35*(1-$F$3) -> 398000000000 | G35: =G34+$H$5 -> 0.63 | H35: =F35*G35 -> 2.5074e+11 | I35: =I34+H35 -> 1.0015783e+14 | J35: =(J34+H35)*(1-$J$3) -> 9.9667256e+13 | K35: =J34*$K$3 -> 6.3061681e+12 | L35: =F35*(1-G35) -> 1.4726e+11 | M35: =K35+L35 -> 6.4534281e+12 | O35: =(M35-N35)*(1-$O$3) -> 6.421161e+12 | Q35: =O35-P35 -> 6.421161e+12 | R35: 9704192304 | S35: =$S$3 -> 1 | T35: =(Q35/(R35*S35))/12 -> 55.140782
A36: Year 28 | B36: 2052 | C36: =C35*(1-$C$5) -> 0.09 | D36: 4000 | E36: =D36*C36*1000000000 -> 3.6e+11 | F36: =E36*(1-$F$3) -> 3.582e+11 | G36: =G35+$H$5 -> 0.65 | H36: =F36*G36 -> 2.3283e+11 | I36: =I35+H36 -> 1.0039066e+14 | J36: =(J35+H36)*(1-$J$3) -> 9.9850136e+13 | K36: =J35*$K$3 -> 6.318904e+12 | L36: =F36*(1-G36) -> 1.2537e+11 | M36: =K36+L36 -> 6.444274e+12 | O36: =(M36-N36)*(1-$O$3) -> 6.4120526e+12 | Q36: =O36-P36 -> 6.4120526e+12 | R36: 9742264515 | S36: =$S$3 -> 1 | T36: =(Q36/(R36*S36))/12 -> 54.847384
A37: Year 29 | B37: 2053 | C37: =C36*(1-$C$5) -> 0.081 | D37: 4000 | E37: =D37*C37*1000000000 -> 3.24e+11 | F37: =E37*(1-$F$3) -> 3.2238e+11 | G37: =G36+$H$5 -> 0.67 | H37: =F37*G37 -> 2.159946e+11 | I37: =I36+H37 -> 1.0060666e+14 | J37: =(J36+H37)*(1-$J$3) -> 1.000161e+14 | K37: =J36*$K$3 -> 6.3304986e+12 | L37: =F37*(1-G37) -> 1.063854e+11 | M37: =K37+L37 -> 6.436884e+12 | O37: =(M37-N37)*(1-$O$3) -> 6.4046996e+12 | Q37: =O37-P37 -> 6.4046996e+12 | R37: 9778614614 | S37: =$S$3 -> 1 | T37: =(Q37/(R37*S37))/12 -> 54.580836
A38: Year 30 | B38: 2054 | C38: =C37*(1-$C$5) -> 0.0729 | D38: 4000 | E38: =D38*C38*1000000000 -> 2.916e+11 | F38: =E38*(1-$F$3) -> 2.90142e+11 | G38: =G37+$H$5 -> 0.69 | H38: =F38*G38 -> 2.0019798e+11 | I38: =I37+H38 -> 1.0080686e+14 | J38: =(J37+H38)*(1-$J$3) -> 1.0016619e+14 | K38: =J37*$K$3 -> 6.3410206e+12 | L38: =F38*(1-G38) -> 8.994402e+10 | M38: =K38+L38 -> 6.4309646e+12 | O38: =(M38-N38)*(1-$O$3) -> 6.3988097e+12 | Q38: =O38-P38 -> 6.3988097e+12 | R38: 9813251659 | S38: =$S$3 -> 1 | T38: =(Q38/(R38*S38))/12 -> 54.338171
A39: Year 31 | B39: 2055 | C39: =C38*(1-$C$5) -> 0.06561 | D39: 4000 | E39: =D39*C39*1000000000 -> 2.6244e+11 | F39: =E39*(1-$F$3) -> 2.611278e+11 | G39: =G38+$H$5 -> 0.71 | H39: =F39*G39 -> 1.8540074e+11 | I39: =I38+H39 -> 1.0099226e+14 | J39: =(J38+H39)*(1-$J$3) -> 1.0030141e+14 | K39: =J38*$K$3 -> 6.3505362e+12 | L39: =F39*(1-G39) -> 7.5727062e+10 | M39: =K39+L39 -> 6.4262633e+12 | O39: =(M39-N39)*(1-$O$3) -> 6.394132e+12 | Q39: =O39-P39 -> 6.394132e+12 | R39: 9846237570 | S39: =$S$3 -> 1 | T39: =(Q39/(R39*S39))/12 -> 54.116542
A40: Year 32 | B40: 2056 | C40: =C39*(1-$C$5) -> 0.059049 | D40: 4000 | E40: =D40*C40*1000000000 -> 2.36196e+11 | F40: =E40*(1-$F$3) -> 2.3501502e+11 | G40: =G39+$H$5 -> 0.73 | H40: =F40*G40 -> 1.7156096e+11 | I40: =I39+H40 -> 1.0116382e+14 | J40: =(J39+H40)*(1-$J$3) -> 1.0042274e+14 | K40: =J39*$K$3 -> 6.3591095e+12 | L40: =F40*(1-G40) -> 6.3454055e+10 | M40: =K40+L40 -> 6.4225636e+12 | O40: =(M40-N40)*(1-$O$3) -> 6.3904507e+12 | Q40: =O40-P40 -> 6.3904507e+12 | R40: 9877680392 | S40: =$S$3 -> 1 | T40: =(Q40/(R40*S40))/12 -> 53.913221
A41: Year 33 | B41: 2057 | C41: =C40*(1-$C$5) -> 0.0531441 | D41: 4000 | E41: =D41*C41*1000000000 -> 2.125764e+11 | F41: =E41*(1-$F$3) -> 2.1151352e+11 | G41: =G40+$H$5 -> 0.75 | H41: =F41*G41 -> 1.5863514e+11 | I41: =I40+H41 -> 1.0132245e+14 | J41: =(J40+H41)*(1-$J$3) -> 1.0053108e+14 | K41: =J40*$K$3 -> 6.3668015e+12 | L41: =F41*(1-G41) -> 5.2878379e+10 | M41: =K41+L41 -> 6.4196799e+12 | N41: =M41*0% -> 0 | O41: =(M41-N41)*(1-$O$3) -> 6.3875815e+12 | Q41: =O41-P41 -> 6.3875815e+12 | R41: 9907637193 | S41: =$S$3 -> 1 | T41: =(Q41/(R41*S41))/12 -> 53.726075
A42: Year 34 | B42: 2058 | C42: =C41*(1-$C$5) -> 0.04782969 | D42: 4000 | E42: =D42*C42*1000000000 -> 1.9131876e+11 | F42: =E42*(1-$F$3) -> 1.9036217e+11 | G42: =G41+$H$5 -> 0.77 | H42: =F42*G42 -> 1.4657887e+11 | I42: =I41+H42 -> 1.0146903e+14 | J42: =(J41+H42)*(1-$J$3) -> 1.0062732e+14 | K42: =J41*$K$3 -> 6.3736705e+12 | L42: =F42*(1-G42) -> 4.3783298e+10 | M42: =K42+L42 -> 6.4174538e+12 | N42: =M42*0.4% -> 2.5669815e+10 | O42: =(M42-N42)*(1-$O$3) -> 6.3598251e+12 | Q42: =O42-P42 -> 6.3598251e+12 | R42: 9936164379 | S42: =$S$3 -> 1 | T42: =(Q42/(R42*S42))/12 -> 53.339035
A43: Year 35 | B43: 2059 | C43: =C42*(1-$C$5) -> 0.043046721 | D43: 4000 | E43: =D43*C43*1000000000 -> 1.7218688e+11 | F43: =E43*(1-$F$3) -> 1.7132595e+11 | G43: =G42+$H$5 -> 0.79 | H43: =F43*G43 -> 1.353475e+11 | I43: =I42+H43 -> 1.0160438e+14 | J43: =(J42+H43)*(1-$J$3) -> 1.0071229e+14 | K43: =J42*$K$3 -> 6.3797721e+12 | L43: =F43*(1-G43) -> 3.5978449e+10 | M43: =K43+L43 -> 6.4157506e+12 | N43: =M43*0.6% -> 3.8494504e+10 | O43: =(M43-N43)*(1-$O$3) -> 6.3453698e+12 | Q43: =O43-P43 -> 6.3453698e+12 | R43: 9963337082 | S43: =$S$3 -> 1 | T43: =(Q43/(R43*S43))/12 -> 53.072662
A44: Year 36 | B44: 2060 | C44: =C43*(1-$C$5) -> 0.038742049 | D44: 4000 | E44: =D44*C44*1000000000 -> 1.549682e+11 | F44: =E44*(1-$F$3) -> 1.5419335e+11 | G44: =G43+$H$5 -> 0.81 | H44: =F44*G44 -> 1.2489662e+11 | I44: =I43+H44 -> 1.0172928e+14 | J44: =(J43+H44)*(1-$J$3) -> 1.0078676e+14 | K44: =J43*$K$3 -> 6.385159e+12 | L44: =F44*(1-G44) -> 2.9296737e+10 | M44: =K44+L44 -> 6.4144557e+12 | N44: =M44*0.8% -> 5.1315646e+10 | O44: =(M44-N44)*(1-$O$3) -> 6.3313244e+12 | Q44: =O44-P44 -> 6.3313244e+12 | R44: 9989232292 | S44: =$S$3 -> 1 | T44: =(Q44/(R44*S44))/12 -> 52.817909
A45: Year 37 | B45: 2061 | C45: =C44*(1-$C$5) -> 0.034867844 | D45: 4000 | E45: =D45*C45*1000000000 -> 1.3947138e+11 | F45: =E45*(1-$F$3) -> 1.3877402e+11 | G45: =G44+$H$5 -> 0.83 | H45: =F45*G45 -> 1.1518244e+11 | I45: =I44+H45 -> 1.0184446e+14 | J45: =(J44+H45)*(1-$J$3) -> 1.008515e+14 | K45: =J44*$K$3 -> 6.3898809e+12 | L45: =F45*(1-G45) -> 2.3591583e+10 | M45: =K45+L45 -> 6.4134725e+12 | N45: =M45*1% -> 6.4134725e+10 | O45: =(M45-N45)*(1-$O$3) -> 6.3175911e+12 | Q45: =O45-P45 -> 6.3175911e+12 | R45: 10013916213 | S45: =$S$3 -> 1 | T45: =(Q45/(R45*S45))/12 -> 52.57343
A46: Year 38 | B46: 2062 | C46: =C45*(1-$C$5) -> 0.03138106 | D46: 4000 | E46: =D46*C46*1000000000 -> 1.2552424e+11 | F46: =E46*(1-$F$3) -> 1.2489662e+11 | G46: =G45+$H$5 -> 0.85 | H46: =F46*G46 -> 1.0616212e+11 | I46: =I45+H46 -> 1.0195062e+14 | J46: =(J45+H46)*(1-$J$3) -> 1.0090718e+14 | K46: =J45*$K$3 -> 6.3939849e+12 | L46: =F46*(1-G46) -> 1.8734493e+10 | M46: =K46+L46 -> 6.4127194e+12 | N46: =M46*1.2% -> 7.6952632e+10 | O46: =(M46-N46)*(1-$O$3) -> 6.3040879e+12 | Q46: =O46-P46 -> 6.3040879e+12 | R46: 10037466600 | S46: =$S$3 -> 1 | T46: =(Q46/(R46*S46))/12 -> 52.337973
A47: Year 39 | B47: 2063 | C47: =C46*(1-$C$5) -> 0.028242954 | D47: 4000 | E47: =D47*C47*1000000000 -> 1.1297181e+11 | F47: =E47*(1-$F$3) -> 1.1240696e+11 | G47: =G46+$H$5 -> 0.87 | H47: =F47*G47 -> 9.7794051e+10 | I47: =I46+H47 -> 1.0204841e+14 | J47: =(J46+H47)*(1-$J$3) -> 1.0095447e+14 | K47: =J46*$K$3 -> 6.3975152e+12 | L47: =F47*(1-G47) -> 1.4612904e+10 | M47: =K47+L47 -> 6.4121281e+12 | N47: =M47*1.4% -> 8.9769793e+10 | O47: =(M47-N47)*(1-$O$3) -> 6.2907465e+12 | Q47: =O47-P47 -> 6.2907465e+12 | R47: 10059950035 | S47: =$S$3 -> 1 | T47: =(Q47/(R47*S47))/12 -> 52.110485
A48: Year 40 | B48: 2064 | C48: =C47*(1-$C$5) -> 0.025418658 | D48: 4000 | E48: =D48*C48*1000000000 -> 1.0167463e+11 | F48: =E48*(1-$F$3) -> 1.0116626e+11 | G48: =G47+$H$5 -> 0.89 | H48: =F48*G48 -> 9.0037971e+10 | I48: =I47+H48 -> 1.0213845e+14 | J48: =(J47+H48)*(1-$J$3) -> 1.0099399e+14 | K48: =J47*$K$3 -> 6.4005135e+12 | L48: =F48*(1-G48) -> 1.1128289e+10 | M48: =K48+L48 -> 6.4116418e+12 | N48: =M48*1.6% -> 1.0258627e+11 | O48: =(M48-N48)*(1-$O$3) -> 6.2775102e+12 | Q48: =O48-P48 -> 6.2775102e+12 | R48: 10081402737 | S48: =$S$3 -> 1 | T48: =(Q48/(R48*S48))/12 -> 51.890185
A49: Year 41 | B49: 2065 | C49: =C48*(1-$C$5) -> 0.022876792 | D49: 4000 | E49: =D49*C49*1000000000 -> 9.150717e+10 | F49: =E49*(1-$F$3) -> 9.1049634e+10 | G49: =G48+$H$5 -> 0.91 | H49: =F49*G49 -> 8.2855167e+10 | I49: =I48+H49 -> 1.0222131e+14 | J49: =(J48+H49)*(1-$J$3) -> 1.010263e+14 | K49: =J48*$K$3 -> 6.4030188e+12 | L49: =F49*(1-G49) -> 8.1944671e+09 | M49: =K49+L49 -> 6.4112132e+12 | N49: =M49*1.8% -> 1.1540184e+11 | O49: =(M49-N49)*(1-$O$3) -> 6.2643323e+12 | Q49: =O49-P49 -> 6.2643323e+12 | R49: 10101849561 | S49: =$S$3 -> 1 | T49: =(Q49/(R49*S49))/12 -> 51.676447
A50: Year 42 | B50: 2066 | C50: =C49*(1-$C$5) -> 0.020589113 | D50: 4000 | E50: =D50*C50*1000000000 -> 8.2356453e+10 | F50: =E50*(1-$F$3) -> 8.1944671e+10 | G50: =G49+$H$5 -> 0.93 | H50: =F50*G50 -> 7.6208544e+10 | I50: =I49+H50 -> 1.0229752e+14 | J50: =(J49+H50)*(1-$J$3) -> 1.0105196e+14 | K50: =J49*$K$3 -> 6.4050677e+12 | L50: =F50*(1-G50) -> 5.7361269e+09 | M50: =K50+L50 -> 6.4108038e+12 | N50: =M50*2% -> 1.2821608e+11 | O50: =(M50-N50)*(1-$O$3) -> 6.2511748e+12 | Q50: =O50-P50 -> 6.2511748e+12 | R50: 10121317107 | S50: =$S$3 -> 1 | T50: =(Q50/(R50*S50))/12 -> 51.468719
A51: Year 43 | B51: 2067 | C51: =C50*(1-$C$5) -> 0.018530202 | D51: 4000 | E51: =D51*C51*1000000000 -> 7.4120808e+10 | F51: =E51*(1-$F$3) -> 7.3750204e+10 | G51: =G50+$H$5 -> 0.95 | H51: =F51*G51 -> 7.0062693e+10 | I51: =I50+H51 -> 1.0236758e+14 | J51: =(J50+H51)*(1-$J$3) -> 1.0107146e+14 | K51: =J50*$K$3 -> 6.4066943e+12 | L51: =F51*(1-G51) -> 3.6875102e+09 | M51: =K51+L51 -> 6.4103818e+12 | N51: =M51*2.2% -> 1.410284e+11 | O51: =(M51-N51)*(1-$O$3) -> 6.2380067e+12 | Q51: =O51-P51 -> 6.2380067e+12 | R51: 10139808361 | S51: =$S$3 -> 1 | T51: =(Q51/(R51*S51))/12 -> 51.266638
A52: Year 44 | B52: 2068 | C52: =C51*(1-$C$5) -> 0.016677182 | D52: 4000 | E52: =D52*C52*1000000000 -> 6.6708727e+10 | F52: =E52*(1-$F$3) -> 6.6375183e+10 | G52: =G51+$H$5 -> 0.97 | H52: =F52*G52 -> 6.4383928e+10 | I52: =I51+H52 -> 1.0243196e+14 | J52: =(J51+H52)*(1-$J$3) -> 1.0108528e+14 | K52: =J51*$K$3 -> 6.4079307e+12 | L52: =F52*(1-G52) -> 1.9912555e+09 | M52: =K52+L52 -> 6.409922e+12 | N52: =M52*2.4% -> 1.5383813e+11 | O52: =(M52-N52)*(1-$O$3) -> 6.2248034e+12 | Q52: =O52-P52 -> 6.2248034e+12 | R52: 10157301941 | S52: =$S$3 -> 1 | T52: =(Q52/(R52*S52))/12 -> 51.070021
A53: Year 45 | B53: 2069 | C53: =C52*(1-$C$5) -> 0.015009464 | D53: 4000 | E53: =D53*C53*1000000000 -> 6.0037854e+10 | F53: =E53*(1-$F$3) -> 5.9737665e+10 | G53: =G52+$H$5 -> 0.99 | H53: =F53*G53 -> 5.9140288e+10 | I53: =I52+H53 -> 1.024911e+14 | J53: =(J52+H53)*(1-$J$3) -> 1.0109385e+14 | K53: =J52*$K$3 -> 6.4088067e+12 | L53: =F53*(1-G53) -> 5.9737665e+08 | M53: =K53+L53 -> 6.409404e+12 | N53: =M53*2.6% -> 1.6664451e+11 | O53: =(M53-N53)*(1-$O$3) -> 6.2115457e+12 | Q53: =O53-P53 -> 6.2115457e+12 | R53: 10173782135 | S53: =$S$3 -> 1 | T53: =(Q53/(R53*S53))/12 -> 50.8787
A54: Year 46 | B54: 2070 | C54: =C53*(1-$C$5) -> 0.013508517 | D54: 4000 | E54: =D54*C54*1000000000 -> 5.4034069e+10 | F54: =E54*(1-$F$3) -> 5.3763898e+10 | G54: 1 | H54: =F54*G54 -> 5.3763898e+10 | I54: =I53+H54 -> 1.0254487e+14 | J54: =(J53+H54)*(1-$J$3) -> 1.0109704e+14 | K54: =J53*$K$3 -> 6.4093499e+12 | L54: =F54*(1-G54) -> 0 | M54: =K54+L54 -> 6.4093499e+12 | N54: =M54*2.8% -> 1.794618e+11 | O54: =(M54-N54)*(1-$O$3) -> 6.1987387e+12 | Q54: =O54-P54 -> 6.1987387e+12 | R54: 10189241959 | S54: =$S$3 -> 1 | T54: =(Q54/(R54*S54))/12 -> 50.69676
A55: Year 47 | B55: 2071 | C55: =C54*(1-$C$5) -> 0.012157665 | D55: 4000 | E55: =D55*C55*1000000000 -> 4.8630662e+10 | F55: =E55*(1-$F$3) -> 4.8387509e+10 | G55: 1 | H55: =F55*G55 -> 4.8387509e+10 | I55: =I54+H55 -> 1.0259325e+14 | J55: =(J54+H55)*(1-$J$3) -> 1.0109485e+14 | K55: =J54*$K$3 -> 6.4095521e+12 | L55: =F55*(1-G55) -> 0 | M55: =K55+L55 -> 6.4095521e+12 | N55: =M55*3% -> 1.9228656e+11 | O55: =(M55-N55)*(1-$O$3) -> 6.1861792e+12 | Q55: =O55-P55 -> 6.1861792e+12 | R55: 10203681568 | S55: =$S$3 -> 1 | T55: =(Q55/(R55*S55))/12 -> 50.522445
A56: Year 48 | B56: 2072 | C56: =C55*(1-$C$5) -> 0.010941899 | D56: 4000 | E56: =D56*C56*1000000000 -> 4.3767596e+10 | F56: =E56*(1-$F$3) -> 4.3548758e+10 | G56: 1 | H56: =F56*G56 -> 4.3548758e+10 | I56: =I55+H56 -> 1.026368e+14 | J56: =(J55+H56)*(1-$J$3) -> 1.0108783e+14 | K56: =J55*$K$3 -> 6.4094136e+12 | L56: =F56*(1-G56) -> 0 | M56: =K56+L56 -> 6.4094136e+12 | N56: =M56*3.2% -> 2.0510124e+11 | O56: =(M56-N56)*(1-$O$3) -> 6.1732908e+12 | Q56: =O56-P56 -> 6.1732908e+12 | R56: 10217055169 | S56: =$S$3 -> 1 | T56: =(Q56/(R56*S56))/12 -> 50.351191
A57: Year 49 | B57: 2073 | C57: =C56*(1-$C$5) -> 0.009847709 | D57: 4000 | E57: =D57*C57*1000000000 -> 3.9390836e+10 | F57: =E57*(1-$F$3) -> 3.9193882e+10 | G57: 1 | H57: =F57*G57 -> 3.9193882e+10 | I57: =I56+H57 -> 1.02676e+14 | J57: =(J56+H57)*(1-$J$3) -> 1.0107646e+14 | K57: =J56*$K$3 -> 6.4089685e+12 | L57: =F57*(1-G57) -> 0 | M57: =K57+L57 -> 6.4089685e+12 | N57: =M57*3.4% -> 2.1790493e+11 | O57: =(M57-N57)*(1-$O$3) -> 6.1601083e+12 | Q57: =O57-P57 -> 6.1601083e+12 | R57: 10229327824 | S57: =$S$3 -> 1 | T57: =(Q57/(R57*S57))/12 -> 50.183391
A58: Year 50 | B58: 2074 | C58: =C57*(1-$C$5) -> 0.0088629381 | D58: 4000 | E58: =D58*C58*1000000000 -> 3.5451752e+10 | F58: =E58*(1-$F$3) -> 3.5274494e+10 | G58: 1 | H58: =F58*G58 -> 3.5274494e+10 | I58: =I57+H58 -> 1.0271127e+14 | J58: =(J57+H58)*(1-$J$3) -> 1.0106118e+14 | K58: =J57*$K$3 -> 6.4082477e+12 | L58: =F58*(1-G58) -> 0 | M58: =K58+L58 -> 6.4082477e+12 | N58: =M58*3.6% -> 2.3069692e+11 | O58: =(M58-N58)*(1-$O$3) -> 6.146663e+12 | Q58: =O58-P58 -> 6.146663e+12 | R58: 10240485056 | S58: =$S$3 -> 1 | T58: =(Q58/(R58*S58))/12 -> 50.019302
A59: Year 51 | B59: 2075 | C59: =C58*(1-$C$5) -> 0.0079766443 | D59: 4000 | E59: =D59*C59*1000000000 -> 3.1906577e+10 | F59: =E59*(1-$F$3) -> 3.1747044e+10 | G59: 1 | H59: =F59*G59 -> 3.1747044e+10 | I59: =I58+H59 -> 1.0274302e+14 | J59: =(J58+H59)*(1-$J$3) -> 1.0104238e+14 | K59: =J58*$K$3 -> 6.4072788e+12 | L59: =F59*(1-G59) -> 0 | M59: =K59+L59 -> 6.4072788e+12 | N59: =M59*3.8% -> 2.434766e+11 | O59: =(M59-N59)*(1-$O$3) -> 6.1329832e+12 | Q59: =O59-P59 -> 6.1329832e+12 | R59: 10250496432 | S59: =$S$3 -> 1 | T59: =(Q59/(R59*S59))/12 -> 49.859237
A60: Year 52 | B60: 2076 | C60: =C59*(1-$C$5) -> 0.0071789799 | D60: 4000 | E60: =D60*C60*1000000000 -> 2.871592e+10 | F60: =E60*(1-$F$3) -> 2.857234e+10 | G60: =100% -> 1 | H60: =F60*G60 -> 2.857234e+10 | I60: =I59+H60+N59 -> 1.0301507e+14 | J60: =(J59+H60)*(1-$J$3) -> 1.0102042e+14 | K60: =J59*$K$3 -> 6.4060869e+12 | L60: =F60*(1-G60) -> 0 | M60: =K60+L60 -> 6.4060869e+12 | N60: =M60*4% -> 2.5624348e+11 | O60: =(M60-N60)*(1-$O$3) -> 6.1190942e+12 | Q60: =O60-P60 -> 6.1190942e+12 | R60: 10259351432 | S60: =$S$3 -> 1 | T60: =(Q60/(R60*S60))/12 -> 49.703388
A61: Year 53 | B61: 2077 | C61: =C60*(1-$C$5) -> 0.0064610819 | D61: 4000 | E61: =D61*C61*1000000000 -> 2.5844328e+10 | F61: =E61*(1-$F$3) -> 2.5715106e+10 | G61: =100% -> 1 | H61: =F61*G61 -> 2.5715106e+10 | I61: =I60+H61+N60 -> 1.0329703e+14 | J61: =(J60+H61+N60)*(1-$J$3) -> 1.0125173e+14 | K61: =J60*$K$3 -> 6.4046945e+12 | L61: =F61*(1-G61) -> 0 | M61: =K61+L61 -> 6.4046945e+12 | N61: =M61*4.5% -> 2.8821125e+11 | O61: =(M61-N61)*(1-$O$3) -> 6.0859008e+12 | Q61: =O61-P61 -> 6.0859008e+12 | R61: 10267045023 | S61: =$S$3 -> 1 | T61: =(Q61/(R61*S61))/12 -> 49.396725
A62: Year 54 | B62: 2078 | C62: =C61*(1-$C$5) -> 0.0058149737 | D62: 4000 | E62: =D62*C62*1000000000 -> 2.3259895e+10 | F62: =E62*(1-$F$3) -> 2.3143595e+10 | G62: =100% -> 1 | H62: =F62*G62 -> 2.3143595e+10 | I62: =I61+H62+N61 -> 1.0360838e+14 | J62: =(J61+H62+N61)*(1-$J$3) -> 1.015123e+14 | K62: =J61*$K$3 -> 6.4193594e+12 | L62: =F62*(1-G62) -> 0 | M62: =K62+L62 -> 6.4193594e+12 | N62: =M62*5% -> 3.2096797e+11 | O62: =(M62-N62)*(1-$O$3) -> 6.0678994e+12 | Q62: =O62-P62 -> 6.0678994e+12 | R62: 10273556322 | S62: =$S$3 -> 1 | T62: =(Q62/(R62*S62))/12 -> 49.219401
A63: Year 55 | B63: 2079 | C63: =C62*(1-$C$5) -> 0.0052334763 | D63: 4000 | E63: =D63*C63*1000000000 -> 2.0933905e+10 | F63: =E63*(1-$F$3) -> 2.0829236e+10 | G63: =100% -> 1 | H63: =F63*G63 -> 2.0829236e+10 | I63: =I62+H63+N62 -> 1.0395018e+14 | J63: =(J62+H63+N62)*(1-$J$3) -> 1.0180317e+14 | K63: =J62*$K$3 -> 6.4358797e+12 | L63: =F63*(1-G63) -> 0 | M63: =K63+L63 -> 6.4358797e+12 | N63: =M63*5.5% -> 3.5397338e+11 | O63: =(M63-N63)*(1-$O$3) -> 6.0514968e+12 | Q63: =O63-P63 -> 6.0514968e+12 | R63: 10278887473 | S63: =$S$3 -> 1 | T63: =(Q63/(R63*S63))/12 -> 49.060893
A64: Year 56 | B64: 2080 | C64: =C63*(1-$C$5) -> 0.0047101287 | D64: 4000 | E64: =D64*C64*1000000000 -> 1.8840515e+10 | F64: =E64*(1-$F$3) -> 1.8746312e+10 | G64: =100% -> 1 | H64: =F64*G64 -> 1.8746312e+10 | I64: =I63+H64+N63 -> 1.043229e+14 | J64: =(J63+H64+N63)*(1-$J$3) -> 1.021248e+14 | K64: =J63*$K$3 -> 6.4543209e+12 | L64: =F64*(1-G64) -> 0 | M64: =K64+L64 -> 6.4543209e+12 | N64: =M64*6% -> 3.8725925e+11 | O64: =(M64-N64)*(1-$O$3) -> 6.0367263e+12 | Q64: =O64-P64 -> 6.0367263e+12 | R64: 10283078029 | S64: =$S$3 -> 1 | T64: =(Q64/(R64*S64))/12 -> 48.921201
A65: Year 57 | B65: 2081 | C65: =C64*(1-$C$5) -> 0.0042391158 | D65: 4000 | E65: =D65*C65*1000000000 -> 1.6956463e+10 | F65: =E65*(1-$F$3) -> 1.6871681e+10 | G65: =100% -> 1 | H65: =F65*G65 -> 1.6871681e+10 | I65: =I64+H65+N64 -> 1.0472703e+14 | J65: =(J64+H65+N64)*(1-$J$3) -> 1.0247767e+14 | K65: =J64*$K$3 -> 6.4747123e+12 | L65: =F65*(1-G65) -> 0 | M65: =K65+L65 -> 6.4747123e+12 | N65: =M65*6.5% -> 4.208563e+11 | O65: =(M65-N65)*(1-$O$3) -> 6.0235868e+12 | Q65: =O65-P65 -> 6.0235868e+12 | R65: 10286161735 | S65: =$S$3 -> 1 | T65: =(Q65/(R65*S65))/12 -> 48.800085
A66: Year 58 | B66: 2082 | C66: =C65*(1-$C$5) -> 0.0038152042 | D66: 4000 | E66: =D66*C66*1000000000 -> 1.5260817e+10 | F66: =E66*(1-$F$3) -> 1.5184513e+10 | G66: =100% -> 1 | H66: =F66*G66 -> 1.5184513e+10 | I66: =I65+H66+N65 -> 1.0516307e+14 | J66: =(J65+H66+N65)*(1-$J$3) -> 1.0286225e+14 | K66: =J65*$K$3 -> 6.4970841e+12 | L66: =F66*(1-G66) -> 0 | M66: =K66+L66 -> 6.4970841e+12 | N66: =M66*7% -> 4.5479589e+11 | O66: =(M66-N66)*(1-$O$3) -> 6.0120767e+12 | Q66: =O66-P66 -> 6.0120767e+12 | R66: 10288205050 | S66: =$S$3 -> 1 | T66: =(Q66/(R66*S66))/12 -> 48.697163
A67: Year 59 | B67: 2083 | C67: =C66*(1-$C$5) -> 0.0034336838 | D67: 4000 | E67: =D67*C67*1000000000 -> 1.3734735e+10 | F67: =E67*(1-$F$3) -> 1.3666062e+10 | G67: =100% -> 1 | H67: =F67*G67 -> 1.3666062e+10 | I67: =I66+H67+N66 -> 1.0563153e+14 | J67: =(J66+H67+N66)*(1-$J$3) -> 1.0327905e+14 | K67: =J66*$K$3 -> 6.5214667e+12 | L67: =F67*(1-G67) -> 0 | M67: =K67+L67 -> 6.5214667e+12 | N67: =M67*7.5% -> 4.8911e+11 | O67: =(M67-N67)*(1-$O$3) -> 6.0021949e+12 | Q67: =O67-P67 -> 6.0021949e+12 | R67: 10289247323 | S67: =$S$3 -> 1 | T67: =(Q67/(R67*S67))/12 -> 48.612196
A68: Year 60 | B68: 2084 | C68: =C67*(1-$C$5) -> 0.0030903154 | D68: 4000 | E68: =D68*C68*1000000000 -> 1.2361262e+10 | F68: =E68*(1-$F$3) -> 1.2299455e+10 | G68: =100% -> 1 | H68: =F68*G68 -> 1.2299455e+10 | I68: =I67+H68+N67 -> 1.0613294e+14 | J68: =(J67+H68+N67)*(1-$J$3) -> 1.0372857e+14 | K68: =J67*$K$3 -> 6.5478916e+12 | L68: =F68*(1-G68) -> 0 | M68: =K68+L68 -> 6.5478916e+12 | N68: =M68*8% -> 5.2383133e+11 | O68: =(M68-N68)*(1-$O$3) -> 5.99394e+12 | Q68: =O68-P68 -> 5.99394e+12 | R68: 10289315244 | S68: =$S$3 -> 1 | T68: =(Q68/(R68*S68))/12 -> 48.545018
A69: Year 61 | B69: 2085 | C69: =C68*(1-$C$5) -> 0.0027812839 | D69: 4000 | E69: =D69*C69*1000000000 -> 1.1125136e+10 | F69: =E69*(1-$F$3) -> 1.106951e+10 | G69: =100% -> 1 | H69: =F69*G69 -> 1.106951e+10 | I69: =I68+H69+N68 -> 1.0666784e+14 | J69: =(J68+H69+N68)*(1-$J$3) -> 1.0421134e+14 | K69: =J68*$K$3 -> 6.5763911e+12 | L69: =F69*(1-G69) -> 0 | M69: =K69+L69 -> 6.5763911e+12 | N69: =M69*8.5% -> 5.5899325e+11 | O69: =(M69-N69)*(1-$O$3) -> 5.9873109e+12 | Q69: =O69-P69 -> 5.9873109e+12 | R69: 10288456599 | S69: =$S$3 -> 1 | T69: =(Q69/(R69*S69))/12 -> 48.495376
A70: Year 62 | B70: 2086 | C70: =C69*(1-$C$5) -> 0.0025031555 | D70: 4000 | E70: =D70*C70*1000000000 -> 1.0012622e+10 | F70: =E70*(1-$F$3) -> 9.9625589e+09 | G70: =100% -> 1 | H70: =F70*G70 -> 9.9625589e+09 | I70: =I69+H70+N69 -> 1.072368e+14 | J70: =(J69+H70+N69)*(1-$J$3) -> 104727901320482 | K70: =J69*$K$3 -> 6.6069987e+12 | L70: =F70*(1-G70) -> 0 | M70: =K70+L70 -> 6.6069987e+12 | N70: =M70*9% -> 5.9462988e+11 | O70: =(M70-N70)*(1-$O$3) -> 5.982307e+12 | Q70: =O70-P70 -> 5.982307e+12 | R70: 10286708360 | S70: =$S$3 -> 1 | T70: =(Q70/(R70*S70))/12 -> 48.463081
A71: Year 63 | B71: 2087 | C71: =C70*(1-$C$5) -> 0.00225284 | D71: 4000 | E71: =D71*C71*1000000000 -> 9.0113598e+09 | F71: =E71*(1-$F$3) -> 8.966303e+09 | G71: =100% -> 1 | H71: =F71*G71 -> 8.966303e+09 | I71: =I70+H71+N70 -> 1.0784039e+14 | J71: =(J70+H71+N70)*(1-$J$3) -> 1.0527883e+14 | K71: =J70*$K$3 -> 6.6397489e+12 | L71: =F71*(1-G71) -> 0 | M71: =K71+L71 -> 6.6397489e+12 | N71: =M71*9.5% -> 6.3077615e+11 | O71: =(M71-N71)*(1-$O$3) -> 5.9789279e+12 | Q71: =O71-P71 -> 5.9789279e+12 | R71: 10284111374 | S71: =$S$3 -> 1 | T71: =(Q71/(R71*S71))/12 -> 48.447938
A72: Year 64 | B72: 2088 | C72: =C71*(1-$C$5) -> 0.002027556 | D72: 4000 | E72: =D72*C72*1000000000 -> 8.1102238e+09 | F72: =E72*(1-$F$3) -> 8.0696727e+09 | G72: =100% -> 1 | H72: =F72*G72 -> 8.0696727e+09 | I72: =I71+H72+N71 -> 1.0847924e+14 | J72: =(J71+H72+N71)*(1-$J$3) -> 1.0586472e+14 | K72: =J71*$K$3 -> 6.6746779e+12 | L72: =F72*(1-G72) -> 0 | M72: =K72+L72 -> 6.6746779e+12 | N72: =M72*$N$5 -> 6.6746779e+11 | O72: =(M72-N72)*(1-$O$3) -> 5.9771741e+12 | Q72: =O72-P72 -> 5.9771741e+12 | R72: 10280704572 | S72: =$S$3 -> 1 | T72: =(Q72/(R72*S72))/12 -> 48.449777
A73: Year 65 | B73: 2089 | C73: =C72*(1-$C$5) -> 0.0018248004 | D73: 4000 | E73: =D73*C73*1000000000 -> 7.2992015e+09 | F73: =E73*(1-$F$3) -> 7.2627054e+09 | G73: =100% -> 1 | H73: =F73*G73 -> 7.2627054e+09 | I73: =I72+H73+N72 -> 109153969598216 | J73: =(J72+H73+N72)*(1-$J$3) -> 1.0648618e+14 | K73: =J72*$K$3 -> 6.7118232e+12 | L73: =F73*(1-G73) -> 0 | M73: =K73+L73 -> 6.7118232e+12 | N73: =M73*$N$5 -> 6.7118232e+11 | O73: =(M73-N73)*(1-$O$3) -> 6.0104376e+12 | Q73: =O73-P73 -> 6.0104376e+12 | R73: 10276518280 | S73: =$S$3 -> 1 | T73: =(Q73/(R73*S73))/12 -> 48.739251
A74: Year 66 | B74: 2090 | C74: =C73*(1-$C$5) -> 0.0016423203 | D74: 4000 | E74: =D74*C74*1000000000 -> 6.5692813e+09 | F74: =E74*(1-$F$3) -> 6.5364349e+09 | G74: =100% -> 1 | H74: =F74*G74 -> 6.5364349e+09 | I74: =I73+H74+N73 -> 1.0983169e+14 | J74: =(J73+H74+N73)*(1-$J$3) -> 1.0711032e+14 | K74: =J73*$K$3 -> 6.7512238e+12 | L74: =F74*(1-G74) -> 0 | M74: =K74+L74 -> 6.7512238e+12 | N74: =M74*$N$5 -> 6.7512238e+11 | O74: =(M74-N74)*(1-$O$3) -> 6.0457209e+12 | Q74: =O74-P74 -> 6.0457209e+12 | R74: 10271565070 | S74: =$S$3 -> 1 | T74: =(Q74/(R74*S74))/12 -> 49.049008
A75: Year 67 | B75: 2091 | C75: =C74*(1-$C$5) -> 0.0014780883 | D75: 4000 | E75: =D75*C75*1000000000 -> 5.9123532e+09 | F75: =E75*(1-$F$3) -> 5.8827914e+09 | G75: =100% -> 1 | H75: =F75*G75 -> 5.8827914e+09 | I75: =I74+H75+N74 -> 1.1051269e+14 | J75: =(J74+H75+N74)*(1-$J$3) -> 1.0773743e+14 | K75: =J74*$K$3 -> 6.7907941e+12 | L75: =F75*(1-G75) -> 0 | M75: =K75+L75 -> 6.7907941e+12 | N75: =M75*$N$5 -> 6.7907941e+11 | O75: =(M75-N75)*(1-$O$3) -> 6.0811561e+12 | Q75: =O75-P75 -> 6.0811561e+12 | R75: 10265861714 | S75: =$S$3 -> 1 | T75: =(Q75/(R75*S75))/12 -> 49.363903
A76: Year 68 | B76: 2092 | C76: =C75*(1-$C$5) -> 0.0013302795 | D76: 4000 | E76: =D76*C76*1000000000 -> 5.3211179e+09 | F76: =E76*(1-$F$3) -> 5.2945123e+09 | G76: =100% -> 1 | H76: =F76*G76 -> 5.2945123e+09 | I76: =I75+H76+N75 -> 1.1119707e+14 | J76: =(J75+H76+N75)*(1-$J$3) -> 1.0836759e+14 | K76: =J75*$K$3 -> 6.8305528e+12 | L76: =F76*(1-G76) -> 0 | M76: =K76+L76 -> 6.8305528e+12 | N76: =M76*$N$5 -> 6.8305528e+11 | O76: =(M76-N76)*(1-$O$3) -> 6.11676e+12 | Q76: =O76-P76 -> 6.11676e+12 | R76: 10259408375 | S76: =$S$3 -> 1 | T76: =(Q76/(R76*S76))/12 -> 49.684152
A77: Year 69 | B77: 2093 | C77: =C76*(1-$C$5) -> 0.0011972515 | D77: 4000 | E77: =D77*C77*1000000000 -> 4.7890061e+09 | F77: =E77*(1-$F$3) -> 4.765061e+09 | G77: =100% -> 1 | H77: =F77*G77 -> 4.765061e+09 | I77: =I76+H77+N76 -> 1.1188489e+14 | J77: =(J76+H77+N76)*(1-$J$3) -> 1.0900088e+14 | K77: =J76*$K$3 -> 6.8705051e+12 | L77: =F77*(1-G77) -> 0 | M77: =K77+L77 -> 6.8705051e+12 | N77: =M77*$N$5 -> 6.8705051e+11 | O77: =(M77-N77)*(1-$O$3) -> 6.1525373e+12 | Q77: =O77-P77 -> 6.1525373e+12 | R77: 10252184759 | S77: =$S$3 -> 1 | T77: =(Q77/(R77*S77))/12 -> 50.009969
A78: Year 70 | B78: 2094 | C78: =C77*(1-$C$5) -> 0.0010775264 | D78: 4000 | E78: =D78*C78*1000000000 -> 4.3101055e+09 | F78: =E78*(1-$F$3) -> 4.2885549e+09 | G78: =100% -> 1 | H78: =F78*G78 -> 4.2885549e+09 | I78: =I77+H78+N77 -> 1.1257623e+14 | J78: =(J77+H78+N77)*(1-$J$3) -> 1.0963737e+14 | K78: =J77*$K$3 -> 6.9106559e+12 | L78: =F78*(1-G78) -> 0 | M78: =K78+L78 -> 6.9106559e+12 | N78: =M78*$N$5 -> 6.9106559e+11 | O78: =(M78-N78)*(1-$O$3) -> 6.1884923e+12 | Q78: =O78-P78 -> 6.1884923e+12 | R78: 10244185837 | S78: =$S$3 -> 1 | T78: =(Q78/(R78*S78))/12 -> 50.341501
A79: Year 71 | B79: 2095 | C79: =C78*(1-$C$5) -> 0.00096977373 | D79: 4000 | E79: =D79*C79*1000000000 -> 3.8790949e+09 | F79: =E79*(1-$F$3) -> 3.8596994e+09 | G79: =100% -> 1 | H79: =F79*G79 -> 3.8596994e+09 | I79: =I78+H79+N78 -> 1.1327115e+14 | J79: =(J78+H79+N78)*(1-$J$3) -> 1.1027713e+14 | K79: =J78*$K$3 -> 6.9510095e+12 | L79: =F79*(1-G79) -> 0 | M79: =K79+L79 -> 6.9510095e+12 | N79: =M79*$N$5 -> 6.9510095e+11 | O79: =(M79-N79)*(1-$O$3) -> 6.224629e+12 | Q79: =O79-P79 -> 6.224629e+12 | R79: 10235403601 | S79: =$S$3 -> 1 | T79: =(Q79/(R79*S79))/12 -> 50.678909
A80: Year 72 | B80: 2096 | C80: =C79*(1-$C$5) -> 0.00087279636 | D80: 4000 | E80: =D80*C80*1000000000 -> 3.4911854e+09 | F80: =E80*(1-$F$3) -> 3.4737295e+09 | G80: =100% -> 1 | H80: =F80*G80 -> 3.4737295e+09 | I80: =I79+H80+N79 -> 1.1396973e+14 | J80: =(J79+H80+N79)*(1-$J$3) -> 1.1092022e+14 | K80: =J79*$K$3 -> 6.9915703e+12 | L80: =F80*(1-G80) -> 0 | M80: =K80+L80 -> 6.9915703e+12 | N80: =M80*$N$5 -> 6.9915703e+11 | O80: =(M80-N80)*(1-$O$3) -> 6.2609512e+12 | Q80: =O80-P80 -> 6.2609512e+12 | R80: 10225850874 | S80: =$S$3 -> 1 | T80: =(Q80/(R80*S80))/12 -> 51.022251
A81: Year 73 | B81: 2097 | C81: =C80*(1-$C$5) -> 0.00078551672 | D81: 4000 | E81: =D81*C81*1000000000 -> 3.1420669e+09 | F81: =E81*(1-$F$3) -> 3.1263566e+09 | G81: =100% -> 1 | H81: =F81*G81 -> 3.1263566e+09 | I81: =I80+H81+N80 -> 1.1467201e+14 | J81: =(J80+H81+N80)*(1-$J$3) -> 1.1156669e+14 | K81: =J80*$K$3 -> 7.032342e+12 | L81: =F81*(1-G81) -> 0 | M81: =K81+L81 -> 7.032342e+12 | N81: =M81*$N$5 -> 7.032342e+11 | O81: =(M81-N81)*(1-$O$3) -> 6.2974622e+12 | Q81: =O81-P81 -> 6.2974622e+12 | R81: 10215549310 | S81: =$S$3 -> 1 | T81: =(Q81/(R81*S81))/12 -> 51.371542
A82: Year 74 | B82: 2098 | C82: =C81*(1-$C$5) -> 0.00070696505 | D82: 4000 | E82: =D82*C82*1000000000 -> 2.8278602e+09 | F82: =E82*(1-$F$3) -> 2.8137209e+09 | G82: =100% -> 1 | H82: =F82*G82 -> 2.8137209e+09 | I82: =I81+H82+N81 -> 1.1537806e+14 | J82: =(J81+H82+N81)*(1-$J$3) -> 1.122166e+14 | K82: =J81*$K$3 -> 7.0733283e+12 | L82: =F82*(1-G82) -> 0 | M82: =K82+L82 -> 7.0733283e+12 | N82: =M82*$N$5 -> 7.0733283e+11 | O82: =(M82-N82)*(1-$O$3) -> 6.3341655e+12 | Q82: =O82-P82 -> 6.3341655e+12 | R82: 10204489862 | S82: =$S$3 -> 1 | T82: =(Q82/(R82*S82))/12 -> 51.726949
A83: Year 75 | B83: 2099 | C83: =C82*(1-$C$5) -> 0.00063626854 | D83: 4000 | E83: =D83*C83*1000000000 -> 2.5450742e+09 | F83: =E83*(1-$F$3) -> 2.5323488e+09 | G83: =100% -> 1 | H83: =F83*G83 -> 2.5323488e+09 | I83: =I82+H83+N82 -> 1.1608792e+14 | J83: =(J82+H83+N82)*(1-$J$3) -> 1.1287001e+14 | K83: =J82*$K$3 -> 7.1145327e+12 | L83: =F83*(1-G83) -> 0 | M83: =K83+L83 -> 7.1145327e+12 | N83: =M83*$N$5 -> 7.1145327e+11 | O83: =(M83-N83)*(1-$O$3) -> 6.371064e+12 | Q83: =O83-P83 -> 6.371064e+12 | R83: 10192689066 | S83: =$S$3 -> 1 | T83: =(Q83/(R83*S83))/12 -> 52.088512
A84: Year 76 | B84: 2100 | C84: =C83*(1-$C$5) -> 0.00057264169 | D84: 4000 | E84: =D84*C84*1000000000 -> 2.2905668e+09 | F84: =E84*(1-$F$3) -> 2.2791139e+09 | G84: =100% -> 1 | H84: =F84*G84 -> 2.2791139e+09 | I84: =I83+H84+N83 -> 1.1680166e+14 | J84: =(J83+H84+N83)*(1-$J$3) -> 1.1352695e+14 | K84: =J83*$K$3 -> 7.1559584e+12 | L84: =F84*(1-G84) -> 0 | M84: =K84+L84 -> 7.1559584e+12 | N84: =M84*$N$5 -> 7.1559584e+11 | O84: =(M84-N84)*(1-$O$3) -> 6.4081607e+12 | Q84: =O84-P84 -> 6.4081607e+12 | R84: 10180160751 | S84: =$S$3 -> 1 | T84: =(Q84/(R84*S84))/12 -> 52.456283
A85: Year 77 | B85: 2101 | C85: =C84*(1-$C$5) -> 0.00051537752 | D85: 4000 | E85: =D85*C85*1000000000 -> 2.0615101e+09 | F85: =E85*(1-$F$3) -> 2.0512025e+09 | G85: =100% -> 1 | H85: =F85*G85 -> 2.0512025e+09 | I85: =I84+H85+N84 -> 1.175193e+14 | J85: =(J84+H85+N84)*(1-$J$3) -> 1.1418747e+14 | K85: =J84*$K$3 -> 7.1976084e+12 | L85: =F85*(1-G85) -> 0 | M85: =K85+L85 -> 7.1976084e+12 | N85: =M85*9% -> 6.4778476e+11 | O85: =(M85-N85)*(1-$O$3) -> 6.5170745e+12 | Q85: =O85-P85 -> 6.5170745e+12 | R85: =R84*99.9% -> 1.0169981e+10 | S85: =$S$3 -> 1 | T85: =(Q85/(R85*S85))/12 -> 53.401237
A86: Year 78 | B86: 2102 | C86: =C85*(1-$C$5) -> 0.00046383977 | D86: 4000 | E86: =D86*C86*1000000000 -> 1.8553591e+09 | F86: =E86*(1-$F$3) -> 1.8460823e+09 | G86: =100% -> 1 | H86: =F86*G86 -> 1.8460823e+09 | I86: =I85+H86+N85 -> 1.1816893e+14 | J86: =(J85+H86+N85)*(1-$J$3) -> 1.1477968e+14 | K86: =J85*$K$3 -> 7.2394857e+12 | L86: =F86*(1-G86) -> 0 | M86: =K86+L86 -> 7.2394857e+12 | N86: =M86*9.5% -> 6.8775114e+11 | O86: =(M86-N86)*(1-$O$3) -> 6.5189759e+12 | Q86: =O86-P86 -> 6.5189759e+12 | R86: =R85*99.9% -> 1.0159811e+10 | S86: =$S$3 -> 1 | T86: =(Q86/(R86*S86))/12 -> 53.470287
A87: Year 79 | B87: 2103 | C87: =C86*(1-$C$5) -> 0.00041745579 | D87: 4000 | E87: =D87*C87*1000000000 -> 1.6698232e+09 | F87: =E87*(1-$F$3) -> 1.6614741e+09 | G87: =100% -> 1 | H87: =F87*G87 -> 1.6614741e+09 | I87: =I86+H87+N86 -> 1.1885835e+14 | J87: =(J86+H87+N86)*(1-$J$3) -> 1.1541136e+14 | K87: =J86*$K$3 -> 7.2770319e+12 | L87: =F87*(1-G87) -> 0 | M87: =K87+L87 -> 7.2770319e+12 | N87: =M87*$N$5 -> 7.2770319e+11 | O87: =(M87-N87)*(1-$O$3) -> 6.5165821e+12 | Q87: =O87-P87 -> 6.5165821e+12 | R87: =R86*99.9% -> 1.0149651e+10 | S87: =$S$3 -> 1 | T87: =(Q87/(R87*S87))/12 -> 53.504157
A88: Year 80 | B88: 2104 | C88: =C87*(1-$C$5) -> 0.00037571021 | D88: 4000 | E88: =D88*C88*1000000000 -> 1.5028409e+09 | F88: =E88*(1-$F$3) -> 1.4953266e+09 | G88: =100% -> 1 | H88: =F88*G88 -> 1.4953266e+09 | I88: =I87+H88+N87 -> 1.1958754e+14 | J88: =(J87+H88+N87)*(1-$J$3) -> 1.1608249e+14 | K88: =J87*$K$3 -> 7.3170803e+12 | L88: =F88*(1-G88) -> 0 | M88: =K88+L88 -> 7.3170803e+12 | N88: =M88*$N$5 -> 7.3170803e+11 | O88: =(M88-N88)*(1-$O$3) -> 6.5524454e+12 | Q88: =O88-P88 -> 6.5524454e+12 | R88: =R87*99.9% -> 1.0139501e+10 | S88: =$S$3 -> 1 | T88: =(Q88/(R88*S88))/12 -> 53.852464
A89: Year 81 | B89: 2105 | C89: =C88*(1-$C$5) -> 0.00033813919 | D89: 4000 | E89: =D89*C89*1000000000 -> 1.3525568e+09 | F89: =E89*(1-$F$3) -> 1.345794e+09 | G89: =100% -> 1 | H89: =F89*G89 -> 1.345794e+09 | I89: =I88+H89+N88 -> 1.203206e+14 | J89: =(J88+H89+N88)*(1-$J$3) -> 1.1675714e+14 | K89: =J88*$K$3 -> 7.3596299e+12 | L89: =F89*(1-G89) -> 0 | M89: =K89+L89 -> 7.3596299e+12 | N89: =M89*$N$5 -> 7.3596299e+11 | O89: =(M89-N89)*(1-$O$3) -> 6.5905485e+12 | Q89: =O89-P89 -> 6.5905485e+12 | R89: =R88*99.9% -> 1.0129362e+10 | S89: =$S$3 -> 1 | T89: =(Q89/(R89*S89))/12 -> 54.219841
A90: Year 82 | B90: 2106 | C90: =C89*(1-$C$5) -> 0.00030432527 | D90: 4000 | E90: =D90*C90*1000000000 -> 1.2173011e+09 | F90: =E90*(1-$F$3) -> 1.2112146e+09 | G90: =100% -> 1 | H90: =F90*G90 -> 1.2112146e+09 | I90: =I89+H90+N89 -> 1.2105777e+14 | J90: =(J89+H90+N89)*(1-$J$3) -> 1.1743556e+14 | K90: =J89*$K$3 -> 7.4024024e+12 | L90: =F90*(1-G90) -> 0 | M90: =K90+L90 -> 7.4024024e+12 | N90: =M90*$N$5 -> 7.4024024e+11 | O90: =(M90-N90)*(1-$O$3) -> 6.6288514e+12 | Q90: =O90-P90 -> 6.6288514e+12 | R90: =R89*99.9% -> 1.0119232e+10 | S90: =$S$3 -> 1 | T90: =(Q90/(R90*S90))/12 -> 54.589544
A91: Year 83 | B91: 2107 | C91: =C90*(1-$C$5) -> 0.00027389274 | D91: 4000 | E91: =D91*C91*1000000000 -> 1.095571e+09 | F91: =E91*(1-$F$3) -> 1.0900931e+09 | G91: =100% -> 1 | H91: =F91*G91 -> 1.0900931e+09 | I91: =I90+H91+N90 -> 1.217991e+14 | J91: =(J90+H91+N90)*(1-$J$3) -> 1.181178e+14 | K91: =J90*$K$3 -> 7.4454147e+12 | L91: =F91*(1-G91) -> 0 | M91: =K91+L91 -> 7.4454147e+12 | N91: =M91*$N$5 -> 7.4454147e+11 | O91: =(M91-N91)*(1-$O$3) -> 6.6673689e+12 | Q91: =O91-P91 -> 6.6673689e+12 | R91: =R90*99.9% -> 1.0109113e+10 | S91: =$S$3 -> 1 | T91: =(Q91/(R91*S91))/12 -> 54.961703
A92: Year 84 | B92: 2108 | C92: =C91*(1-$C$5) -> 0.00024650347 | D92: 4000 | E92: =D92*C92*1000000000 -> 9.8601388e+08 | F92: =E92*(1-$F$3) -> 9.8108381e+08 | G92: =100% -> 1 | H92: =F92*G92 -> 9.8108381e+08 | I92: =I91+H92+N91 -> 1.2254463e+14 | J92: =(J91+H92+N91)*(1-$J$3) -> 1.188039e+14 | K92: =J91*$K$3 -> 7.4886688e+12 | L92: =F92*(1-G92) -> 0 | M92: =K92+L92 -> 7.4886688e+12 | N92: =M92*$N$5 -> 7.4886688e+11 | O92: =(M92-N92)*(1-$O$3) -> 6.7061029e+12 | Q92: =O92-P92 -> 6.7061029e+12 | R92: =R91*99.9% -> 1.0099004e+10 | S92: =$S$3 -> 1 | T92: =(Q92/(R92*S92))/12 -> 55.33634
A93: Year 85 | B93: 2109 | C93: =C92*(1-$C$5) -> 0.00022185312 | D93: 4000 | E93: =D93*C93*1000000000 -> 8.8741249e+08 | F93: =E93*(1-$F$3) -> 8.8297543e+08 | G93: =100% -> 1 | H93: =F93*G93 -> 8.8297543e+08 | I93: =I92+H93+N92 -> 1.2329438e+14 | J93: =(J92+H93+N92)*(1-$J$3) -> 1.1949387e+14 | K93: =J92*$K$3 -> 7.532167e+12 | L93: =F93*(1-G93) -> 0 | M93: =K93+L93 -> 7.532167e+12 | N93: =M93*$N$5 -> 7.532167e+11 | O93: =(M93-N93)*(1-$O$3) -> 6.7450555e+12 | Q93: =O93-P93 -> 6.7450555e+12 | R93: =R92*99.9% -> 1.0088905e+10 | S93: =$S$3 -> 1 | T93: =(Q93/(R93*S93))/12 -> 55.713476
A94: Year 86 | B94: 2110 | C94: =C93*(1-$C$5) -> 0.00019966781 | D94: 4000 | E94: =D94*C94*1000000000 -> 7.9867124e+08 | F94: =E94*(1-$F$3) -> 7.9467789e+08 | G94: =100% -> 1 | H94: =F94*G94 -> 7.9467789e+08 | I94: =I93+H94+N93 -> 1.2404839e+14 | J94: =(J93+H94+N93)*(1-$J$3) -> 1.2018776e+14 | K94: =J93*$K$3 -> 7.5759113e+12 | L94: =F94*(1-G94) -> 0 | M94: =K94+L94 -> 7.5759113e+12 | N94: =M94*$N$5 -> 7.5759113e+11 | O94: =(M94-N94)*(1-$O$3) -> 6.7842286e+12 | Q94: =O94-P94 -> 6.7842286e+12 | R94: =R93*99.9% -> 1.0078816e+10 | S94: =$S$3 -> 1 | T94: =(Q94/(R94*S94))/12 -> 56.093134
A95: Year 87 | B95: 2111 | C95: =C94*(1-$C$5) -> 0.00017970103 | D95: 4000 | E95: =D95*C95*1000000000 -> 7.1880412e+08 | F95: =E95*(1-$F$3) -> 7.152101e+08 | G95: =100% -> 1 | H95: =F95*G95 -> 7.152101e+08 | I95: =I94+H95+N94 -> 1.2480669e+14 | J95: =(J94+H95+N94)*(1-$J$3) -> 1.2088559e+14 | K95: =J94*$K$3 -> 7.6199037e+12 | L95: =F95*(1-G95) -> 0 | M95: =K95+L95 -> 7.6199037e+12 | N95: =M95*$N$5 -> 7.6199037e+11 | O95: =(M95-N95)*(1-$O$3) -> 6.8236238e+12 | Q95: =O95-P95 -> 6.8236238e+12 | R95: =R94*99.9% -> 1.0068737e+10 | S95: =$S$3 -> 1 | T95: =(Q95/(R95*S95))/12 -> 56.475336
A96: Year 88 | B96: 2112 | C96: =C95*(1-$C$5) -> 0.00016173093 | D96: 4000 | E96: =D96*C96*1000000000 -> 6.4692371e+08 | F96: =E96*(1-$F$3) -> 6.4368909e+08 | G96: =100% -> 1 | H96: =F96*G96 -> 6.4368909e+08 | I96: =I95+H96+N95 -> 1.2556933e+14 | J96: =(J95+H96+N95)*(1-$J$3) -> 1.215874e+14 | K96: =J95*$K$3 -> 7.6641464e+12 | L96: =F96*(1-G96) -> 0 | M96: =K96+L96 -> 7.6641464e+12 | N96: =M96*$N$5 -> 7.6641464e+11 | O96: =(M96-N96)*(1-$O$3) -> 6.8632431e+12 | Q96: =O96-P96 -> 6.8632431e+12 | R96: =R95*99.9% -> 1.0058668e+10 | S96: =$S$3 -> 1 | T96: =(Q96/(R96*S96))/12 -> 56.860103
A97: Year 89 | B97: 2113 | C97: =C96*(1-$C$5) -> 0.00014555783 | D97: 4000 | E97: =D97*C97*1000000000 -> 5.8223134e+08 | F97: =E97*(1-$F$3) -> 5.7932018e+08 | G97: =100% -> 1 | H97: =F97*G97 -> 5.7932018e+08 | I97: =I96+H97+N96 -> 1.2633632e+14 | J97: =(J96+H97+N96)*(1-$J$3) -> 1.2229322e+14 | K97: =J96*$K$3 -> 7.7086411e+12 | L97: =F97*(1-G97) -> 0 | M97: =K97+L97 -> 7.7086411e+12 | N97: =M97*$N$5 -> 7.7086411e+11 | O97: =(M97-N97)*(1-$O$3) -> 6.9030881e+12 | Q97: =O97-P97 -> 6.9030881e+12 | R97: =R96*99.9% -> 1.004861e+10 | S97: =$S$3 -> 1 | T97: =(Q97/(R97*S97))/12 -> 57.247456
A98: Year 90 | B98: 2114 | C98: =C97*(1-$C$5) -> 0.00013100205 | D98: 4000 | E98: =D98*C98*1000000000 -> 5.240082e+08 | F98: =E98*(1-$F$3) -> 5.2138816e+08 | G98: =100% -> 1 | H98: =F98*G98 -> 5.2138816e+08 | I98: =I97+H98+N97 -> 1.2710771e+14 | J98: =(J97+H98+N97)*(1-$J$3) -> 1.2300307e+14 | K98: =J97*$K$3 -> 7.7533899e+12 | L98: =F98*(1-G98) -> 0 | M98: =K98+L98 -> 7.7533899e+12 | N98: =M98*$N$5 -> 7.7533899e+11 | O98: =(M98-N98)*(1-$O$3) -> 6.9431607e+12 | Q98: =O98-P98 -> 6.9431607e+12 | R98: =R97*99.9% -> 1.0038561e+10 | S98: =$S$3 -> 1 | T98: =(Q98/(R98*S98))/12 -> 57.637415
... A184: Year 176 | B184: 2200 | C184: =C183*(1-$C$5) -> 1.5210164e-08 | D184: 4000 | E184: =D184*C184*1000000000 -> 60840.657 | F184: =E184*(1-$F$3) -> 60536.454 | G184: =100% -> 1 | H184: =F184*G184 -> 60536.454 | I184: =I183+H184+N183 -> 2.1325587e+14 | J184: =(J183+H184+N183)*(1-$J$3) -> 2.022751e+14 | K184: =J183*$K$3 -> 1.2750286e+13 | L184: =F184*(1-G184) -> 0 | M184: =K184+L184 -> 1.2750286e+13 | N184: =M184*$N$5 -> 1.2750286e+12 | O184: =(M184-N184)*(1-$O$3) -> 1.1417881e+13 | Q184: =O184-P184 -> 1.1417881e+13 | R184: =R183*99.9% -> 9.2109295e+09 | S184: =$S$3 -> 1 | T184: =(Q184/(R184*S184))/12 -> 103.30012
A186: Total CO2e extraction permitted by 2200 (gigatonnes) | C186: =SUM(C9:C184) -> 350.83555 | D186: Total captured for the people of the world and to climate work | E186: =SUM(E8:E184) -> 2.5622432e+14 | G186: Total carbon charges placed in the Fund | H186: =SUM(H8:H184) -> 1.0302874e+14 | N186: Total distributed to the people of the world and to climate work | O186: =SUM(O8:O184) -> 1.3792853e+15

Sheet Carbon charge rates
F1: Charge based on country income group - smaller jumps
A2: CVI rank | B2: Country | C2: CVI index score | D2: Discount applied to carbon charge for CVI score | E2: Income group | F2: Average GNI per capita for this income group | G2: Income group index multiplier | H2: Carbon charge start point (no discounts) | I2: Carbon charge start point with CVI discounts | J2: Annual emissions (Mt CO2e) | K2: Carbon charge raised in Year 1
A3: 1 | B3: Switzerland | C3: 0.251 | D3: 0 | E3: High | F3: 48441 | G3: =F3/1000 -> 48.441 | H3: 240 | I3: =H3*(1-D3) -> 240 | J3: 34.2 | K3: =I3*J3*1000000 -> 8208000000
A4: 2 | B4: Czech Republic | C4: 0.263 | D4: 0 | E4: High | F4: 48441 | G4: =F4/1000 -> 48.441 | H4: 240 | I4: =H4*(1-D4) -> 240 | J4: 90.5 | K4: =I4*J4*1000000 -> 21720000000
A5: 3 | B5: Norway | C5: 0.27 | D5: 0 | E5: High | F5: 48441 | G5: =F5/1000 -> 48.441 | H5: 240 | I5: =H5*(1-D5) -> 240 | J5: 44.1 | K5: =I5*J5*1000000 -> 10584000000
A6: 4 | B6: Canada | C6: 0.281 | D6: 0 | E6: High | F6: 48441 | G6: =F6/1000 -> 48.441 | H6: 240 | I6: =H6*(1-D6) -> 240 | J6: 575 | K6: =I6*J6*1000000 -> 138000000000
A7: 5 | B7: United Kingdom | C7: 0.285 | D7: 0 | E7: High | F7: 48441 | G7: =F7/1000 -> 48.441 | H7: 240 | I7: =H7*(1-D7) -> 240 | J7: 302.1 | K7: =I7*J7*1000000 -> 72504000000
A8: 6 | B8: Spain | C8: 0.292 | D8: 0 | E8: High | F8: 48441 | G8: =F8/1000 -> 48.441 | H8: 240 | I8: =H8*(1-D8) -> 240 | J8: 217.3 | K8: =I8*J8*1000000 -> 52152000000
A9: 6 | B9: Israel | C9: 0.292 | D9: 0 | E9: High | F9: 48441 | G9: =F9/1000 -> 48.441 | H9: 240 | I9: =H9*(1-D9) -> 240 | J9: 61.3 | K9: =I9*J9*1000000 -> 14712000000
A10: 8 | B10: Finland | C10: 0.295 | D10: 0 | E10: High | F10: 48441 | G10: =F10/1000 -> 48.441 | H10: 240 | I10: =H10*(1-D10) -> 240 | J10: 32.3 | K10: =I10*J10*1000000 -> 7.752e+09
A11: 9 | B11: United States | C11: 0.298 | D11: 0 | E11: High | F11: 48441 | G11: =F11/1000 -> 48.441 | H11: 240 | I11: =H11*(1-D11) -> 240 | J11: 4682 | K11: =I11*J11*1000000 -> 1123680000000
A12: 10 | B12: Austria | C12: 0.299 | D12: 0 | E12: High | F12: 48441 | G12: =F12/1000 -> 48.441 | H12: 240 | I12: =H12*(1-D12) -> 240 | J12: 58.8 | K12: =I12*J12*1000000 -> 14112000000
A13: 10 | B13: Germany | C13: 0.299 | D13: 0 | E13: High | F13: 48441 | G13: =F13/1000 -> 48.441 | H13: 240 | I13: =H13*(1-D13) -> 240 | J13: 583 | K13: =I13*J13*1000000 -> 139920000000
A14: 12 | B14: France | C14: 0.3 | D14: 0 | E14: High | F14: 48441 | G14: =F14/1000 -> 48.441 | H14: 240 | I14: =H14*(1-D14) -> 240 | J14: 282.4 | K14: =I14*J14*1000000 -> 67776000000
... A19: 17 | B19: Slovenia | C19: 0.315 | D19: 0 | E19: High | F19: 48441 | G19: =F19/1000 -> 48.441 | H19: 240 | I19: =H19*(1-D19) -> 240 | J19: 12.1 | K19: =I19*J19*1000000 -> 2904000000
A20: 18 | B20: Kazakhstan | C20: 0.316 | D20: 0 | E20: Upper middle | F20: 10563 | G20: 24 | H20: =G20*5 -> 120 | I20: =H20*(1-D20) -> 120 | J20: 239.9 | K20: =I20*J20*1000000 -> 28788000000
A21: 19 | B21: Malta | C21: 0.318 | D21: 0 | E21: High | F21: 48441 | G21: =F21/1000 -> 48.441 | H21: 240 | I21: =H21*(1-D21) -> 240 | J21: 1.7 | K21: =I21*J21*1000000 -> 408000000
A22: 20 | B22: Portugal | C22: 0.319 | D22: 0 | E22: High | F22: 48441 | G22: =F22/1000 -> 48.441 | H22: 240 | I22: =H22*(1-D22) -> 240 | J22: 36.2 | K22: =I22*J22*1000000 -> 8688000000
A23: 21 | B23: New Zealand | C23: 0.321 | D23: 0 | E23: High | F23: 48441 | G23: =F23/1000 -> 48.441 | H23: 240 | I23: =H23*(1-D23) -> 240 | J23: 35.8 | K23: =I23*J23*1000000 -> 8592000000
A24: 22 | B24: Kyrgyzstan | C24: 0.323 | D24: 0 | E24: Lower middle | F24: 2511 | G24: 12 | H24: =G24*5 -> 60 | I24: =H24*(1-D24) -> 60 | J24: 10.5 | K24: =I24*J24*1000000 -> 630000000
A25: 22 | B25: Russian Federation | C25: 0.323 | D25: 0 | E25: High | F25: 48441 | G25: =F25/1000 -> 48.441 | H25: 240 | I25: =H25*(1-D25) -> 240 | J25: 2069.5 | K25: =I25*J25*1000000 -> 496680000000
A26: 24 | B26: Sweden | C26: 0.324 | D26: 0 | E26: High | F26: 48441 | G26: =F26/1000 -> 48.441 | H26: 240 | I26: =H26*(1-D26) -> 240 | J26: 35.4 | K26: =I26*J26*1000000 -> 8496000000
A27: 25 | B27: Belarus | C27: 0.325 | D27: 0 | E27: Upper middle | F27: 10563 | G27: 24 | H27: =G27*5 -> 120 | I27: =H27*(1-D27) -> 120 | J27: 54.2 | K27: =I27*J27*1000000 -> 6504000000
A28: 26 | B28: Belgium | C28: 0.329 | D28: 0 | E28: High | F28: 48441 | G28: =F28/1000 -> 48.441 | H28: 240 | I28: =H28*(1-D28) -> 240 | J28: 84.3 | K28: =I28*J28*1000000 -> 20232000000
A29: 27 | B29: Estonia | C29: 0.33 | D29: 0 | E29: High | F29: 48441 | G29: =F29/1000 -> 48.441 | H29: 240 | I29: =H29*(1-D29) -> 240 | J29: 11.4 | K29: =I29*J29*1000000 -> 2736000000
A30: 28 | B30: Chile | C30: 0.334 | D30: 0 | E30: High | F30: 48441 | G30: =F30/1000 -> 48.441 | H30: 240 | I30: =H30*(1-D30) -> 240 | J30: 84 | K30: =I30*J30*1000000 -> 20160000000
A31: 29 | B31: Greece | C31: 0.339 | D31: 0 | E31: High | F31: 48441 | G31: =F31/1000 -> 48.441 | H31: 240 | I31: =H31*(1-D31) -> 240 | J31: 51.7 | K31: =I31*J31*1000000 -> 12408000000
A32: 30 | B32: Italy | C32: 0.341 | D32: 0 | E32: High | F32: 48441 | G32: =F32/1000 -> 48.441 | H32: 240 | I32: =H32*(1-D32) -> 240 | J32: 305.5 | K32: =I32*J32*1000000 -> 73320000000
A33: 30 | B33: Mongolia | C33: 0.341 | D33: 0 | E33: Upper middle | F33: 10563 | G33: 24 | H33: =G33*5 -> 120 | I33: =H33*(1-D33) -> 120 | J33: 28.1 | K33: =I33*J33*1000000 -> 3372000000
A34: 32 | B34: Slovakia | C34: 0.347 | D34: 0 | E34: High | F34: 48441 | G34: =F34/1000 -> 48.441 | H34: 240 | I34: =H34*(1-D34) -> 240 | J34: 34.9 | K34: =I34*J34*1000000 -> 8376000000
A35: 33 | B35: Denmark | C35: 0.348 | D35: 0 | E35: High | F35: 48441 | G35: =F35/1000 -> 48.441 | H35: 240 | I35: =H35*(1-D35) -> 240 | J35: 26.8 | K35: =I35*J35*1000000 -> 6432000000
A36: 33 | B36: Iceland | C36: 0.348 | D36: 0 | E36: High | F36: 48441 | G36: =F36/1000 -> 48.441 | H36: 240 | I36: =H36*(1-D36) -> 240 | J36: 3.1 | K36: =I36*J36*1000000 -> 744000000
A37: 35 | B37: Bosnia & Herzegovina | C37: 0.349 | D37: 0 | E37: Upper middle | F37: 10563 | G37: 24 | H37: =G37*5 -> 120 | I37: =H37*(1-D37) -> 120 | J37: 22 | K37: =I37*J37*1000000 -> 2640000000
A38: 35 | B38: Uzbekistan | C38: 0.349 | D38: 0 | E38: Lower middle | F38: 2511 | G38: 12 | H38: =G38*5 -> 60 | I38: =H38*(1-D38) -> 60 | J38: 137.9 | K38: =I38*J38*1000000 -> 8274000000
A39: 37 | B39: Hungary | C39: 0.352 | D39: 0.1 | E39: High | F39: 48441 | G39: =F39/1000 -> 48.441 | H39: 240 | I39: =H39*(1-D39) -> 216 | J39: 43.8 | K39: =I39*J39*1000000 -> 9460800000
A40: 37 | B40: Qatar | C40: 0.352 | D40: 0.1 | E40: High | F40: 48441 | G40: =F40/1000 -> 48.441 | H40: 240 | I40: =H40*(1-D40) -> 216 | J40: 127.9 | K40: =I40*J40*1000000 -> 27626400000
A41: 39 | B41: China | C41: 0.353 | D41: 0.1 | E41: Upper middle | F41: 10563 | G41: 24 | H41: =G41*5 -> 120 | I41: =H41*(1-D41) -> 108 | J41: 13259.6 | K41: =I41*J41*1000000 -> 1432036800000
A42: 39 | B42: Republic of Korea | C42: 0.353 | D42: 0.1 | E42: High | F42: 48441 | G42: =F42/1000 -> 48.441 | H42: 240 | I42: =H42*(1-D42) -> 216 | J42: 573.5 | K42: =I42*J42*1000000 -> 123876000000
A43: 41 | B43: Netherlands | C43: 0.355 | D43: 0.1 | E43: High | F43: 48441 | G43: =F43/1000 -> 48.441 | H43: 240 | I43: =H43*(1-D43) -> 216 | J43: 122.9 | K43: =I43*J43*1000000 -> 26546400000
A44: 42 | B44: Bulgaria | C44: 0.358 | D44: 0.1 | E44: High | F44: 48441 | G44: =F44/1000 -> 48.441 | H44: 240 | I44: =H44*(1-D44) -> 216 | J44: 39.8 | K44: =I44*J44*1000000 -> 8596800000
A45: 42 | B45: Turkey | C45: 0.358 | D45: 0.1 | E45: Upper middle | F45: 10563 | G45: 24 | H45: =G45*5 -> 120 | I45: =H45*(1-D45) -> 108 | J45: 438.3 | K45: =I45*J45*1000000 -> 47336400000
A46: 44 | B46: Cyprus | C46: 0.359 | D46: 0.1 | E46: High | F46: 48441 | G46: =F46/1000 -> 48.441 | H46: 240 | I46: =H46*(1-D46) -> 216 | J46: 7.2 | K46: =I46*J46*1000000 -> 1555200000
A47: 44 | B47: Ukraine | C47: 0.359 | D47: 0.1 | E47: Upper middle | F47: 10563 | G47: 24 | H47: =G47*5 -> 120 | I47: =H47*(1-D47) -> 108 | J47: 136.2 | K47: =I47*J47*1000000 -> 1.47096e+10
A48: 46 | B48: Japan | C48: 0.36 | D48: 0.1 | E48: High | F48: 48441 | G48: =F48/1000 -> 48.441 | H48: 240 | I48: =H48*(1-D48) -> 216 | J48: 944.8 | K48: =I48*J48*1000000 -> 204076800000
A49: 47 | B49: Lithuania | C49: 0.361 | D49: 0.1 | E49: High | F49: 48441 | G49: =F49/1000 -> 48.441 | H49: 240 | I49: =H49*(1-D49) -> 216 | J49: 13.1 | K49: =I49*J49*1000000 -> 2829600000
A50: 48 | B50: Armenia | C50: 0.362 | D50: 0.1 | E50: Upper middle | F50: 10563 | G50: 24 | H50: =G50*5 -> 120 | I50: =H50*(1-D50) -> 108 | J50: 7.7 | K50: =I50*J50*1000000 -> 831600000
A51: 49 | B51: Brazil | C51: 0.363 | D51: 0.1 | E51: Upper middle | F51: 10563 | G51: 24 | H51: =G51*5 -> 120 | I51: =H51*(1-D51) -> 108 | J51: 479.5 | K51: =I51*J51*1000000 -> 51786000000
A52: 50 | B52: Algeria | C52: 0.364 | D52: 0.1 | E52: Upper middle | F52: 10563 | G52: 24 | H52: =G52*5 -> 120 | I52: =H52*(1-D52) -> 108 | J52: 180.4 | K52: =I52*J52*1000000 -> 19483200000
A53: 50 | B53: Kuwait | C53: 0.364 | D53: 0.1 | E53: High | F53: 48441 | G53: =F53/1000 -> 48.441 | H53: 240 | I53: =H53*(1-D53) -> 216 | J53: 111.6 | K53: =I53*J53*1000000 -> 24105600000
A54: 50 | B54: Latvia | C54: 0.364 | D54: 0.1 | E54: High | F54: 48441 | G54: =F54/1000 -> 48.441 | H54: 240 | I54: =H54*(1-D54) -> 216 | J54: 6.6 | K54: =I54*J54*1000000 -> 1425600000
A55: 50 | B55: Malaysia | C55: 0.364 | D55: 0.1 | E55: Upper middle | F55: 10563 | G55: 24 | H55: =G55*5 -> 120 | I55: =H55*(1-D55) -> 108 | J55: 283.3 | K55: =I55*J55*1000000 -> 30596400000
A56: 54 | B56: Iran | C56: 0.365 | D56: 0.1 | E56: Upper middle | F56: 10563 | G56: 24 | H56: =G56*5 -> 120 | I56: =H56*(1-D56) -> 108 | J56: 778.8 | K56: =I56*J56*1000000 -> 84110400000
A57: 55 | B57: Jordan | C57: 0.366 | D57: 0.1 | E57: Lower middle | F57: 2511 | G57: 12 | H57: =G57*5 -> 60 | I57: =H57*(1-D57) -> 54 | J57: 23.6 | K57: =I57*J57*1000000 -> 1274400000
A58: 55 | B58: Morocco | C58: 0.366 | D58: 0.1 | E58: Lower middle | F58: 2511 | G58: 12 | H58: =G58*5 -> 60 | I58: =H58*(1-D58) -> 54 | J58: 69.9 | K58: =I58*J58*1000000 -> 3.7746e+09
A59: 57 | B59: Tajikistan | C59: 0.367 | D59: 0.1 | E59: Lower middle | F59: 2511 | G59: 12 | H59: =G59*5 -> 60 | I59: =H59*(1-D59) -> 54 | J59: 9.3 | K59: =I59*J59*1000000 -> 5.022e+08
A60: 58 | B60: Mexico | C60: 0.368 | D60: 0.1 | E60: Upper middle | F60: 10563 | G60: 24 | H60: =G60*5 -> 120 | I60: =H60*(1-D60) -> 108 | J60: 487.1 | K60: =I60*J60*1000000 -> 52606800000
A61: 59 | B61: Argentina | C61: 0.372 | D61: 0.1 | E61: Upper middle | F61: 10563 | G61: 24 | H61: =G61*5 -> 120 | I61: =H61*(1-D61) -> 108 | J61: 183.8 | K61: =I61*J61*1000000 -> 19850400000
A62: 59 | B62: Barbados | C62: 0.372 | D62: 0.1 | E62: High | F62: 48441 | G62: =F62/1000 -> 48.441 | H62: 240 | I62: =H62*(1-D62) -> 216 | J62: 0.8 | K62: =I62*J62*1000000 -> 172800000
A63: 61 | B63: Venezuela | C63: 0.374 | D63: 0.1 | E63: Upper middle | F63: 10563 | G63: 24 | H63: =G63*5 -> 120 | I63: =H63*(1-D63) -> 108 | J63: 84.6 | K63: =I63*J63*1000000 -> 9136800000
A64: 62 | B64: Turkmenistan | C64: 0.375 | D64: 0.1 | E64: Upper middle | F64: 10563 | G64: 24 | H64: =G64*5 -> 120 | I64: =H64*(1-D64) -> 108 | J64: 66 | K64: =I64*J64*1000000 -> 7128000000
A65: 62 | B65: Trinidad & Tobago | C65: 0.375 | D65: 0.1 | E65: High | F65: 48441 | G65: =F65/1000 -> 48.441 | H65: 240 | I65: =H65*(1-D65) -> 216 | J65: 27.2 | K65: =I65*J65*1000000 -> 5875200000
A66: 64 | B66: Tunisia | C66: 0.376 | D66: 0.1 | E66: Lower middle | F66: 2511 | G66: 12 | H66: =G66*5 -> 60 | I66: =H66*(1-D66) -> 54 | J66: 31.5 | K66: =I66*J66*1000000 -> 1701000000
A67: 65 | B67: Saint Lucia | C67: 0.379 | D67: 0.1 | E67: Upper middle | F67: 10563 | G67: 24 | H67: =G67*5 -> 120 | I67: =H67*(1-D67) -> 108 | J67: 0.3 | K67: =I67*J67*1000000 -> 32400000
A68: 65 | B68: Macedonia | C68: 0.379 | D68: 0.1 | E68: Upper middle | F68: 10563 | G68: 24 | H68: =G68*5 -> 120 | I68: =H68*(1-D68) -> 108 | J68: 8.8 | K68: =I68*J68*1000000 -> 9.504e+08
A69: 67 | B69: Costa Rica | C69: 0.38 | D69: 0.1 | E69: Upper middle | F69: 10563 | G69: 24 | H69: =G69*5 -> 120 | I69: =H69*(1-D69) -> 108 | J69: 8.6 | K69: =I69*J69*1000000 -> 928800000
A70: 67 | B70: Croatia | C70: 0.38 | D70: 0.1 | E70: High | F70: 48441 | G70: =F70/1000 -> 48.441 | H70: 240 | I70: =H70*(1-D70) -> 216 | J70: 17.5 | K70: =I70*J70*1000000 -> 3780000000
A71: 69 | B71: Montenegro | C71: 0.381 | D71: 0.1 | E71: Upper middle | F71: 10563 | G71: 24 | H71: =G71*5 -> 120 | I71: =H71*(1-D71) -> 108 | K71: =I71*J71*1000000 -> 0
A72: 70 | B72: United Arab Emirates | C72: 0.382 | D72: 0.1 | E72: High | F72: 48441 | G72: =F72/1000 -> 48.441 | H72: 240 | I72: =H72*(1-D72) -> 216 | J72: 206 | K72: =I72*J72*1000000 -> 44496000000
A73: 71 | B73: South Africa | C73: 0.383 | D73: 0.1 | E73: Upper middle | F73: 10563 | G73: 24 | H73: =G73*5 -> 120 | I73: =H73*(1-D73) -> 108 | J73: 397.4 | K73: =I73*J73*1000000 -> 42919200000
A74: 72 | B74: Albania | C74: 0.386 | D74: 0.1 | E74: Upper middle | F74: 10563 | G74: 24 | H74: =G74*5 -> 120 | I74: =H74*(1-D74) -> 108 | J74: 4.6 | K74: =I74*J74*1000000 -> 4.968e+08
A75: 73 | B75: Grenada | C75: 0.387 | D75: 0.1 | E75: Upper middle | F75: 10563 | G75: 24 | H75: =G75*5 -> 120 | I75: =H75*(1-D75) -> 108 | J75: 0.1 | K75: =I75*J75*1000000 -> 10800000
A76: 74 | B76: Singapore | C76: 0.39 | D76: 0.1 | E76: High | F76: 48441 | G76: =F76/1000 -> 48.441 | H76: 240 | I76: =H76*(1-D76) -> 216 | J76: 57.1 | K76: =I76*J76*1000000 -> 12333600000
A77: 75 | B77: Paraguay | C77: 0.391 | D77: 0.1 | E77: Upper middle | F77: 10563 | G77: 24 | H77: =G77*5 -> 120 | I77: =H77*(1-D77) -> 108 | J77: 8.3 | K77: =I77*J77*1000000 -> 8.964e+08
A78: 75 | B78: Uruguay | C78: 0.391 | D78: 0.1 | E78: High | F78: 48441 | G78: =F78/1000 -> 48.441 | H78: 240 | I78: =H78*(1-D78) -> 216 | J78: 8.8 | K78: =I78*J78*1000000 -> 1.9008e+09
A79: 77 | B79: Moldova | C79: 0.393 | D79: 0.1 | E79: Upper middle | F79: 10563 | G79: 24 | H79: =G79*5 -> 120 | I79: =H79*(1-D79) -> 108 | J79: 9.9 | K79: =I79*J79*1000000 -> 1069200000
A80: 78 | B80: Egypt | C80: 0.396 | D80: 0.1 | E80: Lower middle | F80: 2511 | G80: 12 | H80: =G80*5 -> 60 | I80: =H80*(1-D80) -> 54 | J80: 249.3 | K80: =I80*J80*1000000 -> 13462200000
A81: 79 | B81: Georgia | C81: 0.399 | D81: 0.1 | E81: Upper middle | F81: 10563 | G81: 24 | H81: =G81*5 -> 120 | I81: =H81*(1-D81) -> 108 | J81: 12.9 | K81: =I81*J81*1000000 -> 1393200000
A82: 80 | B82: Lebanon | C82: 0.402 | D82: 0.2 | E82: Lower middle | F82: 2511 | G82: 12 | H82: =G82*5 -> 60 | I82: =H82*(1-D82) -> 48 | J82: 17.3 | K82: =I82*J82*1000000 -> 8.304e+08
A83: 81 | B83: Colombia | C83: 0.403 | D83: 0.2 | E83: Upper middle | F83: 10563 | G83: 24 | H83: =G83*5 -> 120 | I83: =H83*(1-D83) -> 96 | J83: 100.9 | K83: =I83*J83*1000000 -> 9.6864e+09
A84: 82 | B84: Brunei Darussalam | C84: 0.404 | D84: 0.2 | E84: High | F84: 48441 | G84: =F84/1000 -> 48.441 | H84: 240 | I84: =H84*(1-D84) -> 192 | J84: 9.7 | K84: =I84*J84*1000000 -> 1.8624e+09
A85: 83 | B85: Peru | C85: 0.406 | D85: 0.2 | E85: Upper middle | F85: 10563 | G85: 24 | H85: =G85*5 -> 120 | I85: =H85*(1-D85) -> 96 | J85: 58.4 | K85: =I85*J85*1000000 -> 5606400000
A86: 84 | B86: Azerbaijan | C86: 0.409 | D86: 0.2 | E86: Upper middle | F86: 10563 | G86: 24 | H86: =G86*5 -> 120 | I86: =H86*(1-D86) -> 96 | J86: 42.8 | K86: =I86*J86*1000000 -> 4.1088e+09
A87: 85 | B87: Mauritius | C87: 0.41 | D87: 0.2 | E87: Upper middle | F87: 10563 | G87: 24 | H87: =G87*5 -> 120 | I87: =H87*(1-D87) -> 96 | J87: 4.2 | K87: =I87*J87*1000000 -> 4.032e+08
A88: 86 | B88: Equatorial Guinea | C88: 0.411 | D88: 0.2 | E88: Upper middle | F88: 10563 | G88: 24 | H88: =G88*5 -> 120 | I88: =H88*(1-D88) -> 96 | J88: 3.8 | K88: =I88*J88*1000000 -> 3.648e+08
A89: 86 | B89: Saudi Arabia | C89: 0.411 | D89: 0.2 | E89: High | F89: 48441 | G89: =F89/1000 -> 48.441 | H89: 240 | I89: =H89*(1-D89) -> 192 | J89: 622.9 | K89: =I89*J89*1000000 -> 1.195968e+11
A90: 86 | B90: Thailand | C90: 0.411 | D90: 0.2 | E90: Upper middle | F90: 10563 | G90: 24 | H90: =G90*5 -> 120 | I90: =H90*(1-D90) -> 96 | J90: 274.2 | K90: =I90*J90*1000000 -> 2.63232e+10
A91: 89 | B91: Romania | C91: 0.415 | D91: 0.2 | E91: High | F91: 48441 | G91: =F91/1000 -> 48.441 | H91: 240 | I91: =H91*(1-D91) -> 192 | J91: 70.8 | K91: =I91*J91*1000000 -> 1.35936e+10
A92: 90 | B92: El Salvador | C92: 0.417 | D92: 0.2 | E92: Upper middle | F92: 10563 | G92: 24 | H92: =G92*5 -> 120 | I92: =H92*(1-D92) -> 96 | J92: 8.4 | K92: =I92*J92*1000000 -> 8.064e+08
A93: 91 | B93: Serbia | C93: 0.421 | D93: 0.2 | E93: Upper middle | F93: 10563 | G93: 24 | H93: =G93*5 -> 120 | I93: =H93*(1-D93) -> 96 | K93: =I93*J93*1000000 -> 0
A94: 92 | B94: Jamaica | C94: 0.422 | D94: 0.2 | E94: Upper middle | F94: 10563 | G94: 24 | H94: =G94*5 -> 120 | I94: =H94*(1-D94) -> 96 | J94: 6.9 | K94: =I94*J94*1000000 -> 6.624e+08
A95: 92 | B95: Oman | C95: 0.422 | D95: 0.2 | E95: High | F95: 48441 | G95: =F95/1000 -> 48.441 | H95: 240 | I95: =H95*(1-D95) -> 192 | J95: 93.1 | K95: =I95*J95*1000000 -> 1.78752e+10
A96: 92 | B96: Panama | C96: 0.422 | D96: 0.2 | E96: High | F96: 48441 | G96: =F96/1000 -> 48.441 | H96: 240 | I96: =H96*(1-D96) -> 192 | J96: 14.7 | K96: =I96*J96*1000000 -> 2.8224e+09
A97: 95 | B97: Libya | C97: 0.423 | D97: 0.2 | E97: Upper middle | F97: 10563 | G97: 24 | H97: =G97*5 -> 120 | I97: =H97*(1-D97) -> 96 | J97: 61.3 | K97: =I97*J97*1000000 -> 5.8848e+09
A98: 96 | B98: Suriname | C98: 0.424 | D98: 0.2 | E98: Upper middle | F98: 10563 | G98: 24 | H98: =G98*5 -> 120 | I98: =H98*(1-D98) -> 96 | J98: 2.6 | K98: =I98*J98*1000000 -> 2.496e+08
A99: 97 | B99: Indonesia | C99: 0.426 | D99: 0.2 | E99: Upper middle | F99: 10563 | G99: 24 | H99: =G99*5 -> 120 | I99: =H99*(1-D99) -> 96 | J99: 674.5 | K99: =I99*J99*1000000 -> 64752000000
A100: 98 | B100: Cape Verde | C100: 0.428 | D100: 0.2 | E100: Lower middle | F100: 2511 | G100: 12 | H100: =G100*5 -> 60 | I100: =H100*(1-D100) -> 48 | J100: 1 | K100: =I100*J100*1000000 -> 48000000
A101: 99 | B101: Dominican Republic | C101: 0.432 | D101: 0.2 | E101: Upper middle | F101: 10563 | G101: 24 | H101: =G101*5 -> 120 | I101: =H101*(1-D101) -> 96 | J101: 31.4 | K101: =I101*J101*1000000 -> 3.0144e+09
A102: 100 | B102: Iraq | C102: 0.433 | D102: 0.2 | E102: Upper middle | F102: 10563 | G102: 24 | H102: =G102*5 -> 120 | I102: =H102*(1-D102) -> 96 | J102: 192.9 | K102: =I102*J102*1000000 -> 18518400000
A103: 101 | B103: Botswana | C103: 0.434 | D103: 0.2 | E103: Upper middle | F103: 10563 | G103: 24 | H103: =G103*5 -> 120 | I103: =H103*(1-D103) -> 96 | J103: 7.4 | K103: =I103*J103*1000000 -> 7.104e+08
A104: 102 | B104: Bahrain | C104: 0.435 | D104: 0.2 | E104: High | F104: 48441 | G104: =F104/1000 -> 48.441 | H104: 240 | I104: =H104*(1-D104) -> 192 | J104: 37.4 | K104: =I104*J104*1000000 -> 7.1808e+09
...

Sheet Malawi Norway summary
B3: 2025 | C3: 2030 | D3: 2035 | E3: 2040 | F3: 2063
A4: MALAWI ONLY
A5: Fund capital available for Malawi | B5: ='Malawi-only'!$L$9 -> 4400673.6 | C5: ='Malawi-only'!$L$14 -> 1.1353063e+08 | D5: ='Malawi-only'!$L$19 -> 7.3480518e+08 | E5: ='Malawi-only'!$L$24 -> 4.7725949e+09 | F5: ='Malawi-only'!$L$47 -> 5.7905474e+10
A6: Number of solar farms it would fund | B6: =B5/65000000 -> 0.06770267 | C6: =C5/65000000 -> 1.7466251 | D6: =D5/65000000 -> 11.304695 | E6: =E5/65000000 -> 73.424537 | F6: =F5/65000000 -> 890.85345
A7: Climate grants this year in Malawi | B7: ='Malawi-only'!$R$9 -> 19713873 | C7: ='Malawi-only'!$R$14 -> 1.1782011e+08 | D7: ='Malawi-only'!$R$19 -> 3.813143e+08 | E7: ='Malawi-only'!$R$24 -> 8.3758836e+08 | F7: ='Malawi-only'!$R$47 -> 1.7681201e+09
A8: Monthly cash transfer per person | B8: ='Malawi-only'!$V$9 -> 0.073947329 | C8: ='Malawi-only'!$V$14 -> 0.42453984 | D8: ='Malawi-only'!$V$19 -> 1.3251068 | E8: ='Malawi-only'!$V$24 -> 2.8180999 | F8: ='Malawi-only'!$V$47 -> 5.426895
A9: Monthly cash per four-person household | B9: =B8*4 -> 0.29578932 | C9: =C8*4 -> 1.6981594 | D9: =D8*4 -> 5.3004271 | E9: =E8*4 -> 11.2724 | F9: =F8*4 -> 21.70758
A10: MALAWI and MINIMAL NORWAY
A11: Fund capital available for Malawi | B11: ='Malawi and Norway'!$L$9 -> 2.8330189e+09 | C11: ='Malawi and Norway'!$L$14 -> 1.3333037e+10 | D11: ='Malawi and Norway'!$L$19 -> 1.6840344e+10 | E11: ='Malawi and Norway'!$L$24 -> 2.083791e+10 | F11: ='Malawi and Norway'!$L$47 -> 7.3843519e+10
A12: Number of solar farms it would fund | B12: =B11/65000000 -> 43.584906 | C12: =C11/65000000 -> 205.12364 | D12: =D11/65000000 -> 259.08222 | E12: =E11/65000000 -> 320.58323 | F12: =F11/65000000 -> 1136.0541
A13: Climate grants this year in Malawi | B13: ='Malawi and Norway'!$R$9 -> 19713873 | C13: ='Malawi and Norway'!$R$14 -> 4.8652348e+08 | D13: ='Malawi and Norway'!$R$19 -> 8.8956128e+08 | E13: ='Malawi and Norway'!$R$24 -> 1.344566e+09 | F13: ='Malawi and Norway'!$R$47 -> 2.2625952e+09
A14: Monthly cash transfer per person | B14: ='Malawi and Norway'!$V$9 -> 0.073947329 | C14: ='Malawi and Norway'!$V$14 -> 1.7530844 | D14: ='Malawi and Norway'!$V$19 -> 3.0913178 | E14: ='Malawi and Norway'!$V$24 -> 4.5238467 | F14: ='Malawi and Norway'!$V$47 -> 6.9445887
A15: Monthly cash per four-person household | B15: =B14*4 -> 0.29578932 | C15: =C14*4 -> 7.0123375 | D15: =D14*4 -> 12.365271 | E15: =E14*4 -> 18.095387 | F15: =F14*4 -> 27.778355
A16: MALAWI and FULL NORWAY
A17: Fund capital available for Malawi | B17: ='Malawi and Norway'!$X$9 -> 1.8621261e+09 | C17: ='Malawi and Norway'!$X$14 -> 1.0068088e+10 | D17: ='Malawi and Norway'!$X$19 -> 1.6259368e+10 | E17: ='Malawi and Norway'!$X$24 -> 2.9265276e+10 | F17: ='Malawi and Norway'!$X$47 -> 1.2085918e+11
A18: Number of solar farms it would fund | B18: =B17/65000000 -> 28.648094 | C18: =C17/65000000 -> 154.89366 | D18: =D17/65000000 -> 250.14412 | E18: =E17/65000000 -> 450.23501 | F18: =F17/65000000 -> 1859.372
A19: Climate grants this year in Malawi | B19: ='Malawi and Norway'!$Z$9 -> 4.091063e+08 | C19: ='Malawi and Norway'!$Z$14 -> 6.5054613e+08 | D19: ='Malawi and Norway'!$Z$19 -> 8.5414993e+08 | E19: ='Malawi and Norway'!$Z$24 -> 1.0832393e+09 | F19: ='Malawi and Norway'!$Z$47 -> 1.6468298e+09
A20: Monthly cash transfer per person | B20: ='Malawi and Norway'!$AA$9 -> 21.570917 | C20: ='Malawi and Norway'!$AA$14 -> 22.479488 | D20: ='Malawi and Norway'!$AA$19 -> 22.901569 | E20: ='Malawi and Norway'!$AA$24 -> 23.471304 | F20: ='Malawi and Norway'!$AA$47 -> 28.270853
A21: Monthly cash per four-person household | B21: =B20*4 -> 86.283666 | C21: =C20*4 -> 89.917953 | D21: =D20*4 -> 91.606275 | E21: =E20*4 -> 93.885216 | F21: =F20*4 -> 113.08341
B25: 2025 | C25: 2030 | D25: 2035 | E25: 2040 | F25: 2063
A26: MALAWI ONLY
A27: Monthly cash transfer per person | B27: ='Malawi-only'!$V$9 -> 0.073947329 | C27: ='Malawi-only'!$V$14 -> 0.42453984 | D27: ='Malawi-only'!$V$19 -> 1.3251068 | E27: ='Malawi-only'!$V$24 -> 2.8180999 | F27: ='Malawi-only'!$V$47 -> 5.426895
A28: Monthly cash per four-person household | B28: =B27*4 -> 0.29578932 | C28: =C27*4 -> 1.6981594 | D28: =D27*4 -> 5.3004271 | E28: =E27*4 -> 11.2724 | F28: =F27*4 -> 21.70758
A29: MALAWI and MINIMAL NORWAY
A30: Monthly cash transfer per person | B30: ='Malawi and Norway'!$V$9 -> 0.073947329 | C30: ='Malawi and Norway'!$V$14 -> 1.7530844 | D30: ='Malawi and Norway'!$V$19 -> 3.0913178 | E30: ='Malawi and Norway'!$V$24 -> 4.5238467 | F30: ='Malawi and Norway'!$V$47 -> 6.9445887
A31: Monthly cash per four-person household | B31: =B30*4 -> 0.29578932 | C31: =C30*4 -> 7.0123375 | D31: =D30*4 -> 12.365271 | E31: =E30*4 -> 18.095387 | F31: =F30*4 -> 27.778355
A32: MALAWI and FULL NORWAY
A33: Monthly cash transfer per person | B33: ='Malawi and Norway'!$AA$9 -> 21.570917 | C33: ='Malawi and Norway'!$AA$14 -> 22.479488 | D33: ='Malawi and Norway'!$AA$19 -> 22.901569 | E33: ='Malawi and Norway'!$AA$24 -> 23.471304 | F33: ='Malawi and Norway'!$AA$47 -> 28.270853
A34: Monthly cash per four-person household | B34: =B33*4 -> 86.283666 | C34: =C33*4 -> 89.917953 | D34: =D33*4 -> 91.606275 | E34: =E33*4 -> 93.885216 | F34: =F33*4 -> 113.08341
B37: 2025 | C37: 2030 | D37: 2035 | E37: 2040 | F37: 2063
A38: MALAWI ONLY
A39: Fund capital available for Malawi | B39: ='Malawi-only'!$L$9 -> 4400673.6 | C39: ='Malawi-only'!$L$14 -> 1.1353063e+08 | D39: ='Malawi-only'!$L$19 -> 7.3480518e+08 | E39: ='Malawi-only'!$L$24 -> 4.7725949e+09 | F39: ='Malawi-only'!$L$47 -> 5.7905474e+10
A40: Number of solar farms it would fund | B40: =B39/65000000 -> 0.06770267 | C40: =C39/65000000 -> 1.7466251 | D40: =D39/65000000 -> 11.304695 | E40: =E39/65000000 -> 73.424537 | F40: =F39/65000000 -> 890.85345
A41: MALAWI and MINIMAL NORWAY
A42: Fund capital available for Malawi | B42: ='Malawi and Norway'!$L$9 -> 2.8330189e+09 | C42: ='Malawi and Norway'!$L$14 -> 1.3333037e+10 | D42: ='Malawi and Norway'!$L$19 -> 1.6840344e+10 | E42: ='Malawi and Norway'!$L$24 -> 2.083791e+10 | F42: ='Malawi and Norway'!$L$47 -> 7.3843519e+10
A43: Number of solar farms it would fund | B43: =B42/65000000 -> 43.584906 | C43: =C42/65000000 -> 205.12364 | D43: =D42/65000000 -> 259.08222 | E43: =E42/65000000 -> 320.58323 | F43: =F42/65000000 -> 1136.0541
A44: MALAWI and FULL NORWAY
A45: Fund capital available for Malawi | B45: ='Malawi and Norway'!$X$9 -> 1.8621261e+09 | C45: ='Malawi and Norway'!$X$14 -> 1.0068088e+10 | D45: ='Malawi and Norway'!$X$19 -> 1.6259368e+10 | E45: ='Malawi and Norway'!$X$24 -> 2.9265276e+10 | F45: ='Malawi and Norway'!$X$47 -> 1.2085918e+11
A46: Number of solar farms it would fund | B46: =B45/65000000 -> 28.648094 | C46: =C45/65000000 -> 154.89366 | D46: =D45/65000000 -> 250.14412 | E46: =E45/65000000 -> 450.23501 | F46: =F45/65000000 -> 1859.372
B49: 2025 | C49: 2030 | D49: 2035 | E49: 2040 | F49: 2063
A50: MALAWI ONLY
A51: Fund capital available for Malawi | B51: ='Malawi-only'!$L$9 -> 4400673.6 | C51: ='Malawi-only'!$L$14 -> 1.1353063e+08 | D51: ='Malawi-only'!$L$19 -> 7.3480518e+08 | E51: ='Malawi-only'!$L$24 -> 4.7725949e+09 | F51: ='Malawi-only'!$L$47 -> 5.7905474e+10
A52: Number of solar farms it would fund | B52: =B51/65000000 -> 0.06770267 | C52: =C51/65000000 -> 1.7466251 | D52: =D51/65000000 -> 11.304695 | E52: =E51/65000000 -> 73.424537 | F52: =F51/65000000 -> 890.85345
A53: Resulting KWh per Malawian per year | B53: =(B52*100740000)/'Malawi-only'!$A$3 -> 0.30700082 | C53: =(C52*100740000)/'Malawi-only'!$A$3 -> 7.9201502 | D53: =(D52*100740000)/'Malawi-only'!$A$3 -> 51.261651 | E53: =(E52*100740000)/'Malawi-only'!$A$3 -> 332.94688 | F53: =(F52*100740000)/'Malawi-only'!$A$3 -> 4039.6152
A54: MALAWI and MINIMAL NORWAY
A55: Fund capital available for Malawi | B55: ='Malawi and Norway'!$L$9 -> 2.8330189e+09 | C55: ='Malawi and Norway'!$L$14 -> 1.3333037e+10 | D55: ='Malawi and Norway'!$L$19 -> 1.6840344e+10 | E55: ='Malawi and Norway'!$L$24 -> 2.083791e+10 | F55: ='Malawi and Norway'!$L$47 -> 7.3843519e+10
A56: Number of solar farms it would fund | B56: =B55/65000000 -> 43.584906 | C56: =C55/65000000 -> 205.12364 | D56: =D55/65000000 -> 259.08222 | E56: =E55/65000000 -> 320.58323 | F56: =F55/65000000 -> 1136.0541
A57: Resulting KWh per Malawian per year | B57: =(B56*100740000)/'Malawi-only'!$A$3 -> 197.63772 | C57: =(C56*100740000)/'Malawi-only'!$A$3 -> 930.14244 | D57: =(D56*100740000)/'Malawi-only'!$A$3 -> 1174.82 | E57: =(E56*100740000)/'Malawi-only'!$A$3 -> 1453.6992 | F57: =(F56*100740000)/'Malawi-only'!$A$3 -> 5151.4888
A58: MALAWI and FULL NORWAY
A59: Fund capital available for Malawi | B59: ='Malawi and Norway'!$X$9 -> 1.8621261e+09 | C59: ='Malawi and Norway'!$X$14 -> 1.0068088e+10 | D59: ='Malawi and Norway'!$X$19 -> 1.6259368e+10 | E59: ='Malawi and Norway'!$X$24 -> 2.9265276e+10 | F59: ='Malawi and Norway'!$X$47 -> 1.2085918e+11
A60: Number of solar farms it would fund | B60: =B59/65000000 -> 28.648094 | C60: =C59/65000000 -> 154.89366 | D60: =D59/65000000 -> 250.14412 | E60: =E59/65000000 -> 450.23501 | F60: =F59/65000000 -> 1859.372
A61: Resulting KWh per Malawian per year | B61: =(B60*100740000)/'Malawi-only'!$A$3 -> 129.90608 | C61: =(C60*100740000)/'Malawi-only'!$A$3 -> 702.37229 | D61: =(D60*100740000)/'Malawi-only'!$A$3 -> 1134.2898 | E61: =(E60*100740000)/'Malawi-only'!$A$3 -> 2041.611 | F61: =(F60*100740000)/'Malawi-only'!$A$3 -> 8431.4066
A63: This is based on data that shows that 250KWh per person per year would be needed to provide basic electricity (enough to power two lightbulbs per person) for each Malawian, whereas 1260KWh would be needed to power lights, a few devices and an electric stove each - see https://www.cgdev.org/blog/how-much-power-does-power-africa-really-need#:~:text=The%20figures%20show%20the%20various,and%20one%20AC%20window%20unit.&text=%5B2%5DTackling%20Investment%20Challenges%20in,freepublications/publication/tackling_i%E2%80%A6. Basic electricity for all 21.1 million Malawians would therefore require 5,275 GWh of power, whereas fuller provision would require 26,586 GWh. A 50MW power plant would generate 100.74GWh per year, assuming a capacity factor of 23% (https://www.sciencedirect.com/science/article/pii/S254243512200304X#:~:text=For%20projects%20used%20as%20input,%2C%20across%202013%E2%80%932020).) Alternative estimates for capacity factors are provided here: https://africa-eu-energy-partnership.org/wp-content/uploads/2023/08/Solar-SSS-Summary-UPDATED-CLEAN-1.pdf

Sheet Malawi-only
A1: National scenarios, adapted from Scenario 1 - Malawi
A2: Population of Malawi (in 2025) | B2: Global population in 2025 | C2: Initial fossil fuel extraction cap (gigatonnes of CO2e) | D2: Expected national allowance price per tonne of CO2 | E2: Assumed starting rate of compensation for extra national allowances per gigatonne of CO2 | F2: Initial carbon charge (per extracted tonne of CO2e) | H2: Running costs of Trust (% of charge money raised) | I2: Initial proportion of charge proceeds going into the Fund (% of total proceeds) | K2: Malawi's cumulative carbon emissions | L2: Management costs of the Fund (% of total Fund capital expended) | M2: Assumed annual rate of return on Fund investments | N2: Initial proportion of charge proceeds directly distributed as dividends that year (% of total proceeds) | P2: Year that money from distribution pot starts getting reinvested | Q2: Distribution costs of the pot (% of total distributed) | T2: Initial global population expected in 2025 | U2: Proportion of global population to receive dividends
A3: 22216120 | B3: 8231613070 | C3: 37.4 | E3: Same as carbon charge | F3: =15 -> 15 | H3: 0.005 | I3: 0.1 | K3: 0 | L3: 0.0005 | M3: 0.0634 | N3: =1-I3 -> 0.9 | P3: 2075 | Q3: 0.005 | U3: =A5 -> 0.0026988781
A4: Proportion of global population | B4: National carbon cap in Year 1 | C4: Annual shrinkage of cap | D4: Actual carbon consumption in 2025 (gigatonnes of CO2e) | E4: Annual growth of compensation amount for extra national allowances | F4: Annual growth of charge | I4: Initial annual increase in proportion going into the Fund (% of total proceeds) | J4: After 2035 annual increase in proportion going into the Fund (% of total proceeds) | K4: Starting endowment of the Fund if a charge on historic carbon emissions | L4: Malawi's expected mining revenues per year by 2029 | N4: Annual decrease in proportion of direct dividends (% of total proceeds) | P4: Maximum proportion that gets reinvested | R4: Proportion of pot to be distributed as climate grants | U4: Description of segment of population to receive dividends
A5: =A3/B3 -> 0.0026988781 | B5: =C3*A5 -> 0.10093804 | C5: 0.1 | D5: 0.00295 | E5: Same as carbon charge | F5: =C5*1.64 -> 0.164 | I5: 0.01 | J5: 0.05 | K5: =K3*5 -> 0 | L5: =2500000000*0.05 -> 125000000 | N5: =I5 -> 0.01 | P5: 0.1 | R5: 0.5 | U5: All adults and children in participating countries
A7: From start | B7: Year | C7: Per capita carbon cap (gigatonnes of CO2e) | D7: Amount of carbon actually used | E7: Amount received/paid out (from govt budget, not from carbon charge proceeds) as a result of sale/purchase of spare national allowances | F7: Carbon charge | G7: Amount raised | H7: Amount raised less 0.5% Trust costs | I7: Proportion of this amount going into the Fund | J7: Amount being placed in the Fund this year | K7: Total capital amount that would be in the Fund if there were no management costs | L7: Total capital amount in the Fund less cumulative 0.05% Fund management costs | M7: Investment income of the Fund this year | N7: Amount to be directly distributed (bypassing the Fund) | O7: Total amount in the distribution pot by the end of the year | P7: Amount from distribution pot to go back into Fund for reinvestment | Q7: Total amount in distribution pot less 0.5% distribution costs, and less any amount going back to the Fund | R7: Amount to be distributed as climate grants (This will be pooled with the amounts raised in other participating countries then distributed mainly to MAPA communities) | S7: Amount left in pot after climate grants distribution | T7: Global population (projected for 1st January each year) | U7: Proportion of global population to receive dividends if going only to this country | V7: Monthly dividend per person
A9: Year 1 | B9: 2025 | C9: =B5 -> 0.10093804 | D9: =$D$5 -> 0.00295 | F9: =$F$3 -> 15 | G9: =D9*F9*1000000000 -> 44250000 | H9: =G9*(1-$H$3) -> 44028750 | I9: =I3 -> 0.1 | J9: =(H9*I9) -> 4402875 | K9: =$K$5+J9+P9 -> 4402875 | L9: =($K$5+J9+P9)*(1-$L$3) -> 4400673.6 | M9: =L8*$M$3 -> 0 | N9: =H9*(1-I9) -> 39625875 | O9: =M9+N9 -> 39625875 | Q9: =(O9-P9)*(1-$Q$3) -> 39427746 | R9: =Q9*$R$5 -> 19713873 | S9: =Q9-R9 -> 19713873 | T9: 8231613070 | U9: =$U$3 -> 0.0026988781 | V9: =(S9/(T9*U9))/12 -> 0.073947329
A10: Year 2 | B10: 2026 | C10: =C9*(1-$C$5) -> 0.090844236 | D10: =D9+0.0011233 -> 0.0040733 | F10: =F9*(1+$F$5) -> 17.46 | G10: =D10*F10*1000000000 -> 71119818 | H10: =G10*(1-$H$3) -> 70764219 | I10: =$I$3+$I$5 -> 0.11 | J10: =(H10*I10)+E10 -> 7784064.1 | K10: =K9+J10+P9 -> 12186939 | L10: =(L9+J10+P9)*(1-$L$3) -> 12178645 | M10: =L9*$M$3 -> 279002.7 | N10: =H10*(1-I10) -> 62980155 | O10: =M10+N10 -> 63259158 | Q10: =(O10-P10)*(1-$Q$3) -> 62942862 | R10: =Q10*$R$5 -> 31471431 | S10: =Q10-R10 -> 31471431 | T10: 8300678395 | U10: =$U$3 -> 0.0026988781 | V10: =(S10/(T10*U10))/12 -> 0.11706805
A11: Year 3 | B11: 2027 | C11: =C10*(1-$C$5) -> 0.081759812 | D11: =D10+0.0011233 -> 0.0051966 | F11: =F10*(1+$F$5) -> 20.32344 | G11: =D11*F11*1000000000 -> 1.0561279e+08 | H11: =G11*(1-$H$3) -> 1.0508472e+08 | I11: =I10+$I$5 -> 0.12 | J11: =(H11*I11)+E11 -> 12610167 | K11: =K10+J11+P10 -> 24797106 | L11: =(L10+J11+P10)*(1-$L$3) -> 24776418 | M11: =L10*$M$3 -> 772126.11 | N11: =H11*(1-I11) -> 92474557 | O11: =M11+N11 -> 93246684 | Q11: =(O11-P11)*(1-$Q$3) -> 92780450 | R11: =Q11*$R$5 -> 46390225 | S11: =Q11-R11 -> 46390225 | T11: 8369094344 | U11: =$U$3 -> 0.0026988781 | V11: =(S11/(T11*U11))/12 -> 0.1711526
A12: Year 4 | B12: 2028 | C12: =C11*(1-$C$5) -> 0.073583831 | D12: =D11+0.0011233 -> 0.0063199 | F12: =F11*(1+$F$5) -> 23.656484 | G12: =D12*F12*1000000000 -> 1.4950661e+08 | H12: =G12*(1-$H$3) -> 1.4875908e+08 | I12: =I11+$I$5 -> 0.13 | J12: =(H12*I12)+E12 -> 19338681 | K12: =K11+J12+P11 -> 44135787 | L12: =(L11+J12+P11)*(1-$L$3) -> 44093041 | M12: =L11*$M$3 -> 1570824.9 | N12: =H12*(1-I12) -> 1.294204e+08 | O12: =M12+N12 -> 1.3099123e+08 | Q12: =(O12-P12)*(1-$Q$3) -> 1.3033627e+08 | R12: =Q12*$R$5 -> 65168135 | S12: =Q12-R12 -> 65168135 | T12: 8436618886 | U12: =$U$3 -> 0.0026988781 | V12: =(S12/(T12*U12))/12 -> 0.23850767
A13: Year 5 | B13: 2029 | C13: =C12*(1-$C$5) -> 0.066225448 | D13: =D12+0.0011233 -> 0.0074432 | F13: =F12*(1+$F$5) -> 27.536148 | G13: =D13*F13*1000000000 -> 2.0495705e+08 | H13: =G13*(1-$H$3) -> 2.0393227e+08 | I13: =I12+$I$5 -> 0.14 | J13: =(H13*I13)+E13 -> 28550518 | K13: =K12+J13+P12 -> 72686304 | L13: =(L12+J13+P12)*(1-$L$3) -> 72607237 | M13: =L12*$M$3 -> 2795498.8 | N13: =H13*(1-I13) -> 1.7538175e+08 | O13: =M13+N13 -> 1.7817725e+08 | Q13: =(O13-P13)*(1-$Q$3) -> 1.7728636e+08 | R13: =Q13*$R$5 -> 88643182 | S13: =Q13-R13 -> 88643182 | T13: 8503285323 | U13: =$U$3 -> 0.0026988781 | V13: =(S13/(T13*U13))/12 -> 0.32188006
A14: Year 6 | B14: 2030 | C14: =C13*(1-$C$5) -> 0.059602903 | D14: =D13+0.0011233 -> 0.0085665 | F14: =F13*(1+$F$5) -> 32.052076 | G14: =D14*F14*1000000000 -> 2.7457411e+08 | H14: =G14*(1-$H$3) -> 2.7320124e+08 | I14: =I13+$I$5 -> 0.15 | J14: =(H14*I14)+E14 -> 40980185 | K14: =K13+J14+P13 -> 1.1366649e+08 | L14: =(L13+J14+P13)*(1-$L$3) -> 1.1353063e+08 | M14: =L13*$M$3 -> 4603298.8 | N14: =H14*(1-I14) -> 2.3222105e+08 | O14: =M14+N14 -> 2.3682435e+08 | Q14: =(O14-P14)*(1-$Q$3) -> 2.3564023e+08 | R14: =Q14*$R$5 -> 1.1782011e+08 | S14: =Q14-R14 -> 1.1782011e+08 | T14: 8569124911 | U14: =$U$3 -> 0.0026988781 | V14: =(S14/(T14*U14))/12 -> 0.42453984
A15: Year 7 | B15: 2031 | C15: =C14*(1-$C$5) -> 0.053642613 | D15: =D14+0.0011233 -> 0.0096898 | F15: =F14*(1+$F$5) -> 37.308616 | G15: =D15*F15*1000000000 -> 3.6151303e+08 | H15: =G15*(1-$H$3) -> 3.5970546e+08 | I15: =I14+$I$5 -> 0.16 | J15: =(H15*I15)+E15 -> 57552874 | K15: =K14+J15+P14 -> 1.7121936e+08 | L15: =(L14+J15+P14)*(1-$L$3) -> 1.7099796e+08 | M15: =L14*$M$3 -> 7197841.8 | N15: =H15*(1-I15) -> 3.0215259e+08 | O15: =M15+N15 -> 3.0935043e+08 | Q15: =(O15-P15)*(1-$Q$3) -> 3.0780368e+08 | R15: =Q15*$R$5 -> 1.5390184e+08 | S15: =Q15-R15 -> 1.5390184e+08 | T15: 8634119333 | U15: =$U$3 -> 0.0026988781 | V15: =(S15/(T15*U15))/12 -> 0.55037824
A16: Year 8 | B16: 2032 | C16: =C15*(1-$C$5) -> 0.048278352 | D16: =D15+0.0011233 -> 0.0108131 | F16: =F15*(1+$F$5) -> 43.427229 | G16: =D16*F16*1000000000 -> 4.6958297e+08 | H16: =G16*(1-$H$3) -> 4.6723506e+08 | I16: =I15+$I$5 -> 0.17 | J16: =(H16*I16)+E16 -> 79429960 | K16: =K15+J16+P15 -> 2.5064932e+08 | L16: =(L15+J16+P15)*(1-$L$3) -> 2.5030271e+08 | M16: =L15*$M$3 -> 10841271 | N16: =H16*(1-I16) -> 3.878051e+08 | O16: =M16+N16 -> 3.9864637e+08 | Q16: =(O16-P16)*(1-$Q$3) -> 3.9665314e+08 | R16: =Q16*$R$5 -> 1.9832657e+08 | S16: =Q16-R16 -> 1.9832657e+08 | T16: 8698229812 | U16: =$U$3 -> 0.0026988781 | V16: =(S16/(T16*U16))/12 -> 0.70402083
A17: Year 9 | B17: 2033 | C17: =C16*(1-$C$5) -> 0.043450516 | D17: =D16+0.0011233 -> 0.0119364 | F17: =F16*(1+$F$5) -> 50.549295 | G17: =D17*F17*1000000000 -> 6.033766e+08 | H17: =G17*(1-$H$3) -> 6.0035972e+08 | I17: =I16+$I$5 -> 0.18 | J17: =(H17*I17)+E17 -> 1.0806475e+08 | K17: =K16+J17+P16 -> 3.5871407e+08 | L17: =(L16+J17+P16)*(1-$L$3) -> 3.5818827e+08 | M17: =L16*$M$3 -> 15869192 | N17: =H17*(1-I17) -> 4.9229497e+08 | O17: =M17+N17 -> 5.0816416e+08 | Q17: =(O17-P17)*(1-$Q$3) -> 5.0562334e+08 | R17: =Q17*$R$5 -> 2.5281167e+08 | S17: =Q17-R17 -> 2.5281167e+08 | T17: 8761449081 | U17: =$U$3 -> 0.0026988781 | V17: =(S17/(T17*U17))/12 -> 0.89095684
A18: Year 10 | B18: 2034 | C18: =C17*(1-$C$5) -> 0.039105465 | D18: =D17+0.0011233 -> 0.0130597 | F18: =F17*(1+$F$5) -> 58.839379 | G18: =D18*F18*1000000000 -> 7.6842464e+08 | H18: =G18*(1-$H$3) -> 7.6458252e+08 | I18: =I17+$I$5 -> 0.19 | J18: =(H18*I18)+E18 -> 1.4527068e+08 | K18: =K17+J18+P17 -> 5.0398475e+08 | L18: =(L17+J18+P17)*(1-$L$3) -> 5.0320722e+08 | M18: =L17*$M$3 -> 22709136 | N18: =H18*(1-I18) -> 6.1931184e+08 | O18: =M18+N18 -> 6.4202098e+08 | Q18: =(O18-P18)*(1-$Q$3) -> 6.3881087e+08 | R18: =Q18*$R$5 -> 3.1940544e+08 | S18: =Q18-R18 -> 3.1940544e+08 | T18: 8823784909 | U18: =$U$3 -> 0.0026988781 | V18: =(S18/(T18*U18))/12 -> 1.1176939
A19: Year 11 | B19: 2035 | C19: =C18*(1-$C$5) -> 0.035194918 | D19: =D18+0.0011233 -> 0.014183 | F19: =F18*(1+$F$5) -> 68.489037 | G19: =D19*F19*1000000000 -> 9.7138002e+08 | H19: =G19*(1-$H$3) -> 9.6652312e+08 | I19: =I18+$J$5 -> 0.24 | J19: =(H19*I19)+E19 -> 2.3196555e+08 | K19: =K18+J19+P18 -> 7.359503e+08 | L19: =(L18+J19+P18)*(1-$L$3) -> 7.3480518e+08 | M19: =L18*$M$3 -> 31903338 | N19: =H19*(1-I19) -> 7.3455757e+08 | O19: =M19+N19 -> 7.6646091e+08 | Q19: =(O19-P19)*(1-$Q$3) -> 7.626286e+08 | R19: =Q19*$R$5 -> 3.813143e+08 | S19: =Q19-R19 -> 3.813143e+08 | T19: 8885210181 | U19: =$U$3 -> 0.0026988781 | V19: =(S19/(T19*U19))/12 -> 1.3251068
A20: Year 12 | B20: 2036 | C20: =C19*(1-$C$5) -> 0.031675426 | D20: =D19+0.0011233 -> 0.0153063 | F20: =F19*(1+$F$5) -> 79.72124 | G20: =D20*F20*1000000000 -> 1.2202372e+09 | H20: =G20*(1-$H$3) -> 1.214136e+09 | I20: =I19+$J$5 -> 0.29 | J20: =(H20*I20)+E20 -> 3.5209945e+08 | K20: =K19+J20+P19 -> 1.0880497e+09 | L20: =(L19+J20+P19)*(1-$L$3) -> 1.0863612e+09 | M20: =L19*$M$3 -> 46586649 | N20: =H20*(1-I20) -> 8.6203658e+08 | O20: =M20+N20 -> 9.0862322e+08 | Q20: =(O20-P20)*(1-$Q$3) -> 9.0408011e+08 | R20: =Q20*$R$5 -> 4.5204005e+08 | S20: =Q20-R20 -> 4.5204005e+08 | T20: 8945686614 | U20: =$U$3 -> 0.0026988781 | V20: =(S20/(T20*U20))/12 -> 1.5602663
A21: Year 13 | B21: 2037 | C21: =C20*(1-$C$5) -> 0.028507884 | D21: =D20+0.0011233 -> 0.0164296 | F21: =F20*(1+$F$5) -> 92.795523 | G21: =D21*F21*1000000000 -> 1.5245933e+09 | H21: =G21*(1-$H$3) -> 1.5169704e+09 | I21: =I20+$J$5 -> 0.34 | J21: =(H21*I21)+E21 -> 5.1576992e+08 | K21: =K20+J21+P20 -> 1.6038197e+09 | L21: =(L20+J21+P20)*(1-$L$3) -> 1.60133e+09 | M21: =L20*$M$3 -> 68875299 | N21: =H21*(1-I21) -> 1.0012004e+09 | O21: =M21+N21 -> 1.0700757e+09 | Q21: =(O21-P21)*(1-$Q$3) -> 1.0647254e+09 | R21: =Q21*$R$5 -> 5.3236268e+08 | S21: =Q21-R21 -> 5.3236268e+08 | T21: 9005152624 | U21: =$U$3 -> 0.0026988781 | V21: =(S21/(T21*U21))/12 -> 1.8253746
A22: Year 14 | B22: 2038 | C22: =C21*(1-$C$5) -> 0.025657095 | D22: =D21+0.0011233 -> 0.0175529 | F22: =F21*(1+$F$5) -> 108.01399 | G22: =D22*F22*1000000000 -> 1.8959587e+09 | H22: =G22*(1-$H$3) -> 1.8864789e+09 | I22: =I21+$J$5 -> 0.39 | J22: =(H22*I22)+E22 -> 7.3572679e+08 | K22: =K21+J22+P21 -> 2.3395465e+09 | L22: =(L21+J22+P21)*(1-$L$3) -> 2.3358883e+09 | M22: =L21*$M$3 -> 1.0152432e+08 | N22: =H22*(1-I22) -> 1.1507522e+09 | O22: =M22+N22 -> 1.2522765e+09 | Q22: =(O22-P22)*(1-$Q$3) -> 1.2460151e+09 | R22: =Q22*$R$5 -> 6.2300755e+08 | S22: =Q22-R22 -> 6.2300755e+08 | T22: 9063572926 | U22: =$U$3 -> 0.0026988781 | V22: =(S22/(T22*U22))/12 -> 2.1224104
A23: Year 15 | B23: 2039 | C23: =C22*(1-$C$5) -> 0.023091386 | D23: =D22+0.0011233 -> 0.0186762 | F23: =F22*(1+$F$5) -> 125.72828 | G23: =D23*F23*1000000000 -> 2.3481266e+09 | H23: =G23*(1-$H$3) -> 2.3363859e+09 | I23: =I22+$J$5 -> 0.44 | J23: =(H23*I23)+E23 -> 1.0280098e+09 | K23: =K22+J23+P22 -> 3.3675563e+09 | L23: =(L22+J23+P22)*(1-$L$3) -> 3.3622161e+09 | M23: =L22*$M$3 -> 1.4809532e+08 | N23: =H23*(1-I23) -> 1.3083761e+09 | O23: =M23+N23 -> 1.4564714e+09 | Q23: =(O23-P23)*(1-$Q$3) -> 1.4491891e+09 | R23: =Q23*$R$5 -> 7.2459454e+08 | S23: =Q23-R23 -> 7.2459454e+08 | T23: 9120928380 | U23: =$U$3 -> 0.0026988781 | V23: =(S23/(T23*U23))/12 -> 2.4529658
A24: Year 16 | B24: 2040 | C24: =C23*(1-$C$5) -> 0.020782247 | D24: 0.0198 | F24: =F23*(1+$F$5) -> 146.34772 | G24: =D24*F24*1000000000 -> 2.8976849e+09 | H24: =G24*(1-$H$3) -> 2.8831965e+09 | I24: =I23+$J$5 -> 0.49 | J24: =(H24*I24)+E24 -> 1.4127663e+09 | K24: =K23+J24+P23 -> 4.7803225e+09 | L24: =(L23+J24+P23)*(1-$L$3) -> 4.7725949e+09 | M24: =L23*$M$3 -> 2.131645e+08 | N24: =H24*(1-I24) -> 1.4704302e+09 | O24: =M24+N24 -> 1.6835947e+09 | Q24: =(O24-P24)*(1-$Q$3) -> 1.6751767e+09 | R24: =Q24*$R$5 -> 8.3758836e+08 | S24: =Q24-R24 -> 8.3758836e+08 | T24: 9177190203 | U24: =$U$3 -> 0.0026988781 | V24: =(S24/(T24*U24))/12 -> 2.8180999
A25: Year 17 | B25: 2041 | C25: =C24*(1-$C$5) -> 0.018704023 | D25: =C25 -> 0.018704023 | F25: =F24*(1+$F$5) -> 170.34875 | G25: =D25*F25*1000000000 -> 3.1862068e+09 | H25: =G25*(1-$H$3) -> 3.1702758e+09 | I25: =I24+$J$5 -> 0.54 | J25: =(H25*I25)+E25 -> 1.7119489e+09 | K25: =K24+J25+P24 -> 6.4922714e+09 | L25: =(L24+J25+P24)*(1-$L$3) -> 6.4813016e+09 | M25: =L24*$M$3 -> 3.0258252e+08 | N25: =H25*(1-I25) -> 1.4583269e+09 | O25: =M25+N25 -> 1.7609094e+09 | Q25: =(O25-P25)*(1-$Q$3) -> 1.7521048e+09 | R25: =Q25*$R$5 -> 8.7605241e+08 | S25: =Q25-R25 -> 8.7605241e+08 | T25: 9232281575 | U25: =$U$3 -> 0.0026988781 | V25: =(S25/(T25*U25))/12 -> 2.9299252
A26: Year 18 | B26: 2042 | C26: =C25*(1-$C$5) -> 0.01683362 | D26: =C26 -> 0.01683362 | F26: =F25*(1+$F$5) -> 198.28594 | G26: =D26*F26*1000000000 -> 3.3378703e+09 | H26: =G26*(1-$H$3) -> 3.3211809e+09 | I26: =I25+$J$5 -> 0.59 | J26: =(H26*I26)+E26 -> 1.9594967e+09 | K26: =K25+J26+P25 -> 8.4517682e+09 | L26: =(L25+J26+P25)*(1-$L$3) -> 8.4365779e+09 | M26: =L25*$M$3 -> 4.1091452e+08 | N26: =H26*(1-I26) -> 1.3616842e+09 | O26: =M26+N26 -> 1.7725987e+09 | Q26: =(O26-P26)*(1-$Q$3) -> 1.7637357e+09 | R26: =Q26*$R$5 -> 8.8186785e+08 | S26: =Q26-R26 -> 8.8186785e+08 | T26: 9286110371 | U26: =$U$3 -> 0.0026988781 | V26: =(S26/(T26*U26))/12 -> 2.9322781
A27: Year 19 | B27: 2043 | C27: =C26*(1-$C$5) -> 0.015150258 | D27: =C27 -> 0.015150258 | F27: =F26*(1+$F$5) -> 230.80484 | G27: =D27*F27*1000000000 -> 3.4967529e+09 | H27: =G27*(1-$H$3) -> 3.4792691e+09 | I27: =I26+$J$5 -> 0.64 | J27: =(H27*I27)+E27 -> 2.2267322e+09 | K27: =K26+J27+P26 -> 1.06785e+10 | L27: =(L26+J27+P26)*(1-$L$3) -> 1.0657978e+10 | M27: =L26*$M$3 -> 5.3487904e+08 | N27: =H27*(1-I27) -> 1.2525369e+09 | O27: =M27+N27 -> 1.7874159e+09 | Q27: =(O27-P27)*(1-$Q$3) -> 1.7784788e+09 | R27: =Q27*$R$5 -> 8.8923942e+08 | S27: =Q27-R27 -> 8.8923942e+08 | T27: 9338661314 | U27: =$U$3 -> 0.0026988781 | V27: =(S27/(T27*U27))/12 -> 2.9401506
A28: Year 20 | B28: 2044 | C28: =C27*(1-$C$5) -> 0.013635232 | D28: =C28 -> 0.013635232 | F28: =F27*(1+$F$5) -> 268.65683 | G28: =D28*F28*1000000000 -> 3.6631983e+09 | H28: =G28*(1-$H$3) -> 3.6448823e+09 | I28: =I27+$J$5 -> 0.69 | J28: =(H28*I28)+E28 -> 2.5149688e+09 | K28: =K27+J28+P27 -> 1.3193469e+10 | L28: =(L27+J28+P27)*(1-$L$3) -> 1.3166361e+10 | M28: =L27*$M$3 -> 6.7571584e+08 | N28: =H28*(1-I28) -> 1.1299135e+09 | O28: =M28+N28 -> 1.8056294e+09 | Q28: =(O28-P28)*(1-$Q$3) -> 1.7966012e+09 | R28: =Q28*$R$5 -> 8.9830061e+08 | S28: =Q28-R28 -> 8.9830061e+08 | T28: 9389873693 | U28: =$U$3 -> 0.0026988781 | V28: =(S28/(T28*U28))/12 -> 2.9539112
A29: Year 21 | B29: 2045 | C29: =C28*(1-$C$5) -> 0.012271709 | D29: =C29 -> 0.012271709 | F29: =F28*(1+$F$5) -> 312.71655 | G29: =D29*F29*1000000000 -> 3.8375666e+09 | H29: =G29*(1-$H$3) -> 3.8183787e+09 | I29: =I28+$J$5 -> 0.74 | J29: =(H29*I29)+E29 -> 2.8256003e+09 | K29: =K28+J29+P28 -> 1.6019069e+10 | L29: =(L28+J29+P28)*(1-$L$3) -> 1.5983965e+10 | M29: =L28*$M$3 -> 8.3474728e+08 | N29: =H29*(1-I29) -> 9.9277847e+08 | O29: =M29+N29 -> 1.8275257e+09 | Q29: =(O29-P29)*(1-$Q$3) -> 1.8183881e+09 | R29: =Q29*$R$5 -> 9.0919406e+08 | S29: =Q29-R29 -> 9.0919406e+08 | T29: 9439639668 | U29: =$U$3 -> 0.0026988781 | V29: =(S29/(T29*U29))/12 -> 2.9739705
A30: Year 22 | B30: 2046 | C30: =C29*(1-$C$5) -> 0.011044538 | D30: =C30 -> 0.011044538 | F30: =F29*(1+$F$5) -> 364.00206 | G30: =D30*F30*1000000000 -> 4.0202347e+09 | H30: =G30*(1-$H$3) -> 4.0001336e+09 | I30: =I29+$J$5 -> 0.79 | J30: =(H30*I30)+E30 -> 3.1601055e+09 | K30: =K29+J30+P29 -> 1.9179175e+10 | L30: =(L29+J30+P29)*(1-$L$3) -> 1.9134499e+10 | M30: =L29*$M$3 -> 1.0133834e+09 | N30: =H30*(1-I30) -> 8.4002805e+08 | O30: =M30+N30 -> 1.8534114e+09 | Q30: =(O30-P30)*(1-$Q$3) -> 1.8441444e+09 | R30: =Q30*$R$5 -> 9.2207219e+08 | S30: =Q30-R30 -> 9.2207219e+08 | T30: 9487889604 | U30: =$U$3 -> 0.0026988781 | V30: =(S30/(T30*U30))/12 -> 3.0007567
A31: Year 23 | B31: 2047 | C31: =C30*(1-$C$5) -> 0.0099400845 | D31: =C31 -> 0.0099400845 | F31: =F30*(1+$F$5) -> 423.6984 | G31: =D31*F31*1000000000 -> 4.2115979e+09 | H31: =G31*(1-$H$3) -> 4.1905399e+09 | I31: =I30+$J$5 -> 0.84 | J31: =(H31*I31)+E31 -> 3.5200535e+09 | K31: =K30+J31+P30 -> 2.2699229e+10 | L31: =(L30+J31+P30)*(1-$L$3) -> 2.2643225e+10 | M31: =L30*$M$3 -> 1.2131272e+09 | N31: =H31*(1-I31) -> 6.7048639e+08 | O31: =M31+N31 -> 1.8836136e+09 | Q31: =(O31-P31)*(1-$Q$3) -> 1.8741955e+09 | R31: =Q31*$R$5 -> 9.3709776e+08 | S31: =Q31-R31 -> 9.3709776e+08 | T31: 9534545977 | U31: =$U$3 -> 0.0026988781 | V31: =(S31/(T31*U31))/12 -> 3.0347322
A32: Year 24 | B32: 2048 | C32: =C31*(1-$C$5) -> 0.008946076 | D32: =C32 -> 0.008946076 | F32: =F31*(1+$F$5) -> 493.18494 | G32: =D32*F32*1000000000 -> 4.41207e+09 | H32: =G32*(1-$H$3) -> 4.3900096e+09 | I32: =I31+$J$5 -> 0.89 | J32: =(H32*I32)+E32 -> 3.9071086e+09 | K32: =K31+J32+P31 -> 2.6606337e+10 | L32: =(L31+J32+P31)*(1-$L$3) -> 2.6537058e+10 | M32: =L31*$M$3 -> 1.4355805e+09 | N32: =H32*(1-I32) -> 4.8290106e+08 | O32: =M32+N32 -> 1.9184815e+09 | Q32: =(O32-P32)*(1-$Q$3) -> 1.9088891e+09 | R32: =Q32*$R$5 -> 9.5444455e+08 | S32: =Q32-R32 -> 9.5444455e+08 | T32: 9579536043 | U32: =$U$3 -> 0.0026988781 | V32: =(S32/(T32*U32))/12 -> 3.0763923
A33: Year 25 | B33: 2049 | C33: =C32*(1-$C$5) -> 0.0080514684 | D33: =C33 -> 0.0080514684 | F33: 500 | G33: =D33*F33*1000000000 -> 4.0257342e+09 | H33: =G33*(1-$H$3) -> 4.0056055e+09 | I33: =I32+$J$5 -> 0.94 | J33: =(H33*I33)+E33 -> 3.7652692e+09 | K33: =K32+J33+P32 -> 3.0371606e+10 | L33: =(L32+J33+P32)*(1-$L$3) -> 3.0287176e+10 | M33: =L32*$M$3 -> 1.6824495e+09 | N33: =H33*(1-I33) -> 2.4033633e+08 | O33: =M33+N33 -> 1.9227858e+09 | Q33: =(O33-P33)*(1-$Q$3) -> 1.9131719e+09 | R33: =Q33*$R$5 -> 9.5658595e+08 | S33: =Q33-R33 -> 9.5658595e+08 | T33: 9622824029 | U33: =$U$3 -> 0.0026988781 | V33: =(S33/(T33*U33))/12 -> 3.0694244
A34: Year 26 | B34: 2050 | C34: =C33*(1-$C$5) -> 0.0072463216 | D34: =C34 -> 0.0072463216 | F34: 500 | G34: =D34*F34*1000000000 -> 3.6231608e+09 | H34: =G34*(1-$H$3) -> 3.605045e+09 | I34: =I33+$J$5 -> 0.99 | J34: =(H34*I34)+E34 -> 3.5689945e+09 | K34: =K33+J34+P33 -> 3.3940601e+10 | L34: =(L33+J34+P33)*(1-$L$3) -> 3.3839243e+10 | M34: =L33*$M$3 -> 1.920207e+09 | N34: =H34*(1-I34) -> 36050450 | O34: =M34+N34 -> 1.9562574e+09 | Q34: =(O34-P34)*(1-$Q$3) -> 1.9464761e+09 | R34: =Q34*$R$5 -> 9.7323807e+08 | S34: =Q34-R34 -> 9.7323807e+08 | T34: 9664378587 | U34: =$U$3 -> 0.0026988781 | V34: =(S34/(T34*U34))/12 -> 3.109429
A35: Year 27 | B35: 2051 | C35: =C34*(1-$C$5) -> 0.0065216894 | D35: =C35 -> 0.0065216894 | F35: 500 | G35: =D35*F35*1000000000 -> 3.2608447e+09 | H35: =G35*(1-$H$3) -> 3.2445405e+09 | I35: 1 | J35: =(H35*I35)+E35 -> 3.2445405e+09 | K35: =K34+J35+P34 -> 3.7185141e+10 | L35: =(L34+J35+P34)*(1-$L$3) -> 3.7065241e+10 | M35: =L34*$M$3 -> 2.145408e+09 | N35: =H35*(1-I35) -> 0 | O35: =M35+N35 -> 2.145408e+09 | Q35: =(O35-P35)*(1-$Q$3) -> 2.1346809e+09 | R35: =Q35*$R$5 -> 1.0673405e+09 | S35: =Q35-R35 -> 1.0673405e+09 | T35: 9704192304 | U35: =$U$3 -> 0.0026988781 | V35: =(S35/(T35*U35))/12 -> 3.3960891
A36: Year 28 | B36: 2052 | C36: =C35*(1-$C$5) -> 0.0058695205 | D36: =C36 -> 0.0058695205 | F36: 500 | G36: =D36*F36*1000000000 -> 2.9347602e+09 | H36: =G36*(1-$H$3) -> 2.9200864e+09 | I36: 1 | J36: =(H36*I36)+E36 -> 2.9200864e+09 | K36: =K35+J36+P35 -> 4.0105228e+10 | L36: =(L35+J36+P35)*(1-$L$3) -> 3.9965335e+10 | M36: =L35*$M$3 -> 2.3499363e+09 | N36: =H36*(1-I36) -> 0 | O36: =M36+N36 -> 2.3499363e+09 | Q36: =(O36-P36)*(1-$Q$3) -> 2.3381866e+09 | R36: =Q36*$R$5 -> 1.1690933e+09 | S36: =Q36-R36 -> 1.1690933e+09 | T36: 9742264515 | U36: =$U$3 -> 0.0026988781 | V36: =(S36/(T36*U36))/12 -> 3.7053117
A37: Year 29 | B37: 2053 | C37: =C36*(1-$C$5) -> 0.0052825684 | D37: =C37 -> 0.0052825684 | F37: 500 | G37: =D37*F37*1000000000 -> 2.6412842e+09 | H37: =G37*(1-$H$3) -> 2.6280778e+09 | I37: 1 | J37: =(H37*I37)+E37 -> 2.6280778e+09 | K37: =K36+J37+P36 -> 4.2733305e+10 | L37: =(L36+J37+P36)*(1-$L$3) -> 4.2572116e+10 | M37: =L36*$M$3 -> 2.5338022e+09 | N37: =H37*(1-I37) -> 0 | O37: =M37+N37 -> 2.5338022e+09 | Q37: =(O37-P37)*(1-$Q$3) -> 2.5211332e+09 | R37: =Q37*$R$5 -> 1.2605666e+09 | S37: =Q37-R37 -> 1.2605666e+09 | T37: 9778614614 | U37: =$U$3 -> 0.0026988781 | V37: =(S37/(T37*U37))/12 -> 3.9803747
A38: Year 30 | B38: 2054 | C38: =C37*(1-$C$5) -> 0.0047543116 | D38: =C38 -> 0.0047543116 | F38: 500 | G38: =D38*F38*1000000000 -> 2.3771558e+09 | H38: =G38*(1-$H$3) -> 2.36527e+09 | I38: 1 | J38: =(H38*I38)+E38 -> 2.36527e+09 | K38: =K37+J38+P37 -> 4.5098576e+10 | L38: =(L37+J38+P37)*(1-$L$3) -> 4.4914917e+10 | M38: =L37*$M$3 -> 2.6990722e+09 | N38: =H38*(1-I38) -> 0 | O38: =M38+N38 -> 2.6990722e+09 | Q38: =(O38-P38)*(1-$Q$3) -> 2.6855768e+09 | R38: =Q38*$R$5 -> 1.3427884e+09 | S38: =Q38-R38 -> 1.3427884e+09 | T38: 9813251659 | U38: =$U$3 -> 0.0026988781 | V38: =(S38/(T38*U38))/12 -> 4.2250333
A39: Year 31 | B39: 2055 | C39: =C38*(1-$C$5) -> 0.0042788804 | D39: =C39 -> 0.0042788804 | F39: 500 | G39: =D39*F39*1000000000 -> 2.1394402e+09 | H39: =G39*(1-$H$3) -> 2.128743e+09 | I39: 1 | J39: =(H39*I39)+E39 -> 2.128743e+09 | K39: =K38+J39+P38 -> 4.7227319e+10 | L39: =(L38+J39+P38)*(1-$L$3) -> 4.7020139e+10 | M39: =L38*$M$3 -> 2.8476058e+09 | N39: =H39*(1-I39) -> 0 | O39: =M39+N39 -> 2.8476058e+09 | Q39: =(O39-P39)*(1-$Q$3) -> 2.8333677e+09 | R39: =Q39*$R$5 -> 1.4166839e+09 | S39: =Q39-R39 -> 1.4166839e+09 | T39: 9846237570 | U39: =$U$3 -> 0.0026988781 | V39: =(S39/(T39*U39))/12 -> 4.4426094
A40: Year 32 | B40: 2056 | C40: =C39*(1-$C$5) -> 0.0038509924 | D40: =C40 -> 0.0038509924 | F40: 500 | G40: =D40*F40*1000000000 -> 1.9254962e+09 | H40: =G40*(1-$H$3) -> 1.9158687e+09 | I40: 1 | J40: =(H40*I40)+E40 -> 1.9158687e+09 | K40: =K39+J40+P39 -> 4.9143187e+10 | L40: =(L39+J40+P39)*(1-$L$3) -> 4.8911539e+10 | M40: =L39*$M$3 -> 2.9810768e+09 | N40: =H40*(1-I40) -> 0 | O40: =M40+N40 -> 2.9810768e+09 | P40: =O40*0.2% -> 5962153.6 | Q40: =(O40-P40)*(1-$Q$3) -> 2.9602391e+09 | R40: =Q40*$R$5 -> 1.4801195e+09 | S40: =Q40-R40 -> 1.4801195e+09 | T40: 9877680392 | U40: =$U$3 -> 0.0026988781 | V40: =(S40/(T40*U40))/12 -> 4.6267636
A41: Year 33 | B41: 2057 | C41: =C40*(1-$C$5) -> 0.0034658931 | D41: =C41 -> 0.0034658931 | F41: 500 | G41: =D41*F41*1000000000 -> 1.7329466e+09 | H41: =G41*(1-$H$3) -> 1.7242818e+09 | I41: 1 | J41: =(H41*I41)+E41 -> 1.7242818e+09 | K41: =K40+J41+P40 -> 5.0873431e+10 | L41: =(L40+J41+P40)*(1-$L$3) -> 5.0616462e+10 | M41: =L40*$M$3 -> 3.1009916e+09 | N41: =H41*(1-I41) -> 0 | O41: =M41+N41 -> 3.1009916e+09 | P41: =O41*0.4% -> 12403966 | Q41: =(O41-P41)*(1-$Q$3) -> 3.0731447e+09 | R41: =Q41*$R$5 -> 1.5365723e+09 | S41: =Q41-R41 -> 1.5365723e+09 | T41: 9907637193 | U41: =$U$3 -> 0.0026988781 | V41: =(S41/(T41*U41))/12 -> 4.7887086
A42: Year 34 | B42: 2058 | C42: =C41*(1-$C$5) -> 0.0031193038 | D42: =C42 -> 0.0031193038 | F42: 500 | G42: =D42*F42*1000000000 -> 1.5596519e+09 | H42: =G42*(1-$H$3) -> 1.5518537e+09 | I42: 1 | J42: =(H42*I42)+E42 -> 1.5518537e+09 | K42: =K41+J42+P41 -> 5.2437689e+10 | L42: =(L41+J42+P41)*(1-$L$3) -> 5.215463e+10 | M42: =L41*$M$3 -> 3.2090837e+09 | N42: =H42*(1-I42) -> 0 | O42: =M42+N42 -> 3.2090837e+09 | P42: =O42*0.6% -> 19254502 | Q42: =(O42-P42)*(1-$Q$3) -> 3.1738801e+09 | R42: =Q42*$R$5 -> 1.58694e+09 | S42: =Q42-R42 -> 1.58694e+09 | T42: 9936164379 | U42: =$U$3 -> 0.0026988781 | V42: =(S42/(T42*U42))/12 -> 4.9314796
A43: Year 35 | B43: 2059 | C43: =C42*(1-$C$5) -> 0.0028073734 | D43: =C43 -> 0.0028073734 | F43: 500 | G43: =D43*F43*1000000000 -> 1.4036867e+09 | H43: =G43*(1-$H$3) -> 1.3966683e+09 | I43: 1 | J43: =(H43*I43)+E43 -> 1.3966683e+09 | K43: =K42+J43+P42 -> 5.3853612e+10 | L43: =(L42+J43+P42)*(1-$L$3) -> 5.3543767e+10 | M43: =L42*$M$3 -> 3.3066035e+09 | N43: =H43*(1-I43) -> 0 | O43: =M43+N43 -> 3.3066035e+09 | P43: =O43*0.8% -> 26452828 | Q43: =(O43-P43)*(1-$Q$3) -> 3.2637499e+09 | R43: =Q43*$R$5 -> 1.631875e+09 | S43: =Q43-R43 -> 1.631875e+09 | T43: 9963337082 | U43: =$U$3 -> 0.0026988781 | V43: =(S43/(T43*U43))/12 -> 5.0572864
A44: Year 36 | B44: 2060 | C44: =C43*(1-$C$5) -> 0.0025266361 | D44: =C44 -> 0.0025266361 | F44: 500 | G44: =D44*F44*1000000000 -> 1.2633181e+09 | H44: =G44*(1-$H$3) -> 1.2570015e+09 | I44: 1 | J44: =(H44*I44)+E44 -> 1.2570015e+09 | K44: =K43+J44+P43 -> 5.5137066e+10 | L44: =(L43+J44+P43)*(1-$L$3) -> 5.4799808e+10 | M44: =L43*$M$3 -> 3.3946748e+09 | N44: =H44*(1-I44) -> 0 | O44: =M44+N44 -> 3.3946748e+09 | P44: =O44*1% -> 33946748 | Q44: =(O44-P44)*(1-$Q$3) -> 3.3439245e+09 | R44: =Q44*$R$5 -> 1.6719622e+09 | S44: =Q44-R44 -> 1.6719622e+09 | T44: 9989232292 | U44: =$U$3 -> 0.0026988781 | V44: =(S44/(T44*U44))/12 -> 5.1680873
A45: Year 37 | B45: 2061 | C45: =C44*(1-$C$5) -> 0.0022739725 | D45: =C45 -> 0.0022739725 | F45: 500 | G45: =D45*F45*1000000000 -> 1.1369862e+09 | H45: =G45*(1-$H$3) -> 1.1313013e+09 | I45: 1 | J45: =(H45*I45)+E45 -> 1.1313013e+09 | K45: =K44+J45+P44 -> 5.6302314e+10 | L45: =(L44+J45+P44)*(1-$L$3) -> 5.5937073e+10 | M45: =L44*$M$3 -> 3.4743078e+09 | N45: =H45*(1-I45) -> 0 | O45: =M45+N45 -> 3.4743078e+09 | P45: =O45*1.2% -> 41691694 | Q45: =(O45-P45)*(1-$Q$3) -> 3.415453e+09 | R45: =Q45*$R$5 -> 1.7077265e+09 | S45: =Q45-R45 -> 1.7077265e+09 | T45: 10013916213 | U45: =$U$3 -> 0.0026988781 | V45: =(S45/(T45*U45))/12 -> 5.2656242
A46: Year 38 | B46: 2062 | C46: =C45*(1-$C$5) -> 0.0020465752 | D46: =C46 -> 0.0020465752 | F46: 500 | G46: =D46*F46*1000000000 -> 1.0232876e+09 | H46: =G46*(1-$H$3) -> 1.0181712e+09 | I46: 1 | J46: =(H46*I46)+E46 -> 1.0181712e+09 | K46: =K45+J46+P45 -> 5.7362177e+10 | L46: =(L45+J46+P45)*(1-$L$3) -> 5.6968438e+10 | M46: =L45*$M$3 -> 3.5464105e+09 | N46: =H46*(1-I46) -> 0 | O46: =M46+N46 -> 3.5464105e+09 | P46: =O46*1.4% -> 49649746 | Q46: =(O46-P46)*(1-$Q$3) -> 3.4792769e+09 | R46: =Q46*$R$5 -> 1.7396385e+09 | S46: =Q46-R46 -> 1.7396385e+09 | T46: 10037466600 | U46: =$U$3 -> 0.0026988781 | V46: =(S46/(T46*U46))/12 -> 5.3514365
A47: Year 39 | B47: 2063 | C47: =C46*(1-$C$5) -> 0.0018419177 | D47: =C47 -> 0.0018419177 | F47: 500 | G47: =D47*F47*1000000000 -> 9.2095886e+08 | H47: =G47*(1-$H$3) -> 9.1635406e+08 | I47: 1 | J47: =(H47*I47)+E47 -> 9.1635406e+08 | K47: =K46+J47+P46 -> 5.8328181e+10 | L47: =(L46+J47+P46)*(1-$L$3) -> 5.7905474e+10 | M47: =L46*$M$3 -> 3.611799e+09 | N47: =H47*(1-I47) -> 0 | O47: =M47+N47 -> 3.611799e+09 | P47: =O47*1.6% -> 57788783 | Q47: =(O47-P47)*(1-$Q$3) -> 3.5362401e+09 | R47: =Q47*$R$5 -> 1.7681201e+09 | S47: =Q47-R47 -> 1.7681201e+09 | T47: 10059950035 | U47: =$U$3 -> 0.0026988781 | V47: =(S47/(T47*U47))/12 -> 5.426895
A48: Year 40 | B48: 2064 | C48: =C47*(1-$C$5) -> 0.0016577259 | D48: =C48 -> 0.0016577259 | F48: 500 | G48: =D48*F48*1000000000 -> 8.2886297e+08 | H48: =G48*(1-$H$3) -> 8.2471866e+08 | I48: 1 | J48: =(H48*I48)+E48 -> 8.2471866e+08 | K48: =K47+J48+P47 -> 5.9210688e+10 | L48: =(L47+J48+P47)*(1-$L$3) -> 5.8758588e+10 | M48: =L47*$M$3 -> 3.6712071e+09 | N48: =H48*(1-I48) -> 0 | O48: =M48+N48 -> 3.6712071e+09 | P48: =O48*1.8% -> 66081727 | Q48: =(O48-P48)*(1-$Q$3) -> 3.5870997e+09 | R48: =Q48*$R$5 -> 1.7935499e+09 | S48: =Q48-R48 -> 1.7935499e+09 | T48: 10081402737 | U48: =$U$3 -> 0.0026988781 | V48: =(S48/(T48*U48))/12 -> 5.4932325
A49: Year 41 | B49: 2065 | C49: =C48*(1-$C$5) -> 0.0014919534 | D49: =C49 -> 0.0014919534 | F49: 500 | G49: =D49*F49*1000000000 -> 7.4597668e+08 | H49: =G49*(1-$H$3) -> 7.4224679e+08 | I49: 1 | J49: =(H49*I49)+E49 -> 7.4224679e+08 | K49: =K48+J49+P48 -> 6.0019017e+10 | L49: =(L48+J49+P48)*(1-$L$3) -> 5.9537133e+10 | M49: =L48*$M$3 -> 3.7252945e+09 | N49: =H49*(1-I49) -> 0 | O49: =M49+N49 -> 3.7252945e+09 | P49: =O49*2% -> 74505889 | Q49: =(O49-P49)*(1-$Q$3) -> 3.6325346e+09 | R49: =Q49*$R$5 -> 1.8162673e+09 | S49: =Q49-R49 -> 1.8162673e+09 | T49: 10101849561 | U49: =$U$3 -> 0.0026988781 | V49: =(S49/(T49*U49))/12 -> 5.5515514
A50: Year 42 | B50: 2066 | C50: =C49*(1-$C$5) -> 0.001342758 | D50: =C50 -> 0.001342758 | F50: 500 | G50: =D50*F50*1000000000 -> 6.7137901e+08 | H50: =G50*(1-$H$3) -> 6.6802211e+08 | I50: 1 | J50: =(H50*I50)+E50 -> 6.6802211e+08 | K50: =K49+J50+P49 -> 6.0761545e+10 | L50: =(L49+J50+P49)*(1-$L$3) -> 6.0249521e+10 | M50: =L49*$M$3 -> 3.7746542e+09 | N50: =H50*(1-I50) -> 0 | O50: =M50+N50 -> 3.7746542e+09 | P50: =O50*2.2% -> 83042393 | Q50: =(O50-P50)*(1-$Q$3) -> 3.6731538e+09 | R50: =Q50*$R$5 -> 1.8365769e+09 | S50: =Q50-R50 -> 1.8365769e+09 | T50: 10121317107 | U50: =$U$3 -> 0.0026988781 | V50: =(S50/(T50*U50))/12 -> 5.6028316
A51: Year 43 | B51: 2067 | C51: =C50*(1-$C$5) -> 0.0012084822 | D51: =C51 -> 0.0012084822 | F51: 500 | G51: =D51*F51*1000000000 -> 6.0424111e+08 | H51: =G51*(1-$H$3) -> 6.012199e+08 | I51: 1 | J51: =(H51*I51)+E51 -> 6.012199e+08 | K51: =K50+J51+P50 -> 6.1445807e+10 | L51: =(L50+J51+P50)*(1-$L$3) -> 6.0903316e+10 | M51: =L50*$M$3 -> 3.8198196e+09 | N51: =H51*(1-I51) -> 0 | O51: =M51+N51 -> 3.8198196e+09 | P51: =O51*2.4% -> 91675671 | Q51: =(O51-P51)*(1-$Q$3) -> 3.7095032e+09 | R51: =Q51*$R$5 -> 1.8547516e+09 | S51: =Q51-R51 -> 1.8547516e+09 | T51: 10139808361 | U51: =$U$3 -> 0.0026988781 | V51: =(S51/(T51*U51))/12 -> 5.6479586
A52: Year 44 | B52: 2068 | C52: =C51*(1-$C$5) -> 0.001087634 | D52: =C52 -> 0.001087634 | F52: 500 | G52: =D52*F52*1000000000 -> 5.43817e+08 | H52: =G52*(1-$H$3) -> 5.4109791e+08 | I52: 1 | J52: =(H52*I52)+E52 -> 5.4109791e+08 | K52: =K51+J52+P51 -> 6.2078581e+10 | L52: =(L51+J52+P51)*(1-$L$3) -> 6.1505322e+10 | M52: =L51*$M$3 -> 3.8612703e+09 | N52: =H52*(1-I52) -> 0 | O52: =M52+N52 -> 3.8612703e+09 | P52: =O52*2.6% -> 1.0039303e+08 | Q52: =(O52-P52)*(1-$Q$3) -> 3.7420729e+09 | R52: =Q52*$R$5 -> 1.8710364e+09 | S52: =Q52-R52 -> 1.8710364e+09 | T52: 10157301941 | U52: =$U$3 -> 0.0026988781 | V52: =(S52/(T52*U52))/12 -> 5.6877352
A53: Year 45 | B53: 2069 | C53: =C52*(1-$C$5) -> 0.00097887059 | D53: =C53 -> 0.00097887059 | F53: 500 | G53: =D53*F53*1000000000 -> 4.894353e+08 | H53: =G53*(1-$H$3) -> 4.8698812e+08 | I53: 1 | J53: =(H53*I53)+E53 -> 4.8698812e+08 | K53: =K52+J53+P52 -> 6.2665962e+10 | L53: =(L52+J53+P52)*(1-$L$3) -> 6.2061657e+10 | M53: =L52*$M$3 -> 3.8994374e+09 | N53: =H53*(1-I53) -> 0 | O53: =M53+N53 -> 3.8994374e+09 | P53: =O53*2.8% -> 1.0918425e+08 | Q53: =(O53-P53)*(1-$Q$3) -> 3.7713019e+09 | R53: =Q53*$R$5 -> 1.885651e+09 | S53: =Q53-R53 -> 1.885651e+09 | T53: 10173782135 | U53: =$U$3 -> 0.0026988781 | V53: =(S53/(T53*U53))/12 -> 5.7228763
A54: Year 46 | B54: 2070 | C54: =C53*(1-$C$5) -> 0.00088098353 | D54: =C54 -> 0.00088098353 | F54: 500 | G54: =D54*F54*1000000000 -> 4.4049177e+08 | H54: =G54*(1-$H$3) -> 4.3828931e+08 | I54: 1 | J54: =(H54*I54)+E54 -> 4.3828931e+08 | K54: =K53+J54+P53 -> 6.3213435e+10 | L54: =(L53+J54+P53)*(1-$L$3) -> 6.2577826e+10 | M54: =L53*$M$3 -> 3.934709e+09 | N54: =H54*(1-I54) -> 0 | O54: =M54+N54 -> 3.934709e+09 | P54: =O54*3% -> 1.1804127e+08 | Q54: =(O54-P54)*(1-$Q$3) -> 3.7975844e+09 | R54: =Q54*$R$5 -> 1.8987922e+09 | S54: =Q54-R54 -> 1.8987922e+09 | T54: 10189241959 | U54: =$U$3 -> 0.0026988781 | V54: =(S54/(T54*U54))/12 -> 5.7540159
A55: Year 47 | B55: 2071 | C55: =C54*(1-$C$5) -> 0.00079288518 | D55: =C55 -> 0.00079288518 | F55: 500 | G55: =D55*F55*1000000000 -> 3.9644259e+08 | H55: =G55*(1-$H$3) -> 3.9446038e+08 | I55: 1 | J55: =(H55*I55)+E55 -> 3.9446038e+08 | K55: =K54+J55+P54 -> 6.3725937e+10 | L55: =(L54+J55+P54)*(1-$L$3) -> 6.3058782e+10 | M55: =L54*$M$3 -> 3.9674342e+09 | N55: =H55*(1-I55) -> 0 | O55: =M55+N55 -> 3.9674342e+09 | P55: =O55*3.2% -> 1.2695789e+08 | Q55: =(O55-P55)*(1-$Q$3) -> 3.8212739e+09 | R55: =Q55*$R$5 -> 1.9106369e+09 | S55: =Q55-R55 -> 1.9106369e+09 | T55: 10203681568 | U55: =$U$3 -> 0.0026988781 | V55: =(S55/(T55*U55))/12 -> 5.7817161
A56: Year 48 | B56: 2072 | C56: =C55*(1-$C$5) -> 0.00071359666 | D56: =C56 -> 0.00071359666 | F56: 500 | G56: =D56*F56*1000000000 -> 3.5679833e+08 | H56: =G56*(1-$H$3) -> 3.5501434e+08 | I56: 1 | J56: =(H56*I56)+E56 -> 3.5501434e+08 | K56: =K55+J56+P55 -> 6.4207909e+10 | L56: =(L55+J56+P55)*(1-$L$3) -> 6.3508984e+10 | M56: =L55*$M$3 -> 3.9979268e+09 | N56: =H56*(1-I56) -> 0 | O56: =M56+N56 -> 3.9979268e+09 | P56: =O56*3.4% -> 1.3592951e+08 | Q56: =(O56-P56)*(1-$Q$3) -> 3.8426873e+09 | R56: =Q56*$R$5 -> 1.9213437e+09 | S56: =Q56-R56 -> 1.9213437e+09 | T56: 10217055169 | U56: =$U$3 -> 0.0026988781 | V56: =(S56/(T56*U56))/12 -> 5.8065049
A57: Year 49 | B57: 2073 | C57: =C56*(1-$C$5) -> 0.000642237 | D57: =C57 -> 0.000642237 | F57: 500 | G57: =D57*F57*1000000000 -> 3.211185e+08 | H57: =G57*(1-$H$3) -> 3.1951291e+08 | I57: =100% -> 1 | J57: =(H57*I57)+E57 -> 3.1951291e+08 | K57: =K56+J57+P56 -> 6.4663352e+10 | L57: =(L56+J57+P56)*(1-$L$3) -> 6.3932444e+10 | M57: =L56*$M$3 -> 4.0264696e+09 | N57: =H57*(1-I57) -> 0 | O57: =M57+N57 -> 4.0264696e+09 | P57: =O57*3.6% -> 1.4495291e+08 | Q57: =(O57-P57)*(1-$Q$3) -> 3.8621091e+09 | R57: =Q57*$R$5 -> 1.9310546e+09 | S57: =Q57-R57 -> 1.9310546e+09 | T57: 10229327824 | U57: =$U$3 -> 0.0026988781 | V57: =(S57/(T57*U57))/12 -> 5.8288508
A58: Year 50 | B58: 2074 | C58: =C57*(1-$C$5) -> 0.0005780133 | D58: =C58 -> 0.0005780133 | F58: 500 | G58: =D58*F58*1000000000 -> 2.8900665e+08 | H58: =G58*(1-$H$3) -> 2.8756162e+08 | I58: =100% -> 1 | J58: =(H58*I58)+E58 -> 2.8756162e+08 | K58: =K57+J58+P57 -> 6.5095866e+10 | L58: =(L57+J58+P57)*(1-$L$3) -> 6.4332776e+10 | M58: =L57*$M$3 -> 4.053317e+09 | N58: =H58*(1-I58) -> 0 | O58: =M58+N58 -> 4.053317e+09 | P58: =O58*3.8% -> 1.5402604e+08 | Q58: =(O58-P58)*(1-$Q$3) -> 3.8797945e+09 | R58: =Q58*$R$5 -> 1.9398972e+09 | S58: =Q58-R58 -> 1.9398972e+09 | T58: 10240485056 | U58: =$U$3 -> 0.0026988781 | V58: =(S58/(T58*U58))/12 -> 5.8491625
A59: Year 51 | B59: 2075 | C59: =C58*(1-$C$5) -> 0.00052021197 | D59: =C59 -> 0.00052021197 | F59: 500 | G59: =D59*F59*1000000000 -> 2.6010598e+08 | H59: =G59*(1-$H$3) -> 2.5880545e+08 | I59: =100% -> 1 | J59: =(H59*I59)+E59 -> 2.5880545e+08 | K59: =K58+J59+P58 -> 6.5508698e+10 | L59: =(L58+J59+P58)*(1-$L$3) -> 6.4713235e+10 | M59: =L58*$M$3 -> 4.078698e+09 | N59: =H59*(1-I59) -> 0 | O59: =M59+N59 -> 4.078698e+09 | P59: =O59*4% -> 1.6314792e+08 | Q59: =(O59-P59)*(1-$Q$3) -> 3.8959724e+09 | R59: =Q59*$R$5 -> 1.9479862e+09 | S59: =Q59-R59 -> 1.9479862e+09 | T59: 10250496432 | U59: =$U$3 -> 0.0026988781 | V59: =(S59/(T59*U59))/12 -> 5.8678157
A60: Year 52 | B60: 2076 | C60: =C59*(1-$C$5) -> 0.00046819077 | D60: =C60 -> 0.00046819077 | F60: 500 | G60: =D60*F60*1000000000 -> 2.3409539e+08 | H60: =G60*(1-$H$3) -> 2.3292491e+08 | I60: =100% -> 1 | J60: =(H60*I60)+E60 -> 2.3292491e+08 | K60: =K59+J60+P59 -> 6.590477e+10 | L60: =(L59+J60+P59)*(1-$L$3) -> 6.5076753e+10 | M60: =L59*$M$3 -> 4.1028191e+09 | N60: =H60*(1-I60) -> 0 | O60: =M60+N60 -> 4.1028191e+09 | P60: =O60*4.5% -> 1.8462686e+08 | Q60: =(O60-P60)*(1-$Q$3) -> 3.8986013e+09 | R60: =Q60*$R$5 -> 1.9493006e+09 | S60: =Q60-R60 -> 1.9493006e+09 | T60: 10259351432 | U60: =$U$3 -> 0.0026988781 | V60: =(S60/(T60*U60))/12 -> 5.8667071
A61: Year 53 | B61: 2077 | C61: =C60*(1-$C$5) -> 0.00042137169 | D61: =C61 -> 0.00042137169 | F61: 500 | G61: =D61*F61*1000000000 -> 2.1068585e+08 | H61: =G61*(1-$H$3) -> 2.0963242e+08 | I61: =100% -> 1 | J61: =(H61*I61)+E61 -> 2.0963242e+08 | K61: =K60+J61+P60 -> 6.629903e+10 | L61: =(L60+J61+P60)*(1-$L$3) -> 6.5438277e+10 | M61: =L60*$M$3 -> 4.1258662e+09 | N61: =H61*(1-I61) -> 0 | O61: =M61+N61 -> 4.1258662e+09 | P61: =O61*5% -> 2.0629331e+08 | Q61: =(O61-P61)*(1-$Q$3) -> 3.899975e+09 | R61: =Q61*$R$5 -> 1.9499875e+09 | S61: =Q61-R61 -> 1.9499875e+09 | T61: 10267045023 | U61: =$U$3 -> 0.0026988781 | V61: =(S61/(T61*U61))/12 -> 5.8643766
A62: Year 54 | B62: 2078 | C62: =C61*(1-$C$5) -> 0.00037923452 | D62: =C62 -> 0.00037923452 | F62: 500 | G62: =D62*F62*1000000000 -> 1.8961726e+08 | H62: =G62*(1-$H$3) -> 1.8866918e+08 | I62: =100% -> 1 | J62: =(H62*I62)+E62 -> 1.8866918e+08 | K62: =K61+J62+P61 -> 6.6693992e+10 | L62: =(L61+J62+P61)*(1-$L$3) -> 6.5800323e+10 | M62: =L61*$M$3 -> 4.1487868e+09 | N62: =H62*(1-I62) -> 0 | O62: =M62+N62 -> 4.1487868e+09 | P62: =O62*5.5% -> 2.2818327e+08 | Q62: =(O62-P62)*(1-$Q$3) -> 3.9010005e+09 | R62: =Q62*$R$5 -> 1.9505002e+09 | S62: =Q62-R62 -> 1.9505002e+09 | T62: 10273556322 | U62: =$U$3 -> 0.0026988781 | V62: =(S62/(T62*U62))/12 -> 5.8622008
A63: Year 55 | B63: 2079 | C63: =C62*(1-$C$5) -> 0.00034131107 | D63: =C63 -> 0.00034131107 | F63: 500 | G63: =D63*F63*1000000000 -> 1.7065554e+08 | H63: =G63*(1-$H$3) -> 1.6980226e+08 | I63: =100% -> 1 | J63: =(H63*I63)+E63 -> 1.6980226e+08 | K63: =K62+J63+P62 -> 6.7091978e+10 | L63: =(L62+J63+P62)*(1-$L$3) -> 6.6165209e+10 | M63: =L62*$M$3 -> 4.1717405e+09 | N63: =H63*(1-I63) -> 0 | O63: =M63+N63 -> 4.1717405e+09 | P63: =O63*6% -> 2.5030443e+08 | Q63: =(O63-P63)*(1-$Q$3) -> 3.9018289e+09 | R63: =Q63*$R$5 -> 1.9509144e+09 | S63: =Q63-R63 -> 1.9509144e+09 | T63: 10278887473 | U63: =$U$3 -> 0.0026988781 | V63: =(S63/(T63*U63))/12 -> 5.8604046
A64: Year 56 | B64: 2080 | C64: =C63*(1-$C$5) -> 0.00030717996 | D64: =C64 -> 0.00030717996 | F64: 500 | G64: =D64*F64*1000000000 -> 1.5358998e+08 | H64: =G64*(1-$H$3) -> 1.5282203e+08 | I64: =100% -> 1 | J64: =(H64*I64)+E64 -> 1.5282203e+08 | K64: =K63+J64+P63 -> 6.7495104e+10 | L64: =(L63+J64+P63)*(1-$L$3) -> 6.6535052e+10 | M64: =L63*$M$3 -> 4.1948743e+09 | N64: =H64*(1-I64) -> 0 | O64: =M64+N64 -> 4.1948743e+09 | P64: =O64*6.5% -> 2.7266683e+08 | Q64: =(O64-P64)*(1-$Q$3) -> 3.9025964e+09 | R64: =Q64*$R$5 -> 1.9512982e+09 | S64: =Q64-R64 -> 1.9512982e+09 | T64: 10283078029 | U64: =$U$3 -> 0.0026988781 | V64: =(S64/(T64*U64))/12 -> 5.8591687
A65: Year 57 | B65: 2081 | C65: =C64*(1-$C$5) -> 0.00027646197 | D65: =C65 -> 0.00027646197 | F65: 500 | G65: =D65*F65*1000000000 -> 1.3823098e+08 | H65: =G65*(1-$H$3) -> 1.3753983e+08 | I65: =100% -> 1 | J65: =(H65*I65)+E65 -> 1.3753983e+08 | K65: =K64+J65+P64 -> 6.7905311e+10 | L65: =(L64+J65+P64)*(1-$L$3) -> 6.6911786e+10 | M65: =L64*$M$3 -> 4.2183223e+09 | N65: =H65*(1-I65) -> 0 | O65: =M65+N65 -> 4.2183223e+09 | P65: =O65*7% -> 2.9528256e+08 | Q65: =(O65-P65)*(1-$Q$3) -> 3.9034245e+09 | R65: =Q65*$R$5 -> 1.9517123e+09 | S65: =Q65-R65 -> 1.9517123e+09 | T65: 10286161735 | U65: =$U$3 -> 0.0026988781 | V65: =(S65/(T65*U65))/12 -> 5.8586551
A66: Year 58 | B66: 2082 | C66: =C65*(1-$C$5) -> 0.00024881577 | D66: =C66 -> 0.00024881577 | F66: 500 | G66: =D66*F66*1000000000 -> 1.2440789e+08 | H66: =G66*(1-$H$3) -> 1.2378585e+08 | I66: =100% -> 1 | J66: =(H66*I66)+E66 -> 1.2378585e+08 | K66: =K65+J66+P65 -> 6.8324379e+10 | L66: =(L65+J66+P65)*(1-$L$3) -> 6.7297189e+10 | M66: =L65*$M$3 -> 4.2422072e+09 | N66: =H66*(1-I66) -> 0 | O66: =M66+N66 -> 4.2422072e+09 | P66: =O66*7.5% -> 3.1816554e+08 | Q66: =(O66-P66)*(1-$Q$3) -> 3.9044215e+09 | R66: =Q66*$R$5 -> 1.9522107e+09 | S66: =Q66-R66 -> 1.9522107e+09 | T66: 10288205050 | U66: =$U$3 -> 0.0026988781 | V66: =(S66/(T66*U66))/12 -> 5.8589875
A67: Year 59 | B67: 2083 | C67: =C66*(1-$C$5) -> 0.00022393419 | D67: =C67 -> 0.00022393419 | F67: 500 | G67: =D67*F67*1000000000 -> 1.119671e+08 | H67: =G67*(1-$H$3) -> 1.1140726e+08 | I67: =100% -> 1 | J67: =(H67*I67)+E67 -> 1.1140726e+08 | K67: =K66+J67+P66 -> 6.8753952e+10 | L67: =(L66+J67+P66)*(1-$L$3) -> 6.7692898e+10 | M67: =L66*$M$3 -> 4.2666418e+09 | N67: =H67*(1-I67) -> 0 | O67: =M67+N67 -> 4.2666418e+09 | P67: =O67*8% -> 3.4133134e+08 | Q67: =(O67-P67)*(1-$Q$3) -> 3.9056839e+09 | R67: =Q67*$R$5 -> 1.9528419e+09 | S67: =Q67-R67 -> 1.9528419e+09 | T67: 10289247323 | U67: =$U$3 -> 0.0026988781 | V67: =(S67/(T67*U67))/12 -> 5.8602882
A68: Year 60 | B68: 2084 | C68: =C67*(1-$C$5) -> 0.00020154077 | D68: =C68 -> 0.00020154077 | F68: 500 | G68: =D68*F68*1000000000 -> 1.0077039e+08 | H68: =G68*(1-$H$3) -> 1.0026654e+08 | I68: =100% -> 1 | J68: =(H68*I68)+E68 -> 1.0026654e+08 | K68: =K67+J68+P67 -> 6.919555e+10 | L68: =(L67+J68+P67)*(1-$L$3) -> 6.8100429e+10 | M68: =L67*$M$3 -> 4.2917297e+09 | N68: =H68*(1-I68) -> 0 | O68: =M68+N68 -> 4.2917297e+09 | P68: =O68*8.5% -> 3.6479703e+08 | Q68: =(O68-P68)*(1-$Q$3) -> 3.907298e+09 | R68: =Q68*$R$5 -> 1.953649e+09 | S68: =Q68-R68 -> 1.953649e+09 | T68: 10289315244 | U68: =$U$3 -> 0.0026988781 | V68: =(S68/(T68*U68))/12 -> 5.8626715
A69: Year 61 | B69: 2085 | C69: =C68*(1-$C$5) -> 0.0001813867 | D69: =C69 -> 0.0001813867 | F69: 500 | G69: =D69*F69*1000000000 -> 90693349 | H69: =G69*(1-$H$3) -> 90239882 | I69: =100% -> 1 | J69: =(H69*I69)+E69 -> 90239882 | K69: =K68+J69+P68 -> 6.9650587e+10 | L69: =(L68+J69+P68)*(1-$L$3) -> 6.8521188e+10 | M69: =L68*$M$3 -> 4.3175672e+09 | N69: =H69*(1-I69) -> 0 | O69: =M69+N69 -> 4.3175672e+09 | P69: =O69*9% -> 3.8858105e+08 | Q69: =(O69-P69)*(1-$Q$3) -> 3.9093412e+09 | R69: =Q69*$R$5 -> 1.9546706e+09 | S69: =Q69-R69 -> 1.9546706e+09 | T69: 10288456599 | U69: =$U$3 -> 0.0026988781 | V69: =(S69/(T69*U69))/12 -> 5.8662267
A70: Year 62 | B70: 2086 | C70: =C69*(1-$C$5) -> 0.00016324803 | D70: =C70 -> 0.00016324803 | F70: 500 | G70: =D70*F70*1000000000 -> 81624014 | H70: =G70*(1-$H$3) -> 81215894 | I70: =100% -> 1 | J70: =(H70*I70)+E70 -> 81215894 | K70: =K69+J70+P69 -> 7.0120384e+10 | L70: =(L69+J70+P69)*(1-$L$3) -> 6.8956489e+10 | M70: =L69*$M$3 -> 4.3442433e+09 | N70: =H70*(1-I70) -> 0 | O70: =M70+N70 -> 4.3442433e+09 | P70: =O70*9.5% -> 4.1270311e+08 | Q70: =(O70-P70)*(1-$Q$3) -> 3.9118825e+09 | R70: =Q70*$R$5 -> 1.9559412e+09 | S70: =Q70-R70 -> 1.9559412e+09 | T70: 10286708360 | U70: =$U$3 -> 0.0026988781 | V70: =(S70/(T70*U70))/12 -> 5.8710377
A71: Year 63 | B71: 2087 | C71: =C70*(1-$C$5) -> 0.00014692322 | D71: =C71 -> 0.00014692322 | F71: 500 | G71: =D71*F71*1000000000 -> 73461612 | H71: =G71*(1-$H$3) -> 73094304 | I71: =100% -> 1 | J71: =(H71*I71)+E71 -> 73094304 | K71: =K70+J71+P70 -> 7.0606181e+10 | L71: =(L70+J71+P70)*(1-$L$3) -> 6.9407566e+10 | M71: =L70*$M$3 -> 4.3718414e+09 | N71: =H71*(1-I71) -> 0 | O71: =M71+N71 -> 4.3718414e+09 | P71: =O71*$P$5 -> 4.3718414e+08 | Q71: =(O71-P71)*(1-$Q$3) -> 3.914984e+09 | R71: =Q71*$R$5 -> 1.957492e+09 | S71: =Q71-R71 -> 1.957492e+09 | T71: 10284111374 | U71: =$U$3 -> 0.0026988781 | V71: =(S71/(T71*U71))/12 -> 5.8771762
A72: Year 64 | B72: 2088 | C72: =C71*(1-$C$5) -> 0.0001322309 | D72: =C72 -> 0.0001322309 | F72: 500 | G72: =D72*F72*1000000000 -> 66115451 | H72: =G72*(1-$H$3) -> 65784874 | I72: =100% -> 1 | J72: =(H72*I72)+E72 -> 65784874 | K72: =K71+J72+P71 -> 7.110915e+10 | L72: =(L71+J72+P71)*(1-$L$3) -> 6.9875579e+10 | M72: =L71*$M$3 -> 4.4004397e+09 | N72: =H72*(1-I72) -> 0 | O72: =M72+N72 -> 4.4004397e+09 | P72: =O72*$P$5 -> 4.4004397e+08 | Q72: =(O72-P72)*(1-$Q$3) -> 3.9405937e+09 | R72: =Q72*$R$5 -> 1.9702969e+09 | S72: =Q72-R72 -> 1.9702969e+09 | T72: 10280704572 | U72: =$U$3 -> 0.0026988781 | V72: =(S72/(T72*U72))/12 -> 5.9175819
A73: Year 65 | B73: 2089 | C73: =C72*(1-$C$5) -> 0.00011900781 | D73: =C73 -> 0.00011900781 | F73: 500 | G73: =D73*F73*1000000000 -> 59503906 | H73: =G73*(1-$H$3) -> 59206387 | I73: =100% -> 1 | J73: =(H73*I73)+E73 -> 59206387 | K73: =K72+J73+P72 -> 7.16084e+10 | L73: =(L72+J73+P72)*(1-$L$3) -> 7.0339642e+10 | M73: =L72*$M$3 -> 4.4301117e+09 | N73: =H73*(1-I73) -> 0 | O73: =M73+N73 -> 4.4301117e+09 | P73: =O73*$P$5 -> 4.4301117e+08 | Q73: =(O73-P73)*(1-$Q$3) -> 3.9671651e+09 | R73: =Q73*$R$5 -> 1.9835825e+09 | S73: =Q73-R73 -> 1.9835825e+09 | T73: 10276518280 | U73: =$U$3 -> 0.0026988781 | V73: =(S73/(T73*U73))/12 -> 5.9599109
A74: Year 66 | B74: 2090 | C74: =C73*(1-$C$5) -> 0.00010710703 | D74: =C74 -> 0.00010710703 | F74: 500 | G74: =D74*F74*1000000000 -> 53553515 | H74: =G74*(1-$H$3) -> 53285748 | I74: =100% -> 1 | J74: =(H74*I74)+E74 -> 53285748 | K74: =K73+J74+P73 -> 7.2104697e+10 | L74: =(L73+J74+P73)*(1-$L$3) -> 7.0800521e+10 | M74: =L73*$M$3 -> 4.4595333e+09 | N74: =H74*(1-I74) -> 0 | O74: =M74+N74 -> 4.4595333e+09 | P74: =O74*$P$5 -> 4.4595333e+08 | Q74: =(O74-P74)*(1-$Q$3) -> 3.9935121e+09 | R74: =Q74*$R$5 -> 1.996756e+09 | S74: =Q74-R74 -> 1.996756e+09 | T74: 10271565070 | U74: =$U$3 -> 0.0026988781 | V74: =(S74/(T74*U74))/12 -> 6.0023854
A75: Year 67 | B75: 2091 | C75: =C74*(1-$C$5) -> 9.6396328e-05 | D75: =C75 -> 9.6396328e-05 | F75: 500 | G75: =D75*F75*1000000000 -> 48198164 | H75: =G75*(1-$H$3) -> 47957173 | I75: =100% -> 1 | J75: =(H75*I75)+E75 -> 47957173 | K75: =K74+J75+P74 -> 7.2598608e+10 | L75: =(L74+J75+P74)*(1-$L$3) -> 7.1258784e+10 | M75: =L74*$M$3 -> 4.488753e+09 | N75: =H75*(1-I75) -> 0 | O75: =M75+N75 -> 4.488753e+09 | P75: =O75*$P$5 -> 4.488753e+08 | Q75: =(O75-P75)*(1-$Q$3) -> 4.0196783e+09 | R75: =Q75*$R$5 -> 2.0098392e+09 | S75: =Q75-R75 -> 2.0098392e+09 | T75: 10265861714 | U75: =$U$3 -> 0.0026988781 | V75: =(S75/(T75*U75))/12 -> 6.0450707
A76: Year 68 | B76: 2092 | C76: =C75*(1-$C$5) -> 8.6756695e-05 | D76: =C76 -> 8.6756695e-05 | F76: 500 | G76: =D76*F76*1000000000 -> 43378347 | H76: =G76*(1-$H$3) -> 43161456 | I76: =100% -> 1 | J76: =(H76*I76)+E76 -> 43161456 | K76: =K75+J76+P75 -> 7.3090645e+10 | L76: =(L75+J76+P75)*(1-$L$3) -> 7.1714946e+10 | M76: =L75*$M$3 -> 4.5178069e+09 | N76: =H76*(1-I76) -> 0 | O76: =M76+N76 -> 4.5178069e+09 | P76: =O76*$P$5 -> 4.5178069e+08 | Q76: =(O76-P76)*(1-$Q$3) -> 4.0456961e+09 | R76: =Q76*$R$5 -> 2.0228481e+09 | S76: =Q76-R76 -> 2.0228481e+09 | T76: 10259408375 | U76: =$U$3 -> 0.0026988781 | V76: =(S76/(T76*U76))/12 -> 6.0880251
A77: Year 69 | B77: 2093 | C77: =C76*(1-$C$5) -> 7.8081025e-05 | D77: =C77 -> 7.8081025e-05 | F77: 500 | G77: =D77*F77*1000000000 -> 39040513 | H77: =G77*(1-$H$3) -> 38845310 | I77: =100% -> 1 | J77: =(H77*I77)+E77 -> 38845310 | K77: =K76+J77+P76 -> 7.3581271e+10 | L77: =(L76+J77+P76)*(1-$L$3) -> 7.2169469e+10 | M77: =L76*$M$3 -> 4.5467276e+09 | N77: =H77*(1-I77) -> 0 | O77: =M77+N77 -> 4.5467276e+09 | P77: =O77*$P$5 -> 4.5467276e+08 | Q77: =(O77-P77)*(1-$Q$3) -> 4.0715945e+09 | R77: =Q77*$R$5 -> 2.0357973e+09 | S77: =Q77-R77 -> 2.0357973e+09 | T77: 10252184759 | U77: =$U$3 -> 0.0026988781 | V77: =(S77/(T77*U77))/12 -> 6.1313145
A78: Year 70 | B78: 2094 | C78: =C77*(1-$C$5) -> 7.0272923e-05 | D78: =C78 -> 7.0272923e-05 | F78: 500 | G78: =D78*F78*1000000000 -> 35136461 | H78: =G78*(1-$H$3) -> 34960779 | I78: =100% -> 1 | J78: =(H78*I78)+E78 -> 34960779 | K78: =K77+J78+P77 -> 7.4070904e+10 | L78: =(L77+J78+P77)*(1-$L$3) -> 7.2622773e+10 | M78: =L77*$M$3 -> 4.5755443e+09 | N78: =H78*(1-I78) -> 0 | O78: =M78+N78 -> 4.5755443e+09 | P78: =O78*$P$5 -> 4.5755443e+08 | Q78: =(O78-P78)*(1-$Q$3) -> 4.0974e+09 | R78: =Q78*$R$5 -> 2.0487e+09 | S78: =Q78-R78 -> 2.0487e+09 | T78: 10244185837 | U78: =$U$3 -> 0.0026988781 | V78: =(S78/(T78*U78))/12 -> 6.1749921
A79: Year 71 | B79: 2095 | C79: =C78*(1-$C$5) -> 6.3245631e-05 | D79: =C79 -> 6.3245631e-05 | F79: 500 | G79: =D79*F79*1000000000 -> 31622815 | H79: =G79*(1-$H$3) -> 31464701 | I79: =100% -> 1 | J79: =(H79*I79)+E79 -> 31464701 | K79: =K78+J79+P78 -> 7.4559923e+10 | L79: =(L78+J79+P78)*(1-$L$3) -> 7.3075236e+10 | M79: =L78*$M$3 -> 4.6042838e+09 | N79: =H79*(1-I79) -> 0 | O79: =M79+N79 -> 4.6042838e+09 | P79: =O79*$P$5 -> 4.6042838e+08 | Q79: =(O79-P79)*(1-$Q$3) -> 4.1231362e+09 | R79: =Q79*$R$5 -> 2.0615681e+09 | S79: =Q79-R79 -> 2.0615681e+09 | T79: 10235403601 | U79: =$U$3 -> 0.0026988781 | V79: =(S79/(T79*U79))/12 -> 6.2191094
A80: Year 72 | B80: 2096 | C80: =C79*(1-$C$5) -> 5.6921068e-05 | D80: =C80 -> 5.6921068e-05 | F80: 500 | G80: =D80*F80*1000000000 -> 28460534 | H80: =G80*(1-$H$3) -> 28318231 | I80: =100% -> 1 | J80: =(H80*I80)+E80 -> 28318231 | K80: =K79+J80+P79 -> 7.504867e+10 | L80: =(L79+J80+P79)*(1-$L$3) -> 7.3527201e+10 | M80: =L79*$M$3 -> 4.63297e+09 | N80: =H80*(1-I80) -> 0 | O80: =M80+N80 -> 4.63297e+09 | P80: =O80*$P$5 -> 4.63297e+08 | Q80: =(O80-P80)*(1-$Q$3) -> 4.1488246e+09 | R80: =Q80*$R$5 -> 2.0744123e+09 | S80: =Q80-R80 -> 2.0744123e+09 | T80: 10225850874 | U80: =$U$3 -> 0.0026988781 | V80: =(S80/(T80*U80))/12 -> 6.2637024
A81: Year 73 | B81: 2097 | C81: =C80*(1-$C$5) -> 5.1228961e-05 | D81: =C81 -> 5.1228961e-05 | F81: 500 | G81: =D81*F81*1000000000 -> 25614480 | H81: =G81*(1-$H$3) -> 25486408 | I81: =100% -> 1 | J81: =(H81*I81)+E81 -> 25486408 | K81: =K80+J81+P80 -> 7.5537453e+10 | L81: =(L80+J81+P80)*(1-$L$3) -> 7.3978976e+10 | M81: =L80*$M$3 -> 4.6616245e+09 | N81: =H81*(1-I81) -> 0 | O81: =M81+N81 -> 4.6616245e+09 | P81: =O81*$P$5 -> 4.6616245e+08 | Q81: =(O81-P81)*(1-$Q$3) -> 4.1744848e+09 | R81: =Q81*$R$5 -> 2.0872424e+09 | S81: =Q81-R81 -> 2.0872424e+09 | T81: 10215549310 | U81: =$U$3 -> 0.0026988781 | V81: =(S81/(T81*U81))/12 -> 6.3087984
A82: Year 74 | B82: 2098 | C82: =C81*(1-$C$5) -> 4.6106065e-05 | D82: =C82 -> 4.6106065e-05 | F82: 500 | G82: =D82*F82*1000000000 -> 23053032 | H82: =G82*(1-$H$3) -> 22937767 | I82: =100% -> 1 | J82: =(H82*I82)+E82 -> 22937767 | K82: =K81+J82+P81 -> 7.6026554e+10 | L82: =(L81+J82+P81)*(1-$L$3) -> 7.4430842e+10 | M82: =L81*$M$3 -> 4.6902671e+09 | N82: =H82*(1-I82) -> 0 | O82: =M82+N82 -> 4.6902671e+09 | P82: =O82*$P$5 -> 4.6902671e+08 | Q82: =(O82-P82)*(1-$Q$3) -> 4.2001342e+09 | R82: =Q82*$R$5 -> 2.1000671e+09 | S82: =Q82-R82 -> 2.1000671e+09 | T82: 10204489862 | U82: =$U$3 -> 0.0026988781 | V82: =(S82/(T82*U82))/12 -> 6.3544411
... A84: Year 76 | B84: 2100 | C84: =C83*(1-$C$5) -> 3.7345912e-05 | D84: =C84 -> 3.7345912e-05 | F84: 500 | G84: =D84*F84*1000000000 -> 18672956 | H84: =G84*(1-$H$3) -> 18579591 | I84: =100% -> 1 | J84: =(H84*I84)+E84 -> 18579591 | K84: =K83+J84+P83 -> 7.7006695e+10 | L84: =(L83+J84+P83)*(1-$L$3) -> 7.5335837e+10 | M84: =L83*$M$3 -> 4.7475856e+09 | N84: =H84*(1-I84) -> 0 | O84: =M84+N84 -> 4.7475856e+09 | P84: =O84*$P$5 -> 4.7475856e+08 | Q84: =(O84-P84)*(1-$Q$3) -> 4.2514629e+09 | R84: =Q84*$R$5 -> 2.1257314e+09 | S84: =Q84-R84 -> 2.1257314e+09 | T84: 10180160751 | U84: =$U$3 -> 0.0026988781 | V84: =(S84/(T84*U84))/12 -> 6.4474688
A85: Year 77 | B85: 2101 | C85: =C84*(1-$C$5) -> 3.3611321e-05 | D85: =C85 -> 3.3611321e-05 | F85: 500 | G85: =D85*F85*1000000000 -> 16805661 | H85: =G85*(1-$H$3) -> 16721632 | I85: =100% -> 1 | J85: =(H85*I85)+E85 -> 16721632 | K85: =K84+J85+P84 -> 7.7498176e+10 | L85: =(L84+J85+P84)*(1-$L$3) -> 7.5789404e+10 | M85: =L84*$M$3 -> 4.7762921e+09 | N85: =H85*(1-I85) -> 0 | O85: =M85+N85 -> 4.7762921e+09 | P85: =O85*$P$5 -> 4.7762921e+08 | Q85: =(O85-P85)*(1-$Q$3) -> 4.2771696e+09 | R85: =Q85*$R$5 -> 2.1385848e+09 | S85: =Q85-R85 -> 2.1385848e+09 | T85: =T84*99.9% -> 1.0169981e+10 | U85: =$U$3 -> 0.0026988781 | V85: =(S85/(T85*U85))/12 -> 6.4929467
A86: Year 78 | B86: 2102 | C86: =C85*(1-$C$5) -> 3.0250189e-05 | D86: =C86 -> 3.0250189e-05 | F86: 500 | G86: =D86*F86*1000000000 -> 15125095 | H86: =G86*(1-$H$3) -> 15049469 | I86: =100% -> 1 | J86: =(H86*I86)+E86 -> 15049469 | K86: =K85+J86+P85 -> 7.7990854e+10 | L86: =(L85+J86+P85)*(1-$L$3) -> 7.6243941e+10 | M86: =L85*$M$3 -> 4.8050482e+09 | N86: =H86*(1-I86) -> 0 | O86: =M86+N86 -> 4.8050482e+09 | P86: =O86*$P$5 -> 4.8050482e+08 | Q86: =(O86-P86)*(1-$Q$3) -> 4.3029207e+09 | R86: =Q86*$R$5 -> 2.1514603e+09 | S86: =Q86-R86 -> 2.1514603e+09 | T86: =T85*99.9% -> 1.0159811e+10 | U86: =$U$3 -> 0.0026988781 | V86: =(S86/(T86*U86))/12 -> 6.5385767
A87: Year 79 | B87: 2103 | C87: =C86*(1-$C$5) -> 2.722517e-05 | D87: =C87 -> 2.722517e-05 | F87: 500 | G87: =D87*F87*1000000000 -> 13612585 | H87: =G87*(1-$H$3) -> 13544522 | I87: =100% -> 1 | J87: =(H87*I87)+E87 -> 13544522 | K87: =K86+J87+P86 -> 7.8484904e+10 | L87: =(L86+J87+P86)*(1-$L$3) -> 7.6699622e+10 | M87: =L86*$M$3 -> 4.8338659e+09 | N87: =H87*(1-I87) -> 0 | O87: =M87+N87 -> 4.8338659e+09 | P87: =O87*$P$5 -> 4.8338659e+08 | Q87: =(O87-P87)*(1-$Q$3) -> 4.3287269e+09 | R87: =Q87*$R$5 -> 2.1643635e+09 | S87: =Q87-R87 -> 2.1643635e+09 | T87: =T86*99.9% -> 1.0149651e+10 | U87: =$U$3 -> 0.0026988781 | V87: =(S87/(T87*U87))/12 -> 6.5843754
A88: Year 80 | B88: 2104 | C88: =C87*(1-$C$5) -> 2.4502653e-05 | D88: =C88 -> 2.4502653e-05 | F88: 500 | G88: =D88*F88*1000000000 -> 12251327 | H88: =G88*(1-$H$3) -> 12190070 | I88: =100% -> 1 | J88: =(H88*I88)+E88 -> 12190070 | K88: =K87+J88+P87 -> 7.898048e+10 | L88: =(L87+J88+P87)*(1-$L$3) -> 7.7156601e+10 | M88: =L87*$M$3 -> 4.862756e+09 | N88: =H88*(1-I88) -> 0 | O88: =M88+N88 -> 4.862756e+09 | P88: =O88*$P$5 -> 4.862756e+08 | Q88: =(O88-P88)*(1-$Q$3) -> 4.354598e+09 | R88: =Q88*$R$5 -> 2.177299e+09 | S88: =Q88-R88 -> 2.177299e+09 | T88: =T87*99.9% -> 1.0139501e+10 | U88: =$U$3 -> 0.0026988781 | V88: =(S88/(T88*U88))/12 -> 6.630358
A89: Year 81 | B89: 2105 | C89: =C88*(1-$C$5) -> 2.2052388e-05 | D89: =C89 -> 2.2052388e-05 | F89: 500 | G89: =D89*F89*1000000000 -> 11026194 | H89: =G89*(1-$H$3) -> 10971063 | I89: =100% -> 1 | J89: =(H89*I89)+E89 -> 10971063 | K89: =K88+J89+P88 -> 7.9477727e+10 | L89: =(L88+J89+P88)*(1-$L$3) -> 7.7615021e+10 | M89: =L88*$M$3 -> 4.8917285e+09 | N89: =H89*(1-I89) -> 0 | O89: =M89+N89 -> 4.8917285e+09 | P89: =O89*$P$5 -> 4.8917285e+08 | Q89: =(O89-P89)*(1-$Q$3) -> 4.3805429e+09 | R89: =Q89*$R$5 -> 2.1902714e+09 | S89: =Q89-R89 -> 2.1902714e+09 | T89: =T88*99.9% -> 1.0129362e+10 | U89: =$U$3 -> 0.0026988781 | V89: =(S89/(T89*U89))/12 -> 6.6765384
A90: Year 82 | B90: 2106 | C90: =C89*(1-$C$5) -> 1.9847149e-05 | D90: =C90 -> 1.9847149e-05 | F90: 500 | G90: =D90*F90*1000000000 -> 9923574.5 | H90: =G90*(1-$H$3) -> 9873956.7 | I90: =100% -> 1 | J90: =(H90*I90)+E90 -> 9873956.7 | K90: =K89+J90+P89 -> 7.9976774e+10 | L90: =(L89+J90+P89)*(1-$L$3) -> 7.807501e+10 | M90: =L89*$M$3 -> 4.9207923e+09 | N90: =H90*(1-I90) -> 0 | O90: =M90+N90 -> 4.9207923e+09 | P90: =O90*$P$5 -> 4.9207923e+08 | Q90: =(O90-P90)*(1-$Q$3) -> 4.4065695e+09 | R90: =Q90*$R$5 -> 2.2032848e+09 | S90: =Q90-R90 -> 2.2032848e+09 | T90: =T89*99.9% -> 1.0119232e+10 | U90: =$U$3 -> 0.0026988781 | V90: =(S90/(T90*U90))/12 -> 6.7229294
A91: Year 83 | B91: 2107 | C91: =C90*(1-$C$5) -> 1.7862434e-05 | D91: =C91 -> 1.7862434e-05 | F91: 500 | G91: =D91*F91*1000000000 -> 8931217.1 | H91: =G91*(1-$H$3) -> 8886561 | I91: =100% -> 1 | J91: =(H91*I91)+E91 -> 8886561 | K91: =K90+J91+P90 -> 8.047774e+10 | L91: =(L90+J91+P90)*(1-$L$3) -> 7.8536688e+10 | M91: =L90*$M$3 -> 4.9499557e+09 | N91: =H91*(1-I91) -> 0 | O91: =M91+N91 -> 4.9499557e+09 | P91: =O91*$P$5 -> 4.9499557e+08 | Q91: =(O91-P91)*(1-$Q$3) -> 4.4326853e+09 | R91: =Q91*$R$5 -> 2.2163426e+09 | S91: =Q91-R91 -> 2.2163426e+09 | T91: =T90*99.9% -> 1.0109113e+10 | U91: =$U$3 -> 0.0026988781 | V91: =(S91/(T91*U91))/12 -> 6.7695428
A92: Year 84 | B92: 2108 | C92: =C91*(1-$C$5) -> 1.6076191e-05 | D92: =C92 -> 1.6076191e-05 | F92: 500 | G92: =D92*F92*1000000000 -> 8038095.4 | H92: =G92*(1-$H$3) -> 7997904.9 | I92: =100% -> 1 | J92: =(H92*I92)+E92 -> 7997904.9 | K92: =K91+J92+P91 -> 8.0980733e+10 | L92: =(L91+J92+P91)*(1-$L$3) -> 7.9000162e+10 | M92: =L91*$M$3 -> 4.979226e+09 | N92: =H92*(1-I92) -> 0 | O92: =M92+N92 -> 4.979226e+09 | P92: =O92*$P$5 -> 4.979226e+08 | Q92: =(O92-P92)*(1-$Q$3) -> 4.4588969e+09 | R92: =Q92*$R$5 -> 2.2294485e+09 | S92: =Q92-R92 -> 2.2294485e+09 | T92: =T91*99.9% -> 1.0099004e+10 | U92: =$U$3 -> 0.0026988781 | V92: =(S92/(T92*U92))/12 -> 6.8163893
A93: Year 85 | B93: 2109 | C93: =C92*(1-$C$5) -> 1.4468572e-05 | D93: =C93 -> 1.4468572e-05 | F93: 500 | G93: =D93*F93*1000000000 -> 7234285.8 | H93: =G93*(1-$H$3) -> 7198114.4 | I93: =100% -> 1 | J93: =(H93*I93)+E93 -> 7198114.4 | K93: =K92+J93+P92 -> 8.1485854e+10 | L93: =(L92+J93+P92)*(1-$L$3) -> 7.946553e+10 | M93: =L92*$M$3 -> 5.0086103e+09 | N93: =H93*(1-I93) -> 0 | O93: =M93+N93 -> 5.0086103e+09 | P93: =O93*$P$5 -> 5.0086103e+08 | Q93: =(O93-P93)*(1-$Q$3) -> 4.4852105e+09 | R93: =Q93*$R$5 -> 2.2426052e+09 | S93: =Q93-R93 -> 2.2426052e+09 | T93: =T92*99.9% -> 1.0088905e+10 | U93: =$U$3 -> 0.0026988781 | V93: =(S93/(T93*U93))/12 -> 6.8634787
A94: Year 86 | B94: 2110 | C94: =C93*(1-$C$5) -> 1.3021714e-05 | D94: =C94 -> 1.3021714e-05 | F94: 500 | G94: =D94*F94*1000000000 -> 6510857.2 | H94: =G94*(1-$H$3) -> 6478303 | I94: =100% -> 1 | J94: =(H94*I94)+E94 -> 6478303 | K94: =K93+J94+P93 -> 8.1993193e+10 | L94: =(L93+J94+P93)*(1-$L$3) -> 7.9932883e+10 | M94: =L93*$M$3 -> 5.0381146e+09 | N94: =H94*(1-I94) -> 0 | O94: =M94+N94 -> 5.0381146e+09 | P94: =O94*$P$5 -> 5.0381146e+08 | Q94: =(O94-P94)*(1-$Q$3) -> 4.5116316e+09 | R94: =Q94*$R$5 -> 2.2558158e+09 | S94: =Q94-R94 -> 2.2558158e+09 | T94: =T93*99.9% -> 1.0078816e+10 | U94: =$U$3 -> 0.0026988781 | V94: =(S94/(T94*U94))/12 -> 6.9108204
